Workbook

Sheet Main Data
A1: Transaction ID | B1: Date | C1: Sales Rep | D1: Branch Code | E1: Region | F1: Product | G1: Lead Source | H1: Customer Segment | I1: Customer Age | J1: Account Tenure Months | K1: Revenue | L1: Processing Fee | M1: Discount Applied | N1: Target Achieved | O1: CSAT Score
A2: TRX-10000 | B2: 46088 | C2: Jamie | D2: BR-006 | E2: East | F2: Wealth Management | G2: Walk-in | H2: Retail | I2: 74 | J2: 16 | K2: 25114.07 | L2: 350.3 | M2: 179.26 | N2: No | O2: 4
A3: TRX-10001 | B3: 46007 | C3: Morgan | D3: BR-015 | E3: South | F3: Personal Loan | G3: Website | H3: High Net Worth | I3: 28 | J3: 28 | K3: 9331.6 | L3: 106.51 | M3: 121.35 | N3: Yes | O3: 5
A4: TRX-10002 | B4: 45886 | C4: Casey | D4: BR-001 | E4: East | F4: Auto Loan | G4: Social Media | H4: High Net Worth | I4: 44 | J4: 112 | K4: 5853.67 | L4: 394.49 | M4: 136.7 | N4: Yes | O4: 5
A5: TRX-10003 | B5: 46015 | C5: Jamie | D5: BR-009 | E5: Central | F5: Mortgage | G5: Website | H5: Retail | I5: 35 | J5: 35 | K5: 42184.29 | L5: 144.59 | M5: 141.15 | N5: Yes | O5: 5
A6: TRX-10004 | B6: 45980 | C6: Taylor | D6: BR-001 | E6: South | F6: Auto Loan | G6: Website | H6: High Net Worth | I6: 63 | J6: 60 | K6: 30899.59 | L6: 195.55 | M6: 246.26 | N6: No | O6: 1
A7: TRX-10005 | B7: 46170 | C7: Drew | D7: BR-005 | E7: West | F7: Mortgage | G7: Walk-in | H7: High Net Worth | I7: 51 | J7: 45 | K7: 16628.32 | L7: 418.66 | M7: 70.9 | N7: No | O7: 5
A8: TRX-10006 | B8: 46132 | C8: Casey | D8: BR-004 | E8: East | F8: Mortgage | G8: Website | H8: Retail | I8: 29 | J8: 46 | K8: 9990.94 | L8: 291.44 | M8: 132.27 | N8: Yes | O8: 4
A9: TRX-10007 | B9: 46226 | C9: Casey | D9: BR-013 | E9: South | F9: Auto Loan | G9: Walk-in | H9: Retail | I9: 59 | J9: 72 | K9: 27997.12 | L9: 436.97 | M9: 78.4 | N9: Yes | O9: 2
A10: TRX-10008 | B10: 46066 | C10: Jamie | D10: BR-012 | E10: East | F10: Mortgage | G10: Social Media | H10: Corporate | I10: 65 | J10: 108 | K10: 29404 | L10: 145.87 | M10: 73.74 | N10: No | O10: 5
A11: TRX-10009 | B11: 46230 | C11: Jordan | D11: BR-013 | E11: South | F11: Mortgage | G11: Email Campaign | H11: SME | I11: 22 | J11: 55 | K11: 10746.18 | L11: 323.5 | M11: 138.01 | N11: Yes | O11: 2
A12: TRX-10010 | B12: 45945 | C12: Taylor | D12: BR-013 | E12: North | F12: Personal Loan | G12: Walk-in | H12: SME | I12: 28 | J12: 119 | K12: 42644.58 | L12: 87.71 | M12: 77.44 | N12: Yes | O12: 4
A13: TRX-10011 | B13: 46203 | C13: Jamie | D13: BR-014 | E13: East | F13: Wealth Management | G13: Social Media | H13: Retail | I13: 27 | J13: 86 | K13: 4671.09 | L13: 339.38 | M13: 69.22 | N13: Yes | O13: 5
... A1001: TRX-10999 | B1001: 46151 | C1001: Taylor | D1001: BR-009 | E1001: West | F1001: Credit Card | G1001: Website | H1001: Corporate | I1001: 42 | J1001: 6 | K1001: 40998.21 | L1001: 121.83 | M1001: 111.97 | N1001: Yes | O1001: 4

Sheet Double lookup
A1: DOUBLE VLOOKUP
A3: Transaction ID | B3: Branch Code | C3: Date | D3: Sales Rep | E3: Region | F3: Product | G3: Lead Source | H3: Customer Segment | I3: Customer Age | J3: Account Tenure Months | K3: Revenue | L3: Processing Fee | M3: Discount Applied | N3: Target Achieved | O3: CSAT Score
A4: TRX-10000 | B4: =VLOOKUP($A$4,A7:B1007,2,0) -> BR-006 | C4: {=VLOOKUP(VLOOKUP($A$4,A7:B1007,2,0),$E$7:$R$1007,{2,3,4,5,6,7,8,9,10,11,12,13,14},0)} -> 46088 | D4: Jamie | E4: East | F4: Wealth Management | G4: Walk-in | H4: Retail | I4: 74 | J4: 16 | K4: 25114.07 | L4: 350.3 | M4: 179.26 | N4: No | O4: 4
A7: Transaction ID | B7: Branch Code | E7: Branch Code | F7: Date | G7: Sales Rep | H7: Region | I7: Product | J7: Lead Source | K7: Customer Segment | L7: Customer Age | M7: Account Tenure Months | N7: Revenue | O7: Processing Fee | P7: Discount Applied | Q7: Target Achieved | R7: CSAT Score
A8: TRX-10000 | B8: BR-006 | E8: BR-006 | F8: 46088 | G8: Jamie | H8: East | I8: Wealth Management | J8: Walk-in | K8: Retail | L8: 74 | M8: 16 | N8: 25114.07 | O8: 350.3 | P8: 179.26 | Q8: No | R8: 4
A9: TRX-10001 | B9: BR-015 | E9: BR-015 | F9: 46007 | G9: Morgan | H9: South | I9: Personal Loan | J9: Website | K9: High Net Worth | L9: 28 | M9: 28 | N9: 9331.6 | O9: 106.51 | P9: 121.35 | Q9: Yes | R9: 5
A10: TRX-10002 | B10: BR-001 | E10: BR-001 | F10: 45886 | G10: Casey | H10: East | I10: Auto Loan | J10: Social Media | K10: High Net Worth | L10: 44 | M10: 112 | N10: 5853.67 | O10: 394.49 | P10: 136.7 | Q10: Yes | R10: 5
A11: TRX-10003 | B11: BR-009 | E11: BR-009 | F11: 46015 | G11: Jamie | H11: Central | I11: Mortgage | J11: Website | K11: Retail | L11: 35 | M11: 35 | N11: 42184.29 | O11: 144.59 | P11: 141.15 | Q11: Yes | R11: 5
A12: TRX-10004 | B12: BR-001 | E12: BR-001 | F12: 45980 | G12: Taylor | H12: South | I12: Auto Loan | J12: Website | K12: High Net Worth | L12: 63 | M12: 60 | N12: 30899.59 | O12: 195.55 | P12: 246.26 | Q12: No | R12: 1
A13: TRX-10005 | B13: BR-005 | E13: BR-005 | F13: 46170 | G13: Drew | H13: West | I13: Mortgage | J13: Walk-in | K13: High Net Worth | L13: 51 | M13: 45 | N13: 16628.32 | O13: 418.66 | P13: 70.9 | Q13: No | R13: 5
A14: TRX-10006 | B14: BR-004 | E14: BR-004 | F14: 46132 | G14: Casey | H14: East | I14: Mortgage | J14: Website | K14: Retail | L14: 29 | M14: 46 | N14: 9990.94 | O14: 291.44 | P14: 132.27 | Q14: Yes | R14: 4
A15: TRX-10007 | B15: BR-013 | E15: BR-013 | F15: 46226 | G15: Casey | H15: South | I15: Auto Loan | J15: Walk-in | K15: Retail | L15: 59 | M15: 72 | N15: 27997.12 | O15: 436.97 | P15: 78.4 | Q15: Yes | R15: 2
A16: TRX-10008 | B16: BR-012 | E16: BR-012 | F16: 46066 | G16: Jamie | H16: East | I16: Mortgage | J16: Social Media | K16: Corporate | L16: 65 | M16: 108 | N16: 29404 | O16: 145.87 | P16: 73.74 | Q16: No | R16: 5
A17: TRX-10009 | B17: BR-013 | E17: BR-013 | F17: 46230 | G17: Jordan | H17: South | I17: Mortgage | J17: Email Campaign | K17: SME | L17: 22 | M17: 55 | N17: 10746.18 | O17: 323.5 | P17: 138.01 | Q17: Yes | R17: 2
A18: TRX-10010 | B18: BR-013 | E18: BR-013 | F18: 45945 | G18: Taylor | H18: North | I18: Personal Loan | J18: Walk-in | K18: SME | L18: 28 | M18: 119 | N18: 42644.58 | O18: 87.71 | P18: 77.44 | Q18: Yes | R18: 4
A19: TRX-10011 | B19: BR-014 | E19: BR-014 | F19: 46203 | G19: Jamie | H19: East | I19: Wealth Management | J19: Social Media | K19: Retail | L19: 27 | M19: 86 | N19: 4671.09 | O19: 339.38 | P19: 69.22 | Q19: Yes | R19: 5
... A1007: TRX-10999 | B1007: BR-009 | E1007: BR-009 | F1007: 46151 | G1007: Taylor | H1007: West | I1007: Credit Card | J1007: Website | K1007: Corporate | L1007: 42 | M1007: 6 | N1007: 40998.21 | O1007: 121.83 | P1007: 111.97 | Q1007: Yes | R1007: 4

Sheet Dynamic Lookup Function
A1: DYNAMIC TWO WAY GRID SEARCH
A3: Transaction ID | B3: Branch Code | C3: Date | D3: Sales Rep | E3: Region | F3: Product | G3: Lead Source | H3: Customer Segment | I3: Customer Age | J3: Account Tenure Months | K3: Revenue | L3: Processing Fee | M3: Discount Applied | N3: Target Achieved | O3: CSAT Score | Q3: Branch Code
A4: TRX-10000 | B4: BR-006 | C4: 46088 | D4: Jamie | E4: East | F4: Wealth Management | G4: Walk-in | H4: Retail | I4: 74 | J4: 16 | K4: 25114.07 | L4: 350.3 | M4: 179.26 | N4: No | O4: 4
A5: TRX-10001 | B5: BR-015 | C5: 46007 | D5: Morgan | E5: South | F5: Personal Loan | G5: Website | H5: High Net Worth | I5: 28 | J5: 28 | K5: 9331.6 | L5: 106.51 | M5: 121.35 | N5: Yes | O5: 5 | Q5: BR-006
A6: TRX-10002 | B6: BR-001 | C6: 45886 | D6: Casey | E6: East | F6: Auto Loan | G6: Social Media | H6: High Net Worth | I6: 44 | J6: 112 | K6: 5853.67 | L6: 394.49 | M6: 136.7 | N6: Yes | O6: 5
A7: TRX-10003 | B7: BR-009 | C7: 46015 | D7: Jamie | E7: Central | F7: Mortgage | G7: Website | H7: Retail | I7: 35 | J7: 35 | K7: 42184.29 | L7: 144.59 | M7: 141.15 | N7: Yes | O7: 5 | Q7: Sales Rep | R7: Region | S7: Product | T7: Lead Source | U7: Customer Segment | V7: Account Tenure Months | W7: Revenue
A8: TRX-10004 | B8: BR-001 | C8: 45980 | D8: Taylor | E8: South | F8: Auto Loan | G8: Website | H8: High Net Worth | I8: 63 | J8: 60 | K8: 30899.59 | L8: 195.55 | M8: 246.26 | N8: No | O8: 1 | Q8: {=IFERROR(VLOOKUP(Q5,$A$3:$O$1003,{4,5,6,7,8,10,11},0),VLOOKUP(Q5,$B$3:$O$1003,{3,4,5,6,7,9,10},0))} -> Jamie | R8: East | S8: Wealth Management | T8: Walk-in | U8: Retail | V8: 16 | W8: 25114.07
A9: TRX-10005 | B9: BR-005 | C9: 46170 | D9: Drew | E9: West | F9: Mortgage | G9: Walk-in | H9: High Net Worth | I9: 51 | J9: 45 | K9: 16628.32 | L9: 418.66 | M9: 70.9 | N9: No | O9: 5
A10: TRX-10006 | B10: BR-004 | C10: 46132 | D10: Casey | E10: East | F10: Mortgage | G10: Website | H10: Retail | I10: 29 | J10: 46 | K10: 9990.94 | L10: 291.44 | M10: 132.27 | N10: Yes | O10: 4
A11: TRX-10007 | B11: BR-013 | C11: 46226 | D11: Casey | E11: South | F11: Auto Loan | G11: Walk-in | H11: Retail | I11: 59 | J11: 72 | K11: 27997.12 | L11: 436.97 | M11: 78.4 | N11: Yes | O11: 2
A12: TRX-10008 | B12: BR-012 | C12: 46066 | D12: Jamie | E12: East | F12: Mortgage | G12: Social Media | H12: Corporate | I12: 65 | J12: 108 | K12: 29404 | L12: 145.87 | M12: 73.74 | N12: No | O12: 5
A13: TRX-10009 | B13: BR-013 | C13: 46230 | D13: Jordan | E13: South | F13: Mortgage | G13: Email Campaign | H13: SME | I13: 22 | J13: 55 | K13: 10746.18 | L13: 323.5 | M13: 138.01 | N13: Yes | O13: 2
A14: TRX-10010 | B14: BR-013 | C14: 45945 | D14: Taylor | E14: North | F14: Personal Loan | G14: Walk-in | H14: SME | I14: 28 | J14: 119 | K14: 42644.58 | L14: 87.71 | M14: 77.44 | N14: Yes | O14: 4
A15: TRX-10011 | B15: BR-014 | C15: 46203 | D15: Jamie | E15: East | F15: Wealth Management | G15: Social Media | H15: Retail | I15: 27 | J15: 86 | K15: 4671.09 | L15: 339.38 | M15: 69.22 | N15: Yes | O15: 5
A16: TRX-10012 | B16: BR-003 | C16: 46076 | D16: Taylor | E16: West | F16: Wealth Management | G16: Email Campaign | H16: Retail | I16: 64 | J16: 85 | K16: 18126.61 | L16: 393.14 | M16: 167.18 | N16: No | O16: 1
A17: TRX-10013 | B17: BR-013 | C17: 45927 | D17: Taylor | E17: West | F17: Personal Loan | G17: Referral | H17: High Net Worth | I17: 71 | J17: 26 | K17: 34179.03 | L17: 313.22 | M17: 30.39 | N17: Yes | O17: 1
A18: TRX-10014 | B18: BR-006 | C18: 46137 | D18: Drew | E18: Central | F18: Auto Loan | G18: Walk-in | H18: Corporate | I18: 59 | J18: 104 | K18: 14068.96 | L18: 169.8 | M18: 135.18 | N18: No | O18: 2
A19: TRX-10015 | B19: BR-002 | C19: 46208 | D19: Casey | E19: South | F19: Credit Card | G19: Walk-in | H19: Corporate | I19: 62 | J19: 85 | K19: 41469.92 | L19: 64.1 | M19: 49.75 | N19: Yes | O19: 1
A20: TRX-10016 | B20: BR-003 | C20: 46029 | D20: Morgan | E20: East | F20: Credit Card | G20: Referral | H20: Retail | I20: 36 | J20: 25 | K20: 37123.46 | L20: 103.75 | M20: 3.1 | N20: No | O20: 1
... A1003: TRX-10999 | B1003: BR-009 | C1003: 46151 | D1003: Taylor | E1003: West | F1003: Credit Card | G1003: Website | H1003: Corporate | I1003: 42 | J1003: 6 | K1003: 40998.21 | L1003: 121.83 | M1003: 111.97 | N1003: Yes | O1003: 4

Sheet Vlookup
A1: VLOOKUP
A5: Transaction ID | B5: Date | C5: Sales Rep | D5: Branch Code | E5: Region | F5: Product | G5: Lead Source | H5: Customer Segment | I5: Customer Age | J5: Account Tenure Months | K5: Revenue | L5: Processing Fee | M5: Discount Applied | N5: Target Achieved | O5: CSAT Score
A6: TRX-10000 | B6: {=VLOOKUP($A$6,'Main Data'!A1:O1001,{2,3,4,5,6,7,8,9,10,11,12,13,14,15},0)} -> 46088 | C6: Jamie | D6: BR-006 | E6: East | F6: Wealth Management | G6: Walk-in | H6: Retail | I6: 74 | J6: 16 | K6: 25114.07 | L6: 350.3 | M6: 179.26 | N6: No | O6: 4

Sheet Hlookup
A1: Transaction ID | B1: TRX-10000 | C1: TRX-10001 | D1: TRX-10002 | E1: TRX-10003 | F1: TRX-10004 | G1: TRX-10005 | H1: TRX-10006 | I1: TRX-10007 | J1: TRX-10008 | K1: TRX-10009 | L1: TRX-10010 | M1: TRX-10011 | N1: TRX-10012 | O1: TRX-10013 | P1: TRX-10014 | Q1: TRX-10015 | R1: TRX-10016 | S1: TRX-10017 | T1: TRX-10018 | U1: TRX-10019 | V1: TRX-10020 | W1: TRX-10021 | X1: TRX-10022 | Y1: TRX-10023 | Z1: TRX-10024 | AA1: TRX-10025 | AB1: TRX-10026 | AC1: TRX-10027 | AD1: TRX-10028 | AE1: TRX-10029 | AF1: TRX-10030 | AG1: TRX-10031 | AH1: TRX-10032 | AI1: TRX-10033 | AJ1: TRX-10034 | AK1: TRX-10035 | AL1: TRX-10036 | AM1: TRX-10037 | AN1: TRX-10038 | AO1: TRX-10039 | AP1: TRX-10040 | AQ1: TRX-10041 | AR1: TRX-10042 | AS1: TRX-10043 | AT1: TRX-10044 | AU1: TRX-10045 | AV1: TRX-10046 | AW1: TRX-10047 | AX1: TRX-10048 | AY1: TRX-10049 | AZ1: TRX-10050 | BA1: TRX-10051 | BB1: TRX-10052 | BC1: TRX-10053 | BD1: TRX-10054 | BE1: TRX-10055 | BF1: TRX-10056 | BG1: TRX-10057 | BH1: TRX-10058 | BI1: TRX-10059 | BJ1: TRX-10060 | BK1: TRX-10061 | BL1: TRX-10062 | BM1: TRX-10063 | BN1: TRX-10064 | BO1: TRX-10065 | BP1: TRX-10066 | BQ1: TRX-10067 | BR1: TRX-10068 | BS1: TRX-10069 | BT1: TRX-10070 | BU1: TRX-10071 | BV1: TRX-10072 | BW1: TRX-10073 | BX1: TRX-10074 | BY1: TRX-10075 | BZ1: TRX-10076 | CA1: TRX-10077 | CB1: TRX-10078 | CC1: TRX-10079 | CD1: TRX-10080 | CE1: TRX-10081 | CF1: TRX-10082 | CG1: TRX-10083 | CH1: TRX-10084 | CI1: TRX-10085 | CJ1: TRX-10086 | CK1: TRX-10087 | CL1: TRX-10088 | CM1: TRX-10089 | CN1: TRX-10090 | CO1: TRX-10091 | CP1: TRX-10092 | CQ1: TRX-10093 | CR1: TRX-10094 | CS1: TRX-10095 | CT1: TRX-10096 | CU1: TRX-10097 | CV1: TRX-10098 | CW1: TRX-10099 | CX1: TRX-10100 | CY1: TRX-10101 | CZ1: TRX-10102 | DA1: TRX-10103 | DB1: TRX-10104 | DC1: TRX-10105 | DD1: TRX-10106 | DE1: TRX-10107 | DF1: TRX-10108 | DG1: TRX-10109 | DH1: TRX-10110 | DI1: TRX-10111 | DJ1: TRX-10112 | DK1: TRX-10113 | DL1: TRX-10114 | DM1: TRX-10115 | DN1: TRX-10116 | DO1: TRX-10117 | DP1: TRX-10118 | DQ1: TRX-10119 | DR1: TRX-10120 | DS1: TRX-10121 | DT1: TRX-10122 | DU1: TRX-10123 | DV1: TRX-10124 | DW1: TRX-10125 | DX1: TRX-10126 | DY1: TRX-10127 | DZ1: TRX-10128 | EA1: TRX-10129 | EB1: TRX-10130 | EC1: TRX-10131 | ED1: TRX-10132 | EE1: TRX-10133 | EF1: TRX-10134 | EG1: TRX-10135 | EH1: TRX-10136 | EI1: TRX-10137 | EJ1: TRX-10138 | EK1: TRX-10139 | EL1: TRX-10140 | EM1: TRX-10141 | EN1: TRX-10142 | EO1: TRX-10143 | EP1: TRX-10144 | EQ1: TRX-10145 | ER1: TRX-10146 | ES1: TRX-10147 | ET1: TRX-10148 | EU1: TRX-10149 | EV1: TRX-10150 | EW1: TRX-10151 | EX1: TRX-10152 | EY1: TRX-10153 | EZ1: TRX-10154 | FA1: TRX-10155 | FB1: TRX-10156 | FC1: TRX-10157 | FD1: TRX-10158 | FE1: TRX-10159 | FF1: TRX-10160 | FG1: TRX-10161 | FH1: TRX-10162 | FI1: TRX-10163 | FJ1: TRX-10164 | FK1: TRX-10165 | FL1: TRX-10166 | FM1: TRX-10167 | FN1: TRX-10168 | FO1: TRX-10169 | FP1: TRX-10170 | FQ1: TRX-10171 | FR1: TRX-10172 | FS1: TRX-10173 | FT1: TRX-10174 | FU1: TRX-10175 | FV1: TRX-10176 | FW1: TRX-10177 | FX1: TRX-10178 | FY1: TRX-10179 | FZ1: TRX-10180 | GA1: TRX-10181 | GB1: TRX-10182 | GC1: TRX-10183 | GD1: TRX-10184 | GE1: TRX-10185 | GF1: TRX-10186 | GG1: TRX-10187 | GH1: TRX-10188 | GI1: TRX-10189 | GJ1: TRX-10190 | GK1: TRX-10191 | GL1: TRX-10192 | GM1: TRX-10193 | GN1: TRX-10194 | GO1: TRX-10195 | GP1: TRX-10196 | GQ1: TRX-10197 | GR1: TRX-10198 | GS1: TRX-10199 | GT1: TRX-10200 | GU1: TRX-10201 | GV1: TRX-10202 | GW1: TRX-10203 | GX1: TRX-10204 | GY1: TRX-10205 | GZ1: TRX-10206 | HA1: TRX-10207 | HB1: TRX-10208 | HC1: TRX-10209 | HD1: TRX-10210 | HE1: TRX-10211 | HF1: TRX-10212 | HG1: TRX-10213 | HH1: TRX-10214 | HI1: TRX-10215 | HJ1: TRX-10216 | HK1: TRX-10217 | HL1: TRX-10218 | HM1: TRX-10219 | HN1: TRX-10220 | HO1: TRX-10221 | HP1: TRX-10222 | HQ1: TRX-10223 | HR1: TRX-10224 | HS1: TRX-10225 | HT1: TRX-10226 | HU1: TRX-10227 | HV1: TRX-10228 | HW1: TRX-10229 | HX1: TRX-10230 | HY1: TRX-10231 | HZ1: TRX-10232 | IA1: TRX-10233 | IB1: TRX-10234 | IC1: TRX-10235 | ID1: TRX-10236 | IE1: TRX-10237 | IF1: TRX-10238 | IG1: TRX-10239 | IH1: TRX-10240 | II1: TRX-10241 | IJ1: TRX-10242 | IK1: TRX-10243 | IL1: TRX-10244 | IM1: TRX-10245 | IN1: TRX-10246 | IO1: TRX-10247 | IP1: TRX-10248 | IQ1: TRX-10249 | IR1: TRX-10250 | IS1: TRX-10251 | IT1: TRX-10252 | IU1: TRX-10253 | IV1: TRX-10254 | IW1: TRX-10255 | IX1: TRX-10256 | IY1: TRX-10257 | IZ1: TRX-10258 | JA1: TRX-10259 | JB1: TRX-10260 | JC1: TRX-10261 | JD1: TRX-10262 | JE1: TRX-10263 | JF1: TRX-10264 | JG1: TRX-10265 | JH1: TRX-10266 | JI1: TRX-10267 | JJ1: TRX-10268 | JK1: TRX-10269 | JL1: TRX-10270 | JM1: TRX-10271 | JN1: TRX-10272 | JO1: TRX-10273 | JP1: TRX-10274 | JQ1: TRX-10275 | JR1: TRX-10276 | JS1: TRX-10277 | JT1: TRX-10278 | JU1: TRX-10279 | JV1: TRX-10280 | JW1: TRX-10281 | JX1: TRX-10282 | JY1: TRX-10283 | JZ1: TRX-10284 | KA1: TRX-10285 | KB1: TRX-10286 | KC1: TRX-10287 | KD1: TRX-10288 | KE1: TRX-10289 | KF1: TRX-10290 | KG1: TRX-10291 | KH1: TRX-10292 | KI1: TRX-10293 | KJ1: TRX-10294 | KK1: TRX-10295 | KL1: TRX-10296 | KM1: TRX-10297 | KN1: TRX-10298 | KO1: TRX-10299 | KP1: TRX-10300 | KQ1: TRX-10301 | KR1: TRX-10302 | KS1: TRX-10303 | KT1: TRX-10304 | KU1: TRX-10305 | KV1: TRX-10306 | KW1: TRX-10307 | KX1: TRX-10308 | KY1: TRX-10309 | KZ1: TRX-10310 | LA1: TRX-10311 | LB1: TRX-10312 | LC1: TRX-10313 | LD1: TRX-10314 | LE1: TRX-10315 | LF1: TRX-10316 | LG1: TRX-10317 | LH1: TRX-10318 | LI1: TRX-10319 | LJ1: TRX-10320 | LK1: TRX-10321 | LL1: TRX-10322 | LM1: TRX-10323 | LN1: TRX-10324 | LO1: TRX-10325 | LP1: TRX-10326 | LQ1: TRX-10327 | LR1: TRX-10328 | LS1: TRX-10329 | LT1: TRX-10330 | LU1: TRX-10331 | LV1: TRX-10332 | LW1: TRX-10333 | LX1: TRX-10334 | LY1: TRX-10335 | LZ1: TRX-10336 | MA1: TRX-10337 | MB1: TRX-10338 | MC1: TRX-10339 | MD1: TRX-10340 | ME1: TRX-10341 | MF1: TRX-10342 | MG1: TRX-10343 | MH1: TRX-10344 | MI1: TRX-10345 | MJ1: TRX-10346 | MK1: TRX-10347 | ML1: TRX-10348 | MM1: TRX-10349 | MN1: TRX-10350 | MO1: TRX-10351 | MP1: TRX-10352 | MQ1: TRX-10353 | MR1: TRX-10354 | MS1: TRX-10355 | MT1: TRX-10356 | MU1: TRX-10357 | MV1: TRX-10358 | MW1: TRX-10359 | MX1: TRX-10360 | MY1: TRX-10361 | MZ1: TRX-10362 | NA1: TRX-10363 | NB1: TRX-10364 | NC1: TRX-10365 | ND1: TRX-10366 | NE1: TRX-10367 | NF1: TRX-10368 | NG1: TRX-10369 | NH1: TRX-10370 | NI1: TRX-10371 | NJ1: TRX-10372 | NK1: TRX-10373 | NL1: TRX-10374 | NM1: TRX-10375 | NN1: TRX-10376 | NO1: TRX-10377 | NP1: TRX-10378 | NQ1: TRX-10379 | NR1: TRX-10380 | NS1: TRX-10381 | NT1: TRX-10382 | NU1: TRX-10383 | NV1: TRX-10384 | NW1: TRX-10385 | NX1: TRX-10386 | NY1: TRX-10387 | NZ1: TRX-10388 | OA1: TRX-10389 | OB1: TRX-10390 | OC1: TRX-10391 | OD1: TRX-10392 | OE1: TRX-10393 | OF1: TRX-10394 | OG1: TRX-10395 | OH1: TRX-10396 | OI1: TRX-10397 | OJ1: TRX-10398 | OK1: TRX-10399 | OL1: TRX-10400 | OM1: TRX-10401 | ON1: TRX-10402 | OO1: TRX-10403 | OP1: TRX-10404 | OQ1: TRX-10405 | OR1: TRX-10406 | OS1: TRX-10407 | OT1: TRX-10408 | OU1: TRX-10409 | OV1: TRX-10410 | OW1: TRX-10411 | OX1: TRX-10412 | OY1: TRX-10413 | OZ1: TRX-10414 | PA1: TRX-10415 | PB1: TRX-10416 | PC1: TRX-10417 | PD1: TRX-10418 | PE1: TRX-10419 | PF1: TRX-10420 | PG1: TRX-10421 | PH1: TRX-10422 | PI1: TRX-10423 | PJ1: TRX-10424 | PK1: TRX-10425 | PL1: TRX-10426 | PM1: TRX-10427 | PN1: TRX-10428 | PO1: TRX-10429 | PP1: TRX-10430 | PQ1: TRX-10431 | PR1: TRX-10432 | PS1: TRX-10433 | PT1: TRX-10434 | PU1: TRX-10435 | PV1: TRX-10436 | PW1: TRX-10437 | PX1: TRX-10438 | PY1: TRX-10439 | PZ1: TRX-10440 | QA1: TRX-10441 | QB1: TRX-10442 | QC1: TRX-10443 | QD1: TRX-10444 | QE1: TRX-10445 | QF1: TRX-10446 | QG1: TRX-10447 | QH1: TRX-10448 | QI1: TRX-10449 | QJ1: TRX-10450 | QK1: TRX-10451 | QL1: TRX-10452 | QM1: TRX-10453 | QN1: TRX-10454 | QO1: TRX-10455 | QP1: TRX-10456 | QQ1: TRX-10457 | QR1: TRX-10458 | QS1: TRX-10459 | QT1: TRX-10460 | QU1: TRX-10461 | QV1: TRX-10462 | QW1: TRX-10463 | QX1: TRX-10464 | QY1: TRX-10465 | QZ1: TRX-10466 | RA1: TRX-10467 | RB1: TRX-10468 | RC1: TRX-10469 | RD1: TRX-10470 | RE1: TRX-10471 | RF1: TRX-10472 | RG1: TRX-10473 | RH1: TRX-10474 | RI1: TRX-10475 | RJ1: TRX-10476 | RK1: TRX-10477 | RL1: TRX-10478 | RM1: TRX-10479 | RN1: TRX-10480 | RO1: TRX-10481 | RP1: TRX-10482 | RQ1: TRX-10483 | RR1: TRX-10484 | RS1: TRX-10485 | RT1: TRX-10486 | RU1: TRX-10487 | RV1: TRX-10488 | RW1: TRX-10489 | RX1: TRX-10490 | RY1: TRX-10491 | RZ1: TRX-10492 | SA1: TRX-10493 | SB1: TRX-10494 | SC1: TRX-10495 | SD1: TRX-10496 | SE1: TRX-10497 | SF1: TRX-10498 | SG1: TRX-10499 | SH1: TRX-10500 | SI1: TRX-10501 | SJ1: TRX-10502 | SK1: TRX-10503 | SL1: TRX-10504 | SM1: TRX-10505 | SN1: TRX-10506 | SO1: TRX-10507 | SP1: TRX-10508 | SQ1: TRX-10509 | SR1: TRX-10510 | SS1: TRX-10511 | ST1: TRX-10512 | SU1: TRX-10513 | SV1: TRX-10514 | SW1: TRX-10515 | SX1: TRX-10516 | SY1: TRX-10517 | SZ1: TRX-10518 | TA1: TRX-10519 | TB1: TRX-10520 | TC1: TRX-10521 | TD1: TRX-10522 | TE1: TRX-10523 | TF1: TRX-10524 | TG1: TRX-10525 | TH1: TRX-10526 | TI1: TRX-10527 | TJ1: TRX-10528 | TK1: TRX-10529 | TL1: TRX-10530 | TM1: TRX-10531 | TN1: TRX-10532 | TO1: TRX-10533 | TP1: TRX-10534 | TQ1: TRX-10535 | TR1: TRX-10536 | TS1: TRX-10537 | TT1: TRX-10538 | TU1: TRX-10539 | TV1: TRX-10540 | TW1: TRX-10541 | TX1: TRX-10542 | TY1: TRX-10543 | TZ1: TRX-10544 | UA1: TRX-10545 | UB1: TRX-10546 | UC1: TRX-10547 | UD1: TRX-10548 | UE1: TRX-10549 | UF1: TRX-10550 | UG1: TRX-10551 | UH1: TRX-10552 | UI1: TRX-10553 | UJ1: TRX-10554 | UK1: TRX-10555 | UL1: TRX-10556 | UM1: TRX-10557 | UN1: TRX-10558 | UO1: TRX-10559 | UP1: TRX-10560 | UQ1: TRX-10561 | UR1: TRX-10562 | US1: TRX-10563 | UT1: TRX-10564 | UU1: TRX-10565 | UV1: TRX-10566 | UW1: TRX-10567 | UX1: TRX-10568 | UY1: TRX-10569 | UZ1: TRX-10570 | VA1: TRX-10571 | VB1: TRX-10572 | VC1: TRX-10573 | VD1: TRX-10574 | VE1: TRX-10575 | VF1: TRX-10576 | VG1: TRX-10577 | VH1: TRX-10578 | VI1: TRX-10579 | VJ1: TRX-10580 | VK1: TRX-10581 | VL1: TRX-10582 | VM1: TRX-10583 | VN1: TRX-10584 | VO1: TRX-10585 | VP1: TRX-10586 | VQ1: TRX-10587 | VR1: TRX-10588 | VS1: TRX-10589 | VT1: TRX-10590 | VU1: TRX-10591 | VV1: TRX-10592 | VW1: TRX-10593 | VX1: TRX-10594 | VY1: TRX-10595 | VZ1: TRX-10596 | WA1: TRX-10597 | WB1: TRX-10598 | WC1: TRX-10599 | WD1: TRX-10600 | WE1: TRX-10601 | WF1: TRX-10602 | WG1: TRX-10603 | WH1: TRX-10604 | WI1: TRX-10605 | WJ1: TRX-10606 | WK1: TRX-10607 | WL1: TRX-10608 | WM1: TRX-10609 | WN1: TRX-10610 | WO1: TRX-10611 | WP1: TRX-10612 | WQ1: TRX-10613 | WR1: TRX-10614 | WS1: TRX-10615 | WT1: TRX-10616 | WU1: TRX-10617 | WV1: TRX-10618 | WW1: TRX-10619 | WX1: TRX-10620 | WY1: TRX-10621 | WZ1: TRX-10622 | XA1: TRX-10623 | XB1: TRX-10624 | XC1: TRX-10625 | XD1: TRX-10626 | XE1: TRX-10627 | XF1: TRX-10628 | XG1: TRX-10629 | XH1: TRX-10630 | XI1: TRX-10631 | XJ1: TRX-10632 | XK1: TRX-10633 | XL1: TRX-10634 | XM1: TRX-10635 | XN1: TRX-10636 | XO1: TRX-10637 | XP1: TRX-10638 | XQ1: TRX-10639 | XR1: TRX-10640 | XS1: TRX-10641 | XT1: TRX-10642 | XU1: TRX-10643 | XV1: TRX-10644 | XW1: TRX-10645 | XX1: TRX-10646 | XY1: TRX-10647 | XZ1: TRX-10648 | YA1: TRX-10649 | YB1: TRX-10650 | YC1: TRX-10651 | YD1: TRX-10652 | YE1: TRX-10653 | YF1: TRX-10654 | YG1: TRX-10655 | YH1: TRX-10656 | YI1: TRX-10657 | YJ1: TRX-10658 | YK1: TRX-10659 | YL1: TRX-10660 | YM1: TRX-10661 | YN1: TRX-10662 | YO1: TRX-10663 | YP1: TRX-10664 | YQ1: TRX-10665 | YR1: TRX-10666 | YS1: TRX-10667 | YT1: TRX-10668 | YU1: TRX-10669 | YV1: TRX-10670 | YW1: TRX-10671 | YX1: TRX-10672 | YY1: TRX-10673 | YZ1: TRX-10674 | ZA1: TRX-10675 | ZB1: TRX-10676 | ZC1: TRX-10677 | ZD1: TRX-10678 | ZE1: TRX-10679 | ZF1: TRX-10680 | ZG1: TRX-10681 | ZH1: TRX-10682 | ZI1: TRX-10683 | ZJ1: TRX-10684 | ZK1: TRX-10685 | ZL1: TRX-10686 | ZM1: TRX-10687 | ZN1: TRX-10688 | ZO1: TRX-10689 | ZP1: TRX-10690 | ZQ1: TRX-10691 | ZR1: TRX-10692 | ZS1: TRX-10693 | ZT1: TRX-10694 | ZU1: TRX-10695 | ZV1: TRX-10696 | ZW1: TRX-10697 | ZX1: TRX-10698 | ZY1: TRX-10699 | ZZ1: TRX-10700 | AAA1: TRX-10701 | AAB1: TRX-10702 | AAC1: TRX-10703 | AAD1: TRX-10704 | AAE1: TRX-10705 | AAF1: TRX-10706 | AAG1: TRX-10707 | AAH1: TRX-10708 | AAI1: TRX-10709 | AAJ1: TRX-10710 | AAK1: TRX-10711 | AAL1: TRX-10712 | AAM1: TRX-10713 | AAN1: TRX-10714 | AAO1: TRX-10715 | AAP1: TRX-10716 | AAQ1: TRX-10717 | AAR1: TRX-10718 | AAS1: TRX-10719 | AAT1: TRX-10720 | AAU1: TRX-10721 | AAV1: TRX-10722 | AAW1: TRX-10723 | AAX1: TRX-10724 | AAY1: TRX-10725 | AAZ1: TRX-10726 | ABA1: TRX-10727 | ABB1: TRX-10728 | ABC1: TRX-10729 | ABD1: TRX-10730 | ABE1: TRX-10731 | ABF1: TRX-10732 | ABG1: TRX-10733 | ABH1: TRX-10734 | ABI1: TRX-10735 | ABJ1: TRX-10736 | ABK1: TRX-10737 | ABL1: TRX-10738 | ABM1: TRX-10739 | ABN1: TRX-10740 | ABO1: TRX-10741 | ABP1: TRX-10742 | ABQ1: TRX-10743 | ABR1: TRX-10744 | ABS1: TRX-10745 | ABT1: TRX-10746 | ABU1: TRX-10747 | ABV1: TRX-10748 | ABW1: TRX-10749 | ABX1: TRX-10750 | ABY1: TRX-10751 | ABZ1: TRX-10752 | ACA1: TRX-10753 | ACB1: TRX-10754 | ACC1: TRX-10755 | ACD1: TRX-10756 | ACE1: TRX-10757 | ACF1: TRX-10758 | ACG1: TRX-10759 | ACH1: TRX-10760 | ACI1: TRX-10761 | ACJ1: TRX-10762 | ACK1: TRX-10763 | ACL1: TRX-10764 | ACM1: TRX-10765 | ACN1: TRX-10766 | ACO1: TRX-10767 | ACP1: TRX-10768 | ACQ1: TRX-10769 | ACR1: TRX-10770 | ACS1: TRX-10771 | ACT1: TRX-10772 | ACU1: TRX-10773 | ACV1: TRX-10774 | ACW1: TRX-10775 | ACX1: TRX-10776 | ACY1: TRX-10777 | ACZ1: TRX-10778 | ADA1: TRX-10779 | ADB1: TRX-10780 | ADC1: TRX-10781 | ADD1: TRX-10782 | ADE1: TRX-10783 | ADF1: TRX-10784 | ADG1: TRX-10785 | ADH1: TRX-10786 | ADI1: TRX-10787 | ADJ1: TRX-10788 | ADK1: TRX-10789 | ADL1: TRX-10790 | ADM1: TRX-10791 | ADN1: TRX-10792 | ADO1: TRX-10793 | ADP1: TRX-10794 | ADQ1: TRX-10795 | ADR1: TRX-10796 | ADS1: TRX-10797 | ADT1: TRX-10798 | ADU1: TRX-10799 | ADV1: TRX-10800 | ADW1: TRX-10801 | ADX1: TRX-10802 | ADY1: TRX-10803 | ADZ1: TRX-10804 | AEA1: TRX-10805 | AEB1: TRX-10806 | AEC1: TRX-10807 | AED1: TRX-10808 | AEE1: TRX-10809 | AEF1: TRX-10810 | AEG1: TRX-10811 | AEH1: TRX-10812 | AEI1: TRX-10813 | AEJ1: TRX-10814 | AEK1: TRX-10815 | AEL1: TRX-10816 | AEM1: TRX-10817 | AEN1: TRX-10818 | AEO1: TRX-10819 | AEP1: TRX-10820 | AEQ1: TRX-10821 | AER1: TRX-10822 | AES1: TRX-10823 | AET1: TRX-10824 | AEU1: TRX-10825 | AEV1: TRX-10826 | AEW1: TRX-10827 | AEX1: TRX-10828 | AEY1: TRX-10829 | AEZ1: TRX-10830 | AFA1: TRX-10831 | AFB1: TRX-10832 | AFC1: TRX-10833 | AFD1: TRX-10834 | AFE1: TRX-10835 | AFF1: TRX-10836 | AFG1: TRX-10837 | AFH1: TRX-10838 | AFI1: TRX-10839 | AFJ1: TRX-10840 | AFK1: TRX-10841 | AFL1: TRX-10842 | AFM1: TRX-10843 | AFN1: TRX-10844 | AFO1: TRX-10845 | AFP1: TRX-10846 | AFQ1: TRX-10847 | AFR1: TRX-10848 | AFS1: TRX-10849 | AFT1: TRX-10850 | AFU1: TRX-10851 | AFV1: TRX-10852 | AFW1: TRX-10853 | AFX1: TRX-10854 | AFY1: TRX-10855 | AFZ1: TRX-10856 | AGA1: TRX-10857 | AGB1: TRX-10858 | AGC1: TRX-10859 | AGD1: TRX-10860 | AGE1: TRX-10861 | AGF1: TRX-10862 | AGG1: TRX-10863 | AGH1: TRX-10864 | AGI1: TRX-10865 | AGJ1: TRX-10866 | AGK1: TRX-10867 | AGL1: TRX-10868 | AGM1: TRX-10869 | AGN1: TRX-10870 | AGO1: TRX-10871 | AGP1: TRX-10872 | AGQ1: TRX-10873 | AGR1: TRX-10874 | AGS1: TRX-10875 | AGT1: TRX-10876 | AGU1: TRX-10877 | AGV1: TRX-10878 | AGW1: TRX-10879 | AGX1: TRX-10880 | AGY1: TRX-10881 | AGZ1: TRX-10882 | AHA1: TRX-10883 | AHB1: TRX-10884 | AHC1: TRX-10885 | AHD1: TRX-10886 | AHE1: TRX-10887 | AHF1: TRX-10888 | AHG1: TRX-10889 | AHH1: TRX-10890 | AHI1: TRX-10891 | AHJ1: TRX-10892 | AHK1: TRX-10893 | AHL1: TRX-10894 | AHM1: TRX-10895 | AHN1: TRX-10896 | AHO1: TRX-10897 | AHP1: TRX-10898 | AHQ1: TRX-10899 | AHR1: TRX-10900 | AHS1: TRX-10901 | AHT1: TRX-10902 | AHU1: TRX-10903 | AHV1: TRX-10904 | AHW1: TRX-10905 | AHX1: TRX-10906 | AHY1: TRX-10907 | AHZ1: TRX-10908 | AIA1: TRX-10909 | AIB1: TRX-10910 | AIC1: TRX-10911 | AID1: TRX-10912 | AIE1: TRX-10913 | AIF1: TRX-10914 | AIG1: TRX-10915 | AIH1: TRX-10916 | AII1: TRX-10917 | AIJ1: TRX-10918 | AIK1: TRX-10919 | AIL1: TRX-10920 | AIM1: TRX-10921 | AIN1: TRX-10922 | AIO1: TRX-10923 | AIP1: TRX-10924 | AIQ1: TRX-10925 | AIR1: TRX-10926 | AIS1: TRX-10927 | AIT1: TRX-10928 | AIU1: TRX-10929 | AIV1: TRX-10930 | AIW1: TRX-10931 | AIX1: TRX-10932 | AIY1: TRX-10933 | AIZ1: TRX-10934 | AJA1: TRX-10935 | AJB1: TRX-10936 | AJC1: TRX-10937 | AJD1: TRX-10938 | AJE1: TRX-10939 | AJF1: TRX-10940 | AJG1: TRX-10941 | AJH1: TRX-10942 | AJI1: TRX-10943 | AJJ1: TRX-10944 | AJK1: TRX-10945 | AJL1: TRX-10946 | AJM1: TRX-10947 | AJN1: TRX-10948 | AJO1: TRX-10949 | AJP1: TRX-10950 | AJQ1: TRX-10951 | AJR1: TRX-10952 | AJS1: TRX-10953 | AJT1: TRX-10954 | AJU1: TRX-10955 | AJV1: TRX-10956 | AJW1: TRX-10957 | AJX1: TRX-10958 | AJY1: TRX-10959 | AJZ1: TRX-10960 | AKA1: TRX-10961 | AKB1: TRX-10962 | AKC1: TRX-10963 | AKD1: TRX-10964 | AKE1: TRX-10965 | AKF1: TRX-10966 | AKG1: TRX-10967 | AKH1: TRX-10968 | AKI1: TRX-10969 | AKJ1: TRX-10970 | AKK1: TRX-10971 | AKL1: TRX-10972 | AKM1: TRX-10973 | AKN1: TRX-10974 | AKO1: TRX-10975 | AKP1: TRX-10976 | AKQ1: TRX-10977 | AKR1: TRX-10978 | AKS1: TRX-10979 | AKT1: TRX-10980 | AKU1: TRX-10981 | AKV1: TRX-10982 | AKW1: TRX-10983 | AKX1: TRX-10984 | AKY1: TRX-10985 | AKZ1: TRX-10986 | ALA1: TRX-10987 | ALB1: TRX-10988 | ALC1: TRX-10989 | ALD1: TRX-10990 | ALE1: TRX-10991 | ALF1: TRX-10992 | ALG1: TRX-10993 | ALH1: TRX-10994 | ALI1: TRX-10995 | ALJ1: TRX-10996 | ALK1: TRX-10997 | ALL1: TRX-10998 | ALM1: TRX-10999
A2: Date | B2: 46088 | C2: 46007 | D2: 45886 | E2: 46015 | F2: 45980 | G2: 46170 | H2: 46132 | I2: 46226 | J2: 46066 | K2: 46230 | L2: 45945 | M2: 46203 | N2: 46076 | O2: 45927 | P2: 46137 | Q2: 46208 | R2: 46029 | S2: 45988 | T2: 46166 | U2: 46012 | V2: 46174 | W2: 46172 | X2: 46175 | Y2: 46015 | Z2: 46124 | AA2: 46133 | AB2: 46209 | AC2: 45972 | AD2: 46204 | AE2: 46178 | AF2: 46012 | AG2: 46152 | AH2: 46105 | AI2: 46219 | AJ2: 45890 | AK2: 45974 | AL2: 45899 | AM2: 46221 | AN2: 45890 | AO2: 46134 | AP2: 46126 | AQ2: 46054 | AR2: 46025 | AS2: 46011 | AT2: 46101 | AU2: 46081 | AV2: 46054 | AW2: 46024 | AX2: 46000 | AY2: 46155 | AZ2: 45990 | BA2: 45914 | BB2: 46086 | BC2: 46149 | BD2: 45904 | BE2: 45942 | BF2: 45882 | BG2: 45871 | BH2: 46221 | BI2: 45941 | BJ2: 46214 | BK2: 46084 | BL2: 46225 | BM2: 45947 | BN2: 46042 | BO2: 46160 | BP2: 46096 | BQ2: 46000 | BR2: 46107 | BS2: 46089 | BT2: 46185 | BU2: 45922 | BV2: 46014 | BW2: 46090 | BX2: 45988 | BY2: 46079 | BZ2: 46142 | CA2: 45879 | CB2: 46147 | CC2: 46216 | CD2: 46153 | CE2: 46179 | CF2: 46224 | CG2: 46131 | CH2: 46072 | CI2: 46120 | CJ2: 46127 | CK2: 45953 | CL2: 46154 | CM2: 45958 | CN2: 45956 | CO2: 46148 | CP2: 46031 | CQ2: 46032 | CR2: 45919 | CS2: 46031 | CT2: 45971 | CU2: 46038 | CV2: 46056 | CW2: 45984 | CX2: 46136 | CY2: 46228 | CZ2: 46030 | DA2: 46049 | DB2: 46191 | DC2: 46005 | DD2: 45979 | DE2: 46067 | DF2: 45948 | DG2: 45971 | DH2: 45910 | DI2: 46133 | DJ2: 45995 | DK2: 45966 | DL2: 45950 | DM2: 45941 | DN2: 46192 | DO2: 45970 | DP2: 45994 | DQ2: 46002 | DR2: 46107 | DS2: 46012 | DT2: 46194 | DU2: 46208 | DV2: 45894 | DW2: 45911 | DX2: 46164 | DY2: 46042 | DZ2: 46149 | EA2: 45915 | EB2: 46123 | EC2: 45894 | ED2: 45917 | EE2: 45965 | EF2: 46064 | EG2: 45888 | EH2: 45903 | EI2: 45930 | EJ2: 46117 | EK2: 45944 | EL2: 46225 | EM2: 46055 | EN2: 46161 | EO2: 46064 | EP2: 46014 | EQ2: 46131 | ER2: 46132 | ES2: 45953 | ET2: 46076 | EU2: 46209 | EV2: 46040 | EW2: 46165 | EX2: 45929 | EY2: 45920 | EZ2: 46190 | FA2: 46043 | FB2: 45915 | FC2: 46031 | FD2: 46007 | FE2: 45957 | FF2: 45929 | FG2: 46186 | FH2: 46049 | FI2: 45887 | FJ2: 45980 | FK2: 46096 | FL2: 46025 | FM2: 46064 | FN2: 46015 | FO2: 45978 | FP2: 46165 | FQ2: 46231 | FR2: 45959 | FS2: 45918 | FT2: 45992 | FU2: 45902 | FV2: 46155 | FW2: 45957 | FX2: 46190 | FY2: 46065 | FZ2: 45956 | GA2: 45891 | GB2: 46165 | GC2: 46128 | GD2: 45950 | GE2: 46234 | GF2: 46219 | GG2: 46153 | GH2: 46197 | GI2: 45954 | GJ2: 45876 | GK2: 45975 | GL2: 46199 | GM2: 45953 | GN2: 46049 | GO2: 45948 | GP2: 46032 | GQ2: 46009 | GR2: 46052 | GS2: 46122 | GT2: 45961 | GU2: 46190 | GV2: 46129 | GW2: 46067 | GX2: 46135 | GY2: 45933 | GZ2: 45988 | HA2: 45895 | HB2: 46046 | HC2: 45946 | HD2: 45975 | HE2: 45998 | HF2: 46226 | HG2: 45947 | HH2: 46101 | HI2: 46084 | HJ2: 46156 | HK2: 46091 | HL2: 45998 | HM2: 46182 | HN2: 46025 | HO2: 45881 | HP2: 46214 | HQ2: 45955 | HR2: 46207 | HS2: 46109 | HT2: 46153 | HU2: 46090 | HV2: 46041 | HW2: 46101 | HX2: 46142 | HY2: 45913 | HZ2: 46224 | IA2: 45994 | IB2: 46168 | IC2: 46125 | ID2: 46042 | IE2: 46021 | IF2: 46101 | IG2: 46116 | IH2: 46211 | II2: 45925 | IJ2: 46063 | IK2: 46161 | IL2: 46188 | IM2: 46011 | IN2: 46182 | IO2: 45936 | IP2: 46090 | IQ2: 45898 | IR2: 46118 | IS2: 46192 | IT2: 46167 | IU2: 45931 | IV2: 45966 | IW2: 46131 | IX2: 46172 | IY2: 46122 | IZ2: 46081 | JA2: 46200 | JB2: 46112 | JC2: 46041 | JD2: 46012 | JE2: 45937 | JF2: 45898 | JG2: 45896 | JH2: 46026 | JI2: 45888 | JJ2: 46028 | JK2: 45980 | JL2: 45908 | JM2: 46150 | JN2: 45988 | JO2: 46041 | JP2: 46108 | JQ2: 46128 | JR2: 46111 | JS2: 45922 | JT2: 46019 | JU2: 45938 | JV2: 45949 | JW2: 45932 | JX2: 46115 | JY2: 45900 | JZ2: 46228 | KA2: 46097 | KB2: 46098 | KC2: 45944 | KD2: 46227 | KE2: 45927 | KF2: 46048 | KG2: 46063 | KH2: 46160 | KI2: 46107 | KJ2: 45957 | KK2: 45901 | KL2: 46000 | KM2: 45963 | KN2: 46001 | KO2: 46088 | KP2: 46215 | KQ2: 45890 | KR2: 46031 | KS2: 45983 | KT2: 46130 | KU2: 45876 | KV2: 45946 | KW2: 46024 | KX2: 46119 | KY2: 46226 | KZ2: 46230 | LA2: 46007 | LB2: 45963 | LC2: 46090 | LD2: 45950 | LE2: 46063 | LF2: 46026 | LG2: 45930 | LH2: 46151 | LI2: 45925 | LJ2: 46045 | LK2: 45970 | LL2: 46140 | LM2: 46135 | LN2: 46141 | LO2: 46166 | LP2: 46061 | LQ2: 46161 | LR2: 46089 | LS2: 46050 | LT2: 46124 | LU2: 45901 | LV2: 45917 | LW2: 46045 | LX2: 45905 | LY2: 46106 | LZ2: 46177 | MA2: 46140 | MB2: 45920 | MC2: 46212 | MD2: 46064 | ME2: 45913 | MF2: 45935 | MG2: 46206 | MH2: 45882 | MI2: 45999 | MJ2: 46010 | MK2: 45887 | ML2: 46203 | MM2: 46019 | MN2: 45931 | MO2: 45996 | MP2: 46139 | MQ2: 46144 | MR2: 46173 | MS2: 45914 | MT2: 46076 | MU2: 45979 | MV2: 45938 | MW2: 45981 | MX2: 45903 | MY2: 46145 | MZ2: 46109 | NA2: 46170 | NB2: 46068 | NC2: 46083 | ND2: 46161 | NE2: 45915 | NF2: 45954 | NG2: 46185 | NH2: 46055 | NI2: 46061 | NJ2: 45982 | NK2: 46121 | NL2: 45955 | NM2: 46110 | NN2: 46034 | NO2: 46025 | NP2: 46086 | NQ2: 46206 | NR2: 46082 | NS2: 46077 | NT2: 45929 | NU2: 46064 | NV2: 46200 | NW2: 46023 | NX2: 45879 | NY2: 46167 | NZ2: 46029 | OA2: 46138 | OB2: 46156 | OC2: 45989 | OD2: 45870 | OE2: 46144 | OF2: 46231 | OG2: 45958 | OH2: 46111 | OI2: 46219 | OJ2: 45913 | OK2: 46092 | OL2: 46163 | OM2: 46038 | ON2: 45919 | OO2: 46221 | OP2: 46130 | OQ2: 46107 | OR2: 46056 | OS2: 46161 | OT2: 46196 | OU2: 46092 | OV2: 46047 | OW2: 46165 | OX2: 46013 | OY2: 46116 | OZ2: 46152 | PA2: 45905 | PB2: 45907 | PC2: 45958 | PD2: 45894 | PE2: 45957 | PF2: 45999 | PG2: 45955 | PH2: 46218 | PI2: 46065 | PJ2: 45988 | PK2: 45876 | PL2: 46151 | PM2: 46133 | PN2: 46056 | PO2: 46081 | PP2: 46116 | PQ2: 45884 | PR2: 46109 | PS2: 46128 | PT2: 46052 | PU2: 46224 | PV2: 46008 | PW2: 46091 | PX2: 46144 | PY2: 46056 | PZ2: 45944 | QA2: 46231 | QB2: 46079 | QC2: 45944 | QD2: 46016 | QE2: 46126 | QF2: 46232 | QG2: 46225 | QH2: 46208 | QI2: 45983 | QJ2: 46024 | QK2: 46216 | QL2: 45983 | QM2: 46111 | QN2: 46003 | QO2: 46169 | QP2: 45957 | QQ2: 45933 | QR2: 46080 | QS2: 46086 | QT2: 45918 | QU2: 46180 | QV2: 46057 | QW2: 45943 | QX2: 45875 | QY2: 46165 | QZ2: 46206 | RA2: 46225 | RB2: 45896 | RC2: 45931 | RD2: 46194 | RE2: 46005 | RF2: 45889 | RG2: 46005 | RH2: 46052 | RI2: 46163 | RJ2: 46009 | RK2: 45923 | RL2: 46192 | RM2: 46153 | RN2: 45910 | RO2: 45902 | RP2: 45993 | RQ2: 45937 | RR2: 46118 | RS2: 46209 | RT2: 46183 | RU2: 45872 | RV2: 46185 | RW2: 46136 | RX2: 46110 | RY2: 46230 | RZ2: 46205 | SA2: 46210 | SB2: 46039 | SC2: 45951 | SD2: 45932 | SE2: 45953 | SF2: 46042 | SG2: 46234 | SH2: 46162 | SI2: 45911 | SJ2: 45960 | SK2: 45910 | SL2: 45925 | SM2: 46215 | SN2: 46084 | SO2: 46235 | SP2: 45939 | SQ2: 46024 | SR2: 46000 | SS2: 46139 | ST2: 46046 | SU2: 46184 | SV2: 46212 | SW2: 46053 | SX2: 46007 | SY2: 46062 | SZ2: 46130 | TA2: 45998 | TB2: 46174 | TC2: 46081 | TD2: 46092 | TE2: 46211 | TF2: 46078 | TG2: 46097 | TH2: 45912 | TI2: 46153 | TJ2: 46134 | TK2: 46009 | TL2: 46081 | TM2: 46230 | TN2: 46155 | TO2: 46069 | TP2: 46007 | TQ2: 46209 | TR2: 46107 | TS2: 46063 | TT2: 46090 | TU2: 45905 | TV2: 46019 | TW2: 45929 | TX2: 45905 | TY2: 45973 | TZ2: 46183 | UA2: 45921 | UB2: 45963 | UC2: 46095 | UD2: 46016 | UE2: 46233 | UF2: 45960 | UG2: 45875 | UH2: 45926 | UI2: 45879 | UJ2: 45890 | UK2: 46194 | UL2: 46012 | UM2: 46094 | UN2: 45979 | UO2: 46194 | UP2: 45986 | UQ2: 45972 | UR2: 45978 | US2: 45919 | UT2: 46226 | UU2: 46147 | UV2: 45911 | UW2: 46214 | UX2: 46203 | UY2: 46069 | UZ2: 46022 | VA2: 45971 | VB2: 46132 | VC2: 46195 | VD2: 45929 | VE2: 46107 | VF2: 45943 | VG2: 46205 | VH2: 46177 | VI2: 45998 | VJ2: 46038 | VK2: 46118 | VL2: 45874 | VM2: 46096 | VN2: 46227 | VO2: 46164 | VP2: 46121 | VQ2: 46120 | VR2: 45871 | VS2: 45932 | VT2: 46105 | VU2: 46120 | VV2: 45876 | VW2: 46058 | VX2: 46022 | VY2: 46196 | VZ2: 45924 | WA2: 45871 | WB2: 46041 | WC2: 45912 | WD2: 45896 | WE2: 46187 | WF2: 46098 | WG2: 45879 | WH2: 46060 | WI2: 46206 | WJ2: 46113 | WK2: 45870 | WL2: 46099 | WM2: 46013 | WN2: 46197 | WO2: 46196 | WP2: 46103 | WQ2: 46221 | WR2: 46167 | WS2: 46193 | WT2: 45976 | WU2: 46091 | WV2: 46130 | WW2: 46225 | WX2: 46151 | WY2: 46013 | WZ2: 46109 | XA2: 46113 | XB2: 45904 | XC2: 46029 | XD2: 46186 | XE2: 46185 | XF2: 45984 | XG2: 45994 | XH2: 46082 | XI2: 45919 | XJ2: 46021 | XK2: 46026 | XL2: 46156 | XM2: 46118 | XN2: 46136 | XO2: 46112 | XP2: 45953 | XQ2: 45924 | XR2: 45901 | XS2: 45964 | XT2: 45926 | XU2: 46220 | XV2: 46184 | XW2: 46067 | XX2: 45879 | XY2: 46121 | XZ2: 46075 | YA2: 46162 | YB2: 45962 | YC2: 45955 | YD2: 46187 | YE2: 45999 | YF2: 46164 | YG2: 46020 | YH2: 45936 | YI2: 45930 | YJ2: 46101 | YK2: 46185 | YL2: 46107 | YM2: 45920 | YN2: 45985 | YO2: 45908 | YP2: 46137 | YQ2: 45930 | YR2: 45921 | YS2: 45980 | YT2: 46067 | YU2: 45959 | YV2: 46162 | YW2: 46118 | YX2: 46119 | YY2: 46176 | YZ2: 45900 | ZA2: 46157 | ZB2: 45888 | ZC2: 46043 | ZD2: 46004 | ZE2: 46138 | ZF2: 46191 | ZG2: 45922 | ZH2: 46034 | ZI2: 45915 | ZJ2: 45955 | ZK2: 46043 | ZL2: 46221 | ZM2: 46208 | ZN2: 46140 | ZO2: 46220 | ZP2: 46077 | ZQ2: 46061 | ZR2: 46017 | ZS2: 46008 | ZT2: 46219 | ZU2: 46014 | ZV2: 46142 | ZW2: 45895 | ZX2: 45905 | ZY2: 45870 | ZZ2: 45986 | AAA2: 46205 | AAB2: 46161 | AAC2: 46216 | AAD2: 45887 | AAE2: 46188 | AAF2: 46198 | AAG2: 46114 | AAH2: 46099 | AAI2: 46118 | AAJ2: 46203 | AAK2: 46208 | AAL2: 46032 | AAM2: 46007 | AAN2: 46167 | AAO2: 45894 | AAP2: 46126 | AAQ2: 46211 | AAR2: 45902 | AAS2: 46073 | AAT2: 46146 | AAU2: 45990 | AAV2: 46215 | AAW2: 45981 | AAX2: 45925 | AAY2: 46088 | AAZ2: 46183 | ABA2: 46030 | ABB2: 45925 | ABC2: 45882 | ABD2: 45934 | ABE2: 45944 | ABF2: 45913 | ABG2: 46020 | ABH2: 46160 | ABI2: 45973 | ABJ2: 46025 | ABK2: 46172 | ABL2: 45946 | ABM2: 46034 | ABN2: 45922 | ABO2: 45933 | ABP2: 45979 | ABQ2: 46171 | ABR2: 45952 | ABS2: 46195 | ABT2: 45887 | ABU2: 46164 | ABV2: 46077 | ABW2: 46085 | ABX2: 46059 | ABY2: 46018 | ABZ2: 46185 | ACA2: 46231 | ACB2: 46211 | ACC2: 46208 | ACD2: 46180 | ACE2: 46217 | ACF2: 45976 | ACG2: 46209 | ACH2: 46164 | ACI2: 46121 | ACJ2: 45900 | ACK2: 45966 | ACL2: 45985 | ACM2: 45956 | ACN2: 46229 | ACO2: 46134 | ACP2: 46018 | ACQ2: 45999 | ACR2: 46035 | ACS2: 46181 | ACT2: 45892 | ACU2: 46099 | ACV2: 45973 | ACW2: 46181 | ACX2: 46219 | ACY2: 45910 | ACZ2: 45910 | ADA2: 46178 | ADB2: 46041 | ADC2: 46126 | ADD2: 46050 | ADE2: 46197 | ADF2: 45969 | ADG2: 45937 | ADH2: 46123 | ADI2: 46130 | ADJ2: 46186 | ADK2: 46123 | ADL2: 45912 | ADM2: 46064 | ADN2: 46149 | ADO2: 46061 | ADP2: 45978 | ADQ2: 46102 | ADR2: 45920 | ADS2: 46144 | ADT2: 46059 | ADU2: 46068 | ADV2: 45943 | ADW2: 45966 | ADX2: 46182 | ADY2: 45899 | ADZ2: 46173 | AEA2: 46058 | AEB2: 46215 | AEC2: 45972 | AED2: 45896 | AEE2: 46183 | AEF2: 46007 | AEG2: 46054 | AEH2: 45992 | AEI2: 45989 | AEJ2: 45928 | AEK2: 45896 | AEL2: 46007 | AEM2: 46068 | AEN2: 45926 | AEO2: 46068 | AEP2: 46073 | AEQ2: 46103 | AER2: 45905 | AES2: 45977 | AET2: 45968 | AEU2: 45947 | AEV2: 45920 | AEW2: 45870 | AEX2: 46165 | AEY2: 46211 | AEZ2: 45883 | AFA2: 45974 | AFB2: 46033 | AFC2: 46085 | AFD2: 45977 | AFE2: 46137 | AFF2: 45907 | AFG2: 46177 | AFH2: 46075 | AFI2: 46210 | AFJ2: 46037 | AFK2: 45994 | AFL2: 45959 | AFM2: 45965 | AFN2: 46006 | AFO2: 45961 | AFP2: 45888 | AFQ2: 46043 | AFR2: 46221 | AFS2: 45963 | AFT2: 46100 | AFU2: 46087 | AFV2: 45982 | AFW2: 46178 | AFX2: 46141 | AFY2: 46209 | AFZ2: 46006 | AGA2: 46186 | AGB2: 45909 | AGC2: 46093 | AGD2: 46030 | AGE2: 46083 | AGF2: 46135 | AGG2: 46135 | AGH2: 45928 | AGI2: 46120 | AGJ2: 46156 | AGK2: 46042 | AGL2: 46136 | AGM2: 46089 | AGN2: 46199 | AGO2: 46038 | AGP2: 46185 | AGQ2: 46012 | AGR2: 45976 | AGS2: 45895 | AGT2: 46099 | AGU2: 46131 | AGV2: 45904 | AGW2: 46088 | AGX2: 45920 | AGY2: 46197 | AGZ2: 45995 | AHA2: 46081 | AHB2: 46197 | AHC2: 45969 | AHD2: 45991 | AHE2: 45950 | AHF2: 46130 | AHG2: 46176 | AHH2: 46094 | AHI2: 46129 | AHJ2: 46093 | AHK2: 46067 | AHL2: 46131 | AHM2: 45942 | AHN2: 46098 | AHO2: 45875 | AHP2: 45874 | AHQ2: 45921 | AHR2: 46118 | AHS2: 46212 | AHT2: 45992 | AHU2: 46011 | AHV2: 46190 | AHW2: 46105 | AHX2: 45914 | AHY2: 45872 | AHZ2: 45917 | AIA2: 45989 | AIB2: 46119 | AIC2: 46005 | AID2: 46113 | AIE2: 45872 | AIF2: 46235 | AIG2: 46129 | AIH2: 45886 | AII2: 45871 | AIJ2: 45957 | AIK2: 46005 | AIL2: 46229 | AIM2: 46087 | AIN2: 46224 | AIO2: 46164 | AIP2: 46053 | AIQ2: 46017 | AIR2: 46235 | AIS2: 45891 | AIT2: 45915 | AIU2: 45940 | AIV2: 46138 | AIW2: 46185 | AIX2: 45914 | AIY2: 45992 | AIZ2: 46002 | AJA2: 46065 | AJB2: 46216 | AJC2: 46111 | AJD2: 45903 | AJE2: 46212 | AJF2: 46208 | AJG2: 45939 | AJH2: 46081 | AJI2: 46191 | AJJ2: 46203 | AJK2: 45920 | AJL2: 46148 | AJM2: 46163 | AJN2: 46122 | AJO2: 46065 | AJP2: 45896 | AJQ2: 46001 | AJR2: 46231 | AJS2: 46206 | AJT2: 46156 | AJU2: 45895 | AJV2: 45901 | AJW2: 45887 | AJX2: 46059 | AJY2: 46026 | AJZ2: 45922 | AKA2: 46121 | AKB2: 46089 | AKC2: 46203 | AKD2: 46064 | AKE2: 45876 | AKF2: 46076 | AKG2: 46138 | AKH2: 45889 | AKI2: 46112 | AKJ2: 45913 | AKK2: 46096 | AKL2: 46223 | AKM2: 46228 | AKN2: 46147 | AKO2: 46105 | AKP2: 46219 | AKQ2: 46003 | AKR2: 46092 | AKS2: 45973 | AKT2: 45957 | AKU2: 46086 | AKV2: 45968 | AKW2: 46055 | AKX2: 46235 | AKY2: 46187 | AKZ2: 45926 | ALA2: 46097 | ALB2: 46058 | ALC2: 45970 | ALD2: 45930 | ALE2: 46049 | ALF2: 46193 | ALG2: 46139 | ALH2: 46199 | ALI2: 46115 | ALJ2: 46064 | ALK2: 46157 | ALL2: 46226 | ALM2: 46151
A3: Sales Rep | B3: Jamie | C3: Morgan | D3: Casey | E3: Jamie | F3: Taylor | G3: Drew | H3: Casey | I3: Casey | J3: Jamie | K3: Jordan | L3: Taylor | M3: Jamie | N3: Taylor | O3: Taylor | P3: Drew | Q3: Casey | R3: Morgan | S3: Drew | T3: Drew | U3: Taylor | V3: Sam | W3: Casey | X3: Jordan | Y3: Drew | Z3: Morgan | AA3: Sam | AB3: Sam | AC3: Jordan | AD3: Drew | AE3: Morgan | AF3: Casey | AG3: Alex | AH3: Morgan | AI3: Jordan | AJ3: Sam | AK3: Casey | AL3: Morgan | AM3: Alex | AN3: Alex | AO3: Taylor | AP3: Taylor | AQ3: Jamie | AR3: Jordan | AS3: Drew | AT3: Morgan | AU3: Morgan | AV3: Drew | AW3: Jamie | AX3: Sam | AY3: Sam | AZ3: Jamie | BA3: Sam | BB3: Taylor | BC3: Morgan | BD3: Jamie | BE3: Morgan | BF3: Drew | BG3: Alex | BH3: Taylor | BI3: Casey | BJ3: Taylor | BK3: Jamie | BL3: Casey | BM3: Alex | BN3: Jamie | BO3: Jordan | BP3: Morgan | BQ3: Alex | BR3: Morgan | BS3: Sam | BT3: Jordan | BU3: Jordan | BV3: Alex | BW3: Jordan | BX3: Casey | BY3: Jordan | BZ3: Morgan | CA3: Morgan | CB3: Jamie | CC3: Morgan | CD3: Jamie | CE3: Morgan | CF3: Casey | CG3: Drew | CH3: Jamie | CI3: Taylor | CJ3: Sam | CK3: Alex | CL3: Morgan | CM3: Jordan | CN3: Drew | CO3: Morgan | CP3: Jordan | CQ3: Sam | CR3: Sam | CS3: Sam | CT3: Jordan | CU3: Morgan | CV3: Sam | CW3: Casey | CX3: Jamie | CY3: Jordan | CZ3: Jordan | DA3: Morgan | DB3: Jordan | DC3: Jordan | DD3: Sam | DE3: Morgan | DF3: Sam | DG3: Jamie | DH3: Drew | DI3: Jamie | DJ3: Drew | DK3: Sam | DL3: Jamie | DM3: Morgan | DN3: Alex | DO3: Sam | DP3: Drew | DQ3: Casey | DR3: Drew | DS3: Casey | DT3: Jordan | DU3: Jamie | DV3: Casey | DW3: Drew | DX3: Jordan | DY3: Alex | DZ3: Morgan | EA3: Morgan | EB3: Morgan | EC3: Casey | ED3: Alex | EE3: Casey | EF3: Jamie | EG3: Casey | EH3: Alex | EI3: Alex | EJ3: Jamie | EK3: Alex | EL3: Drew | EM3: Alex | EN3: Morgan | EO3: Drew | EP3: Drew | EQ3: Jamie | ER3: Taylor | ES3: Taylor | ET3: Alex | EU3: Drew | EV3: Taylor | EW3: Taylor | EX3: Alex | EY3: Taylor | EZ3: Casey | FA3: Jordan | FB3: Jamie | FC3: Jordan | FD3: Alex | FE3: Morgan | FF3: Jamie | FG3: Alex | FH3: Drew | FI3: Morgan | FJ3: Jordan | FK3: Alex | FL3: Drew | FM3: Jamie | FN3: Jamie | FO3: Sam | FP3: Drew | FQ3: Casey | FR3: Taylor | FS3: Morgan | FT3: Drew | FU3: Sam | FV3: Taylor | FW3: Taylor | FX3: Alex | FY3: Taylor | FZ3: Casey | GA3: Jamie | GB3: Sam | GC3: Taylor | GD3: Alex | GE3: Casey | GF3: Jordan | GG3: Jamie | GH3: Jamie | GI3: Sam | GJ3: Jamie | GK3: Taylor | GL3: Alex | GM3: Jamie | GN3: Jamie | GO3: Jordan | GP3: Jordan | GQ3: Morgan | GR3: Casey | GS3: Taylor | GT3: Jamie | GU3: Drew | GV3: Jamie | GW3: Alex | GX3: Morgan | GY3: Casey | GZ3: Drew | HA3: Morgan | HB3: Sam | HC3: Casey | HD3: Jamie | HE3: Jamie | HF3: Casey | HG3: Jamie | HH3: Taylor | HI3: Casey | HJ3: Morgan | HK3: Casey | HL3: Drew | HM3: Jamie | HN3: Taylor | HO3: Taylor | HP3: Sam | HQ3: Morgan | HR3: Jordan | HS3: Jordan | HT3: Casey | HU3: Sam | HV3: Alex | HW3: Casey | HX3: Sam | HY3: Morgan | HZ3: Morgan | IA3: Morgan | IB3: Morgan | IC3: Morgan | ID3: Sam | IE3: Sam | IF3: Taylor | IG3: Drew | IH3: Jordan | II3: Jamie | IJ3: Morgan | IK3: Alex | IL3: Jamie | IM3: Sam | IN3: Alex | IO3: Alex | IP3: Alex | IQ3: Taylor | IR3: Sam | IS3: Alex | IT3: Morgan | IU3: Casey | IV3: Alex | IW3: Taylor | IX3: Jamie | IY3: Sam | IZ3: Drew | JA3: Taylor | JB3: Alex | JC3: Sam | JD3: Casey | JE3: Alex | JF3: Taylor | JG3: Jordan | JH3: Morgan | JI3: Drew | JJ3: Jamie | JK3: Taylor | JL3: Sam | JM3: Drew | JN3: Drew | JO3: Drew | JP3: Alex | JQ3: Morgan | JR3: Alex | JS3: Sam | JT3: Alex | JU3: Jordan | JV3: Morgan | JW3: Morgan | JX3: Sam | JY3: Jamie | JZ3: Jordan | KA3: Taylor | KB3: Alex | KC3: Casey | KD3: Alex | KE3: Drew | KF3: Alex | KG3: Taylor | KH3: Alex | KI3: Jordan | KJ3: Jordan | KK3: Morgan | KL3: Sam | KM3: Jamie | KN3: Casey | KO3: Drew | KP3: Alex | KQ3: Alex | KR3: Taylor | KS3: Sam | KT3: Jordan | KU3: Casey | KV3: Morgan | KW3: Jordan | KX3: Drew | KY3: Sam | KZ3: Drew | LA3: Jamie | LB3: Morgan | LC3: Jamie | LD3: Taylor | LE3: Drew | LF3: Taylor | LG3: Alex | LH3: Jamie | LI3: Sam | LJ3: Drew | LK3: Casey | LL3: Morgan | LM3: Jordan | LN3: Sam | LO3: Sam | LP3: Taylor | LQ3: Jamie | LR3: Drew | LS3: Drew | LT3: Alex | LU3: Alex | LV3: Morgan | LW3: Taylor | LX3: Sam | LY3: Drew | LZ3: Casey | MA3: Taylor | MB3: Morgan | MC3: Morgan | MD3: Taylor | ME3: Morgan | MF3: Taylor | MG3: Jordan | MH3: Taylor | MI3: Jamie | MJ3: Taylor | MK3: Morgan | ML3: Drew | MM3: Jamie | MN3: Morgan | MO3: Alex | MP3: Alex | MQ3: Drew | MR3: Drew | MS3: Jamie | MT3: Jordan | MU3: Drew | MV3: Alex | MW3: Taylor | MX3: Morgan | MY3: Alex | MZ3: Alex | NA3: Jordan | NB3: Jamie | NC3: Jamie | ND3: Sam | NE3: Jordan | NF3: Taylor | NG3: Jamie | NH3: Morgan | NI3: Drew | NJ3: Jordan | NK3: Drew | NL3: Alex | NM3: Morgan | NN3: Morgan | NO3: Alex | NP3: Jordan | NQ3: Alex | NR3: Drew | NS3: Sam | NT3: Morgan | NU3: Casey | NV3: Casey | NW3: Drew | NX3: Taylor | NY3: Jamie | NZ3: Alex | OA3: Alex | OB3: Taylor | OC3: Taylor | OD3: Drew | OE3: Drew | OF3: Taylor | OG3: Morgan | OH3: Drew | OI3: Sam | OJ3: Drew | OK3: Alex | OL3: Drew | OM3: Morgan | ON3: Taylor | OO3: Alex | OP3: Drew | OQ3: Morgan | OR3: Sam | OS3: Drew | OT3: Morgan | OU3: Sam | OV3: Taylor | OW3: Drew | OX3: Sam | OY3: Alex | OZ3: Taylor | PA3: Alex | PB3: Casey | PC3: Jordan | PD3: Drew | PE3: Sam | PF3: Jordan | PG3: Jordan | PH3: Sam | PI3: Taylor | PJ3: Drew | PK3: Casey | PL3: Alex | PM3: Morgan | PN3: Alex | PO3: Morgan | PP3: Alex | PQ3: Sam | PR3: Casey | PS3: Drew | PT3: Morgan | PU3: Drew | PV3: Drew | PW3: Drew | PX3: Jamie | PY3: Taylor | PZ3: Alex | QA3: Drew | QB3: Alex | QC3: Drew | QD3: Morgan | QE3: Taylor | QF3: Taylor | QG3: Sam | QH3: Jamie | QI3: Sam | QJ3: Sam | QK3: Sam | QL3: Sam | QM3: Sam | QN3: Casey | QO3: Taylor | QP3: Sam | QQ3: Drew | QR3: Taylor | QS3: Taylor | QT3: Jordan | QU3: Casey | QV3: Sam | QW3: Alex | QX3: Morgan | QY3: Jamie | QZ3: Drew | RA3: Alex | RB3: Casey | RC3: Morgan | RD3: Casey | RE3: Drew | RF3: Taylor | RG3: Morgan | RH3: Taylor | RI3: Drew | RJ3: Alex | RK3: Drew | RL3: Alex | RM3: Morgan | RN3: Morgan | RO3: Sam | RP3: Casey | RQ3: Sam | RR3: Casey | RS3: Sam | RT3: Taylor | RU3: Morgan | RV3: Alex | RW3: Casey | RX3: Drew | RY3: Casey | RZ3: Alex | SA3: Sam | SB3: Casey | SC3: Jamie | SD3: Taylor | SE3: Morgan | SF3: Alex | SG3: Morgan | SH3: Jamie | SI3: Casey | SJ3: Casey | SK3: Drew | SL3: Jamie | SM3: Alex | SN3: Drew | SO3: Taylor | SP3: Drew | SQ3: Jordan | SR3: Alex | SS3: Jordan | ST3: Jamie | SU3: Sam | SV3: Jordan | SW3: Taylor | SX3: Drew | SY3: Sam | SZ3: Drew | TA3: Jordan | TB3: Drew | TC3: Jamie | TD3: Sam | TE3: Jamie | TF3: Jordan | TG3: Jamie | TH3: Taylor | TI3: Jordan | TJ3: Jordan | TK3: Jordan | TL3: Alex | TM3: Drew | TN3: Alex | TO3: Alex | TP3: Taylor | TQ3: Sam | TR3: Drew | TS3: Jamie | TT3: Casey | TU3: Jordan | TV3: Jamie | TW3: Jordan | TX3: Taylor | TY3: Jordan | TZ3: Alex | UA3: Drew | UB3: Casey | UC3: Morgan | UD3: Jordan | UE3: Jamie | UF3: Alex | UG3: Morgan | UH3: Casey | UI3: Morgan | UJ3: Alex | UK3: Drew | UL3: Drew | UM3: Sam | UN3: Drew | UO3: Sam | UP3: Morgan | UQ3: Taylor | UR3: Jamie | US3: Jamie | UT3: Morgan | UU3: Jordan | UV3: Jordan | UW3: Drew | UX3: Jamie | UY3: Jamie | UZ3: Sam | VA3: Taylor | VB3: Alex | VC3: Jordan | VD3: Jamie | VE3: Sam | VF3: Casey | VG3: Sam | VH3: Jordan | VI3: Jordan | VJ3: Sam | VK3: Alex | VL3: Morgan | VM3: Jordan | VN3: Sam | VO3: Jamie | VP3: Sam | VQ3: Taylor | VR3: Morgan | VS3: Casey | VT3: Alex | VU3: Drew | VV3: Casey | VW3: Morgan | VX3: Morgan | VY3: Morgan | VZ3: Casey | WA3: Jamie | WB3: Morgan | WC3: Sam | WD3: Casey | WE3: Drew | WF3: Morgan | WG3: Sam | WH3: Jamie | WI3: Taylor | WJ3: Jamie | WK3: Drew | WL3: Morgan | WM3: Drew | WN3: Casey | WO3: Jordan | WP3: Morgan | WQ3: Jordan | WR3: Sam | WS3: Taylor | WT3: Alex | WU3: Drew | WV3: Jamie | WW3: Taylor | WX3: Morgan | WY3: Jordan | WZ3: Jamie | XA3: Jordan | XB3: Casey | XC3: Jordan | XD3: Casey | XE3: Sam | XF3: Jamie | XG3: Jamie | XH3: Alex | XI3: Morgan | XJ3: Casey | XK3: Alex | XL3: Jordan | XM3: Jordan | XN3: Alex | XO3: Jamie | XP3: Jordan | XQ3: Drew | XR3: Sam | XS3: Sam | XT3: Drew | XU3: Alex | XV3: Drew | XW3: Casey | XX3: Casey | XY3: Alex | XZ3: Drew | YA3: Casey | YB3: Jamie | YC3: Drew | YD3: Jamie | YE3: Casey | YF3: Sam | YG3: Casey | YH3: Jamie | YI3: Taylor | YJ3: Morgan | YK3: Jordan | YL3: Drew | YM3: Taylor | YN3: Casey | YO3: Sam | YP3: Alex | YQ3: Casey | YR3: Sam | YS3: Morgan | YT3: Casey | YU3: Jamie | YV3: Alex | YW3: Sam | YX3: Sam | YY3: Sam | YZ3: Morgan | ZA3: Casey | ZB3: Morgan | ZC3: Drew | ZD3: Jordan | ZE3: Jordan | ZF3: Drew | ZG3: Casey | ZH3: Jamie | ZI3: Morgan | ZJ3: Alex | ZK3: Sam | ZL3: Sam | ZM3: Casey | ZN3: Jamie | ZO3: Jordan | ZP3: Jordan | ZQ3: Sam | ZR3: Casey | ZS3: Morgan | ZT3: Jordan | ZU3: Morgan | ZV3: Jamie | ZW3: Jordan | ZX3: Jordan | ZY3: Taylor | ZZ3: Jordan | AAA3: Drew | AAB3: Alex | AAC3: Drew | AAD3: Casey | AAE3: Casey | AAF3: Morgan | AAG3: Drew | AAH3: Drew | AAI3: Drew | AAJ3: Jamie | AAK3: Jordan | AAL3: Alex | AAM3: Morgan | AAN3: Drew | AAO3: Drew | AAP3: Taylor | AAQ3: Morgan | AAR3: Drew | AAS3: Morgan | AAT3: Jordan | AAU3: Taylor | AAV3: Morgan | AAW3: Alex | AAX3: Alex | AAY3: Casey | AAZ3: Taylor | ABA3: Taylor | ABB3: Casey | ABC3: Morgan | ABD3: Taylor | ABE3: Alex | ABF3: Alex | ABG3: Drew | ABH3: Jordan | ABI3: Taylor | ABJ3: Morgan | ABK3: Casey | ABL3: Casey | ABM3: Morgan | ABN3: Jamie | ABO3: Sam | ABP3: Jordan | ABQ3: Casey | ABR3: Taylor | ABS3: Jordan | ABT3: Taylor | ABU3: Jamie | ABV3: Alex | ABW3: Jordan | ABX3: Drew | ABY3: Casey | ABZ3: Jordan | ACA3: Jordan | ACB3: Jordan | ACC3: Sam | ACD3: Jordan | ACE3: Taylor | ACF3: Alex | ACG3: Jamie | ACH3: Morgan | ACI3: Jordan | ACJ3: Casey | ACK3: Jordan | ACL3: Casey | ACM3: Taylor | ACN3: Casey | ACO3: Drew | ACP3: Morgan | ACQ3: Alex | ACR3: Casey | ACS3: Casey | ACT3: Alex | ACU3: Morgan | ACV3: Jordan | ACW3: Casey | ACX3: Alex | ACY3: Drew | ACZ3: Drew | ADA3: Taylor | ADB3: Alex | ADC3: Taylor | ADD3: Drew | ADE3: Morgan | ADF3: Jordan | ADG3: Alex | ADH3: Jamie | ADI3: Drew | ADJ3: Drew | ADK3: Jamie | ADL3: Sam | ADM3: Drew | ADN3: Casey | ADO3: Morgan | ADP3: Alex | ADQ3: Jamie | ADR3: Casey | ADS3: Jamie | ADT3: Alex | ADU3: Taylor | ADV3: Alex | ADW3: Sam | ADX3: Alex | ADY3: Alex | ADZ3: Sam | AEA3: Morgan | AEB3: Drew | AEC3: Alex | AED3: Sam | AEE3: Casey | AEF3: Taylor | AEG3: Taylor | AEH3: Alex | AEI3: Morgan | AEJ3: Morgan | AEK3: Casey | AEL3: Alex | AEM3: Taylor | AEN3: Morgan | AEO3: Alex | AEP3: Jamie | AEQ3: Morgan | AER3: Sam | AES3: Jamie | AET3: Drew | AEU3: Morgan | AEV3: Taylor | AEW3: Jordan | AEX3: Jamie | AEY3: Drew | AEZ3: Casey | AFA3: Casey | AFB3: Taylor | AFC3: Morgan | AFD3: Alex | AFE3: Morgan | AFF3: Taylor | AFG3: Casey | AFH3: Morgan | AFI3: Casey | AFJ3: Jamie | AFK3: Drew | AFL3: Alex | AFM3: Jamie | AFN3: Casey | AFO3: Casey | AFP3: Jordan | AFQ3: Jordan | AFR3: Jamie | AFS3: Sam | AFT3: Jamie | AFU3: Jordan | AFV3: Casey | AFW3: Taylor | AFX3: Jamie | AFY3: Casey | AFZ3: Taylor | AGA3: Taylor | AGB3: Jordan | AGC3: Jamie | AGD3: Morgan | AGE3: Alex | AGF3: Jordan | AGG3: Jordan | AGH3: Morgan | AGI3: Alex | AGJ3: Casey | AGK3: Sam | AGL3: Jamie | AGM3: Sam | AGN3: Casey | AGO3: Drew | AGP3: Jordan | AGQ3: Alex | AGR3: Jordan | AGS3: Taylor | AGT3: Jordan | AGU3: Jordan | AGV3: Casey | AGW3: Casey | AGX3: Casey | AGY3: Sam | AGZ3: Taylor | AHA3: Drew | AHB3: Drew | AHC3: Casey | AHD3: Alex | AHE3: Sam | AHF3: Morgan | AHG3: Alex | AHH3: Jamie | AHI3: Jamie | AHJ3: Alex | AHK3: Casey | AHL3: Morgan | AHM3: Morgan | AHN3: Sam | AHO3: Morgan | AHP3: Jamie | AHQ3: Taylor | AHR3: Casey | AHS3: Morgan | AHT3: Sam | AHU3: Jamie | AHV3: Taylor | AHW3: Jordan | AHX3: Jordan | AHY3: Taylor | AHZ3: Jamie | AIA3: Sam | AIB3: Taylor | AIC3: Casey | AID3: Casey | AIE3: Jordan | AIF3: Morgan | AIG3: Sam | AIH3: Jordan | AII3: Morgan | AIJ3: Morgan | AIK3: Drew | AIL3: Casey | AIM3: Jamie | AIN3: Alex | AIO3: Jamie | AIP3: Alex | AIQ3: Taylor | AIR3: Casey | AIS3: Morgan | AIT3: Sam | AIU3: Alex | AIV3: Jamie | AIW3: Morgan | AIX3: Alex | AIY3: Alex | AIZ3: Drew | AJA3: Alex | AJB3: Sam | AJC3: Casey | AJD3: Sam | AJE3: Jordan | AJF3: Morgan | AJG3: Casey | AJH3: Drew | AJI3: Casey | AJJ3: Casey | AJK3: Jamie | AJL3: Casey | AJM3: Drew | AJN3: Sam | AJO3: Casey | AJP3: Taylor | AJQ3: Morgan | AJR3: Casey | AJS3: Morgan | AJT3: Taylor | AJU3: Taylor | AJV3: Morgan | AJW3: Alex | AJX3: Jordan | AJY3: Jamie | AJZ3: Alex | AKA3: Alex | AKB3: Sam | AKC3: Jamie | AKD3: Jamie | AKE3: Alex | AKF3: Casey | AKG3: Sam | AKH3: Sam | AKI3: Taylor | AKJ3: Drew | AKK3: Jamie | AKL3: Alex | AKM3: Taylor | AKN3: Morgan | AKO3: Jordan | AKP3: Drew | AKQ3: Drew | AKR3: Drew | AKS3: Sam | AKT3: Morgan | AKU3: Drew | AKV3: Morgan | AKW3: Casey | AKX3: Drew | AKY3: Jordan | AKZ3: Morgan | ALA3: Morgan | ALB3: Jordan | ALC3: Drew | ALD3: Jordan | ALE3: Morgan | ALF3: Jordan | ALG3: Morgan | ALH3: Morgan | ALI3: Casey | ALJ3: Alex | ALK3: Morgan | ALL3: Drew | ALM3: Taylor
A4: Branch Code | B4: BR-006 | C4: BR-015 | D4: BR-001 | E4: BR-009 | F4: BR-001 | G4: BR-005 | H4: BR-004 | I4: BR-013 | J4: BR-012 | K4: BR-013 | L4: BR-013 | M4: BR-014 | N4: BR-003 | O4: BR-013 | P4: BR-006 | Q4: BR-002 | R4: BR-003 | S4: BR-005 | T4: BR-015 | U4: BR-009 | V4: BR-002 | W4: BR-010 | X4: BR-008 | Y4: BR-014 | Z4: BR-002 | AA4: BR-011 | AB4: BR-013 | AC4: BR-005 | AD4: BR-007 | AE4: BR-008 | AF4: BR-001 | AG4: BR-006 | AH4: BR-001 | AI4: BR-002 | AJ4: BR-015 | AK4: BR-001 | AL4: BR-011 | AM4: BR-005 | AN4: BR-010 | AO4: BR-015 | AP4: BR-009 | AQ4: BR-006 | AR4: BR-011 | AS4: BR-011 | AT4: BR-001 | AU4: BR-013 | AV4: BR-001 | AW4: BR-002 | AX4: BR-009 | AY4: BR-003 | AZ4: BR-015 | BA4: BR-001 | BB4: BR-005 | BC4: BR-007 | BD4: BR-006 | BE4: BR-012 | BF4: BR-001 | BG4: BR-005 | BH4: BR-015 | BI4: BR-005 | BJ4: BR-006 | BK4: BR-003 | BL4: BR-005 | BM4: BR-007 | BN4: BR-005 | BO4: BR-005 | BP4: BR-005 | BQ4: BR-010 | BR4: BR-010 | BS4: BR-003 | BT4: BR-001 | BU4: BR-005 | BV4: BR-014 | BW4: BR-009 | BX4: BR-014 | BY4: BR-001 | BZ4: BR-003 | CA4: BR-013 | CB4: BR-013 | CC4: BR-004 | CD4: BR-014 | CE4: BR-001 | CF4: BR-001 | CG4: BR-008 | CH4: BR-002 | CI4: BR-012 | CJ4: BR-015 | CK4: BR-008 | CL4: BR-007 | CM4: BR-010 | CN4: BR-010 | CO4: BR-002 | CP4: BR-006 | CQ4: BR-006 | CR4: BR-003 | CS4: BR-011 | CT4: BR-002 | CU4: BR-012 | CV4: BR-001 | CW4: BR-006 | CX4: BR-012 | CY4: BR-005 | CZ4: BR-014 | DA4: BR-014 | DB4: BR-011 | DC4: BR-009 | DD4: BR-001 | DE4: BR-015 | DF4: BR-015 | DG4: BR-007 | DH4: BR-015 | DI4: BR-005 | DJ4: BR-005 | DK4: BR-014 | DL4: BR-002 | DM4: BR-011 | DN4: BR-003 | DO4: BR-007 | DP4: BR-006 | DQ4: BR-012 | DR4: BR-002 | DS4: BR-006 | DT4: BR-002 | DU4: BR-002 | DV4: BR-002 | DW4: BR-014 | DX4: BR-015 | DY4: BR-011 | DZ4: BR-003 | EA4: BR-015 | EB4: BR-002 | EC4: BR-004 | ED4: BR-009 | EE4: BR-006 | EF4: BR-001 | EG4: BR-008 | EH4: BR-015 | EI4: BR-012 | EJ4: BR-014 | EK4: BR-007 | EL4: BR-010 | EM4: BR-003 | EN4: BR-001 | EO4: BR-005 | EP4: BR-013 | EQ4: BR-004 | ER4: BR-010 | ES4: BR-008 | ET4: BR-001 | EU4: BR-010 | EV4: BR-001 | EW4: BR-012 | EX4: BR-004 | EY4: BR-008 | EZ4: BR-005 | FA4: BR-002 | FB4: BR-006 | FC4: BR-005 | FD4: BR-002 | FE4: BR-013 | FF4: BR-014 | FG4: BR-011 | FH4: BR-011 | FI4: BR-011 | FJ4: BR-003 | FK4: BR-015 | FL4: BR-009 | FM4: BR-007 | FN4: BR-007 | FO4: BR-015 | FP4: BR-011 | FQ4: BR-006 | FR4: BR-008 | FS4: BR-004 | FT4: BR-008 | FU4: BR-004 | FV4: BR-008 | FW4: BR-009 | FX4: BR-003 | FY4: BR-003 | FZ4: BR-011 | GA4: BR-013 | GB4: BR-002 | GC4: BR-013 | GD4: BR-010 | GE4: BR-003 | GF4: BR-003 | GG4: BR-005 | GH4: BR-005 | GI4: BR-002 | GJ4: BR-012 | GK4: BR-010 | GL4: BR-013 | GM4: BR-006 | GN4: BR-005 | GO4: BR-006 | GP4: BR-001 | GQ4: BR-005 | GR4: BR-009 | GS4: BR-012 | GT4: BR-010 | GU4: BR-014 | GV4: BR-002 | GW4: BR-001 | GX4: BR-014 | GY4: BR-010 | GZ4: BR-013 | HA4: BR-011 | HB4: BR-009 | HC4: BR-010 | HD4: BR-009 | HE4: BR-015 | HF4: BR-009 | HG4: BR-006 | HH4: BR-015 | HI4: BR-008 | HJ4: BR-014 | HK4: BR-011 | HL4: BR-015 | HM4: BR-013 | HN4: BR-001 | HO4: BR-010 | HP4: BR-004 | HQ4: BR-001 | HR4: BR-008 | HS4: BR-001 | HT4: BR-003 | HU4: BR-013 | HV4: BR-004 | HW4: BR-015 | HX4: BR-015 | HY4: BR-015 | HZ4: BR-008 | IA4: BR-006 | IB4: BR-014 | IC4: BR-010 | ID4: BR-012 | IE4: BR-007 | IF4: BR-014 | IG4: BR-008 | IH4: BR-002 | II4: BR-013 | IJ4: BR-010 | IK4: BR-014 | IL4: BR-011 | IM4: BR-008 | IN4: BR-003 | IO4: BR-007 | IP4: BR-003 | IQ4: BR-015 | IR4: BR-007 | IS4: BR-014 | IT4: BR-011 | IU4: BR-015 | IV4: BR-012 | IW4: BR-013 | IX4: BR-002 | IY4: BR-010 | IZ4: BR-006 | JA4: BR-003 | JB4: BR-003 | JC4: BR-015 | JD4: BR-009 | JE4: BR-007 | JF4: BR-005 | JG4: BR-012 | JH4: BR-010 | JI4: BR-007 | JJ4: BR-009 | JK4: BR-001 | JL4: BR-007 | JM4: BR-006 | JN4: BR-010 | JO4: BR-014 | JP4: BR-012 | JQ4: BR-009 | JR4: BR-001 | JS4: BR-013 | JT4: BR-004 | JU4: BR-009 | JV4: BR-004 | JW4: BR-010 | JX4: BR-003 | JY4: BR-009 | JZ4: BR-013 | KA4: BR-002 | KB4: BR-015 | KC4: BR-004 | KD4: BR-015 | KE4: BR-006 | KF4: BR-002 | KG4: BR-015 | KH4: BR-008 | KI4: BR-008 | KJ4: BR-001 | KK4: BR-012 | KL4: BR-003 | KM4: BR-010 | KN4: BR-009 | KO4: BR-005 | KP4: BR-006 | KQ4: BR-004 | KR4: BR-010 | KS4: BR-002 | KT4: BR-011 | KU4: BR-008 | KV4: BR-011 | KW4: BR-013 | KX4: BR-006 | KY4: BR-005 | KZ4: BR-009 | LA4: BR-001 | LB4: BR-005 | LC4: BR-006 | LD4: BR-005 | LE4: BR-006 | LF4: BR-006 | LG4: BR-007 | LH4: BR-004 | LI4: BR-014 | LJ4: BR-011 | LK4: BR-014 | LL4: BR-014 | LM4: BR-014 | LN4: BR-015 | LO4: BR-008 | LP4: BR-007 | LQ4: BR-009 | LR4: BR-007 | LS4: BR-003 | LT4: BR-003 | LU4: BR-015 | LV4: BR-008 | LW4: BR-005 | LX4: BR-004 | LY4: BR-008 | LZ4: BR-015 | MA4: BR-006 | MB4: BR-002 | MC4: BR-004 | MD4: BR-012 | ME4: BR-011 | MF4: BR-004 | MG4: BR-015 | MH4: BR-006 | MI4: BR-006 | MJ4: BR-001 | MK4: BR-014 | ML4: BR-008 | MM4: BR-006 | MN4: BR-003 | MO4: BR-014 | MP4: BR-009 | MQ4: BR-002 | MR4: BR-015 | MS4: BR-011 | MT4: BR-008 | MU4: BR-010 | MV4: BR-003 | MW4: BR-013 | MX4: BR-012 | MY4: BR-005 | MZ4: BR-006 | NA4: BR-010 | NB4: BR-006 | NC4: BR-004 | ND4: BR-003 | NE4: BR-004 | NF4: BR-001 | NG4: BR-004 | NH4: BR-001 | NI4: BR-012 | NJ4: BR-015 | NK4: BR-001 | NL4: BR-010 | NM4: BR-014 | NN4: BR-006 | NO4: BR-005 | NP4: BR-014 | NQ4: BR-011 | NR4: BR-015 | NS4: BR-004 | NT4: BR-013 | NU4: BR-011 | NV4: BR-003 | NW4: BR-001 | NX4: BR-006 | NY4: BR-002 | NZ4: BR-008 | OA4: BR-010 | OB4: BR-005 | OC4: BR-007 | OD4: BR-010 | OE4: BR-012 | OF4: BR-002 | OG4: BR-013 | OH4: BR-008 | OI4: BR-002 | OJ4: BR-004 | OK4: BR-001 | OL4: BR-015 | OM4: BR-005 | ON4: BR-009 | OO4: BR-001 | OP4: BR-009 | OQ4: BR-011 | OR4: BR-015 | OS4: BR-008 | OT4: BR-006 | OU4: BR-007 | OV4: BR-003 | OW4: BR-014 | OX4: BR-015 | OY4: BR-001 | OZ4: BR-005 | PA4: BR-014 | PB4: BR-012 | PC4: BR-012 | PD4: BR-002 | PE4: BR-014 | PF4: BR-005 | PG4: BR-008 | PH4: BR-011 | PI4: BR-009 | PJ4: BR-002 | PK4: BR-012 | PL4: BR-003 | PM4: BR-003 | PN4: BR-001 | PO4: BR-008 | PP4: BR-006 | PQ4: BR-012 | PR4: BR-013 | PS4: BR-008 | PT4: BR-011 | PU4: BR-009 | PV4: BR-005 | PW4: BR-014 | PX4: BR-012 | PY4: BR-014 | PZ4: BR-003 | QA4: BR-005 | QB4: BR-005 | QC4: BR-005 | QD4: BR-003 | QE4: BR-011 | QF4: BR-014 | QG4: BR-010 | QH4: BR-014 | QI4: BR-004 | QJ4: BR-009 | QK4: BR-013 | QL4: BR-010 | QM4: BR-009 | QN4: BR-002 | QO4: BR-008 | QP4: BR-008 | QQ4: BR-007 | QR4: BR-008 | QS4: BR-014 | QT4: BR-003 | QU4: BR-013 | QV4: BR-006 | QW4: BR-001 | QX4: BR-007 | QY4: BR-015 | QZ4: BR-015 | RA4: BR-001 | RB4: BR-009 | RC4: BR-001 | RD4: BR-001 | RE4: BR-015 | RF4: BR-007 | RG4: BR-002 | RH4: BR-014 | RI4: BR-005 | RJ4: BR-008 | RK4: BR-008 | RL4: BR-003 | RM4: BR-007 | RN4: BR-003 | RO4: BR-006 | RP4: BR-006 | RQ4: BR-003 | RR4: BR-007 | RS4: BR-003 | RT4: BR-008 | RU4: BR-010 | RV4: BR-004 | RW4: BR-015 | RX4: BR-015 | RY4: BR-013 | RZ4: BR-001 | SA4: BR-004 | SB4: BR-014 | SC4: BR-007 | SD4: BR-011 | SE4: BR-004 | SF4: BR-013 | SG4: BR-006 | SH4: BR-009 | SI4: BR-001 | SJ4: BR-013 | SK4: BR-005 | SL4: BR-011 | SM4: BR-007 | SN4: BR-001 | SO4: BR-014 | SP4: BR-004 | SQ4: BR-006 | SR4: BR-002 | SS4: BR-010 | ST4: BR-005 | SU4: BR-011 | SV4: BR-010 | SW4: BR-001 | SX4: BR-006 | SY4: BR-006 | SZ4: BR-013 | TA4: BR-015 | TB4: BR-015 | TC4: BR-004 | TD4: BR-013 | TE4: BR-008 | TF4: BR-004 | TG4: BR-008 | TH4: BR-015 | TI4: BR-013 | TJ4: BR-008 | TK4: BR-005 | TL4: BR-013 | TM4: BR-015 | TN4: BR-004 | TO4: BR-012 | TP4: BR-013 | TQ4: BR-002 | TR4: BR-011 | TS4: BR-015 | TT4: BR-003 | TU4: BR-003 | TV4: BR-004 | TW4: BR-004 | TX4: BR-010 | TY4: BR-011 | TZ4: BR-011 | UA4: BR-005 | UB4: BR-004 | UC4: BR-011 | UD4: BR-014 | UE4: BR-010 | UF4: BR-008 | UG4: BR-006 | UH4: BR-006 | UI4: BR-008 | UJ4: BR-007 | UK4: BR-015 | UL4: BR-010 | UM4: BR-014 | UN4: BR-011 | UO4: BR-012 | UP4: BR-010 | UQ4: BR-013 | UR4: BR-008 | US4: BR-014 | UT4: BR-002 | UU4: BR-009 | UV4: BR-001 | UW4: BR-015 | UX4: BR-008 | UY4: BR-012 | UZ4: BR-011 | VA4: BR-012 | VB4: BR-012 | VC4: BR-004 | VD4: BR-004 | VE4: BR-005 | VF4: BR-008 | VG4: BR-005 | VH4: BR-008 | VI4: BR-015 | VJ4: BR-010 | VK4: BR-001 | VL4: BR-012 | VM4: BR-015 | VN4: BR-010 | VO4: BR-009 | VP4: BR-006 | VQ4: BR-003 | VR4: BR-013 | VS4: BR-014 | VT4: BR-008 | VU4: BR-009 | VV4: BR-006 | VW4: BR-011 | VX4: BR-007 | VY4: BR-001 | VZ4: BR-014 | WA4: BR-005 | WB4: BR-005 | WC4: BR-010 | WD4: BR-014 | WE4: BR-004 | WF4: BR-006 | WG4: BR-007 | WH4: BR-009 | WI4: BR-001 | WJ4: BR-015 | WK4: BR-006 | WL4: BR-007 | WM4: BR-003 | WN4: BR-008 | WO4: BR-015 | WP4: BR-005 | WQ4: BR-015 | WR4: BR-009 | WS4: BR-005 | WT4: BR-009 | WU4: BR-010 | WV4: BR-004 | WW4: BR-009 | WX4: BR-005 | WY4: BR-010 | WZ4: BR-009 | XA4: BR-003 | XB4: BR-015 | XC4: BR-004 | XD4: BR-009 | XE4: BR-010 | XF4: BR-011 | XG4: BR-006 | XH4: BR-002 | XI4: BR-007 | XJ4: BR-002 | XK4: BR-011 | XL4: BR-002 | XM4: BR-011 | XN4: BR-001 | XO4: BR-011 | XP4: BR-011 | XQ4: BR-012 | XR4: BR-011 | XS4: BR-003 | XT4: BR-006 | XU4: BR-008 | XV4: BR-009 | XW4: BR-007 | XX4: BR-004 | XY4: BR-006 | XZ4: BR-005 | YA4: BR-008 | YB4: BR-001 | YC4: BR-001 | YD4: BR-013 | YE4: BR-015 | YF4: BR-011 | YG4: BR-006 | YH4: BR-010 | YI4: BR-012 | YJ4: BR-002 | YK4: BR-005 | YL4: BR-001 | YM4: BR-007 | YN4: BR-001 | YO4: BR-004 | YP4: BR-009 | YQ4: BR-001 | YR4: BR-004 | YS4: BR-006 | YT4: BR-006 | YU4: BR-012 | YV4: BR-015 | YW4: BR-013 | YX4: BR-008 | YY4: BR-001 | YZ4: BR-007 | ZA4: BR-001 | ZB4: BR-013 | ZC4: BR-014 | ZD4: BR-007 | ZE4: BR-003 | ZF4: BR-011 | ZG4: BR-008 | ZH4: BR-003 | ZI4: BR-014 | ZJ4: BR-014 | ZK4: BR-013 | ZL4: BR-001 | ZM4: BR-013 | ZN4: BR-013 | ZO4: BR-014 | ZP4: BR-008 | ZQ4: BR-003 | ZR4: BR-002 | ZS4: BR-001 | ZT4: BR-014 | ZU4: BR-003 | ZV4: BR-015 | ZW4: BR-002 | ZX4: BR-002 | ZY4: BR-006 | ZZ4: BR-012 | AAA4: BR-001 | AAB4: BR-002 | AAC4: BR-014 | AAD4: BR-006 | AAE4: BR-003 | AAF4: BR-015 | AAG4: BR-004 | AAH4: BR-001 | AAI4: BR-008 | AAJ4: BR-013 | AAK4: BR-007 | AAL4: BR-007 | AAM4: BR-003 | AAN4: BR-010 | AAO4: BR-010 | AAP4: BR-003 | AAQ4: BR-014 | AAR4: BR-002 | AAS4: BR-012 | AAT4: BR-001 | AAU4: BR-007 | AAV4: BR-007 | AAW4: BR-012 | AAX4: BR-002 | AAY4: BR-007 | AAZ4: BR-013 | ABA4: BR-008 | ABB4: BR-001 | ABC4: BR-009 | ABD4: BR-007 | ABE4: BR-003 | ABF4: BR-008 | ABG4: BR-007 | ABH4: BR-011 | ABI4: BR-015 | ABJ4: BR-013 | ABK4: BR-008 | ABL4: BR-006 | ABM4: BR-009 | ABN4: BR-015 | ABO4: BR-005 | ABP4: BR-003 | ABQ4: BR-003 | ABR4: BR-001 | ABS4: BR-012 | ABT4: BR-015 | ABU4: BR-008 | ABV4: BR-002 | ABW4: BR-003 | ABX4: BR-008 | ABY4: BR-014 | ABZ4: BR-008 | ACA4: BR-014 | ACB4: BR-011 | ACC4: BR-004 | ACD4: BR-004 | ACE4: BR-005 | ACF4: BR-006 | ACG4: BR-005 | ACH4: BR-014 | ACI4: BR-015 | ACJ4: BR-007 | ACK4: BR-002 | ACL4: BR-007 | ACM4: BR-010 | ACN4: BR-007 | ACO4: BR-001 | ACP4: BR-007 | ACQ4: BR-005 | ACR4: BR-003 | ACS4: BR-013 | ACT4: BR-003 | ACU4: BR-004 | ACV4: BR-013 | ACW4: BR-012 | ACX4: BR-002 | ACY4: BR-002 | ACZ4: BR-001 | ADA4: BR-015 | ADB4: BR-005 | ADC4: BR-004 | ADD4: BR-011 | ADE4: BR-010 | ADF4: BR-015 | ADG4: BR-002 | ADH4: BR-003 | ADI4: BR-007 | ADJ4: BR-007 | ADK4: BR-012 | ADL4: BR-004 | ADM4: BR-005 | ADN4: BR-005 | ADO4: BR-006 | ADP4: BR-014 | ADQ4: BR-009 | ADR4: BR-002 | ADS4: BR-005 | ADT4: BR-012 | ADU4: BR-003 | ADV4: BR-004 | ADW4: BR-010 | ADX4: BR-006 | ADY4: BR-012 | ADZ4: BR-008 | AEA4: BR-001 | AEB4: BR-010 | AEC4: BR-014 | AED4: BR-008 | AEE4: BR-011 | AEF4: BR-014 | AEG4: BR-007 | AEH4: BR-001 | AEI4: BR-002 | AEJ4: BR-003 | AEK4: BR-001 | AEL4: BR-014 | AEM4: BR-009 | AEN4: BR-008 | AEO4: BR-002 | AEP4: BR-013 | AEQ4: BR-009 | AER4: BR-007 | AES4: BR-009 | AET4: BR-006 | AEU4: BR-006 | AEV4: BR-011 | AEW4: BR-014 | AEX4: BR-004 | AEY4: BR-010 | AEZ4: BR-010 | AFA4: BR-013 | AFB4: BR-013 | AFC4: BR-002 | AFD4: BR-007 | AFE4: BR-005 | AFF4: BR-011 | AFG4: BR-006 | AFH4: BR-002 | AFI4: BR-005 | AFJ4: BR-010 | AFK4: BR-004 | AFL4: BR-009 | AFM4: BR-006 | AFN4: BR-002 | AFO4: BR-001 | AFP4: BR-005 | AFQ4: BR-009 | AFR4: BR-006 | AFS4: BR-010 | AFT4: BR-012 | AFU4: BR-007 | AFV4: BR-005 | AFW4: BR-010 | AFX4: BR-006 | AFY4: BR-005 | AFZ4: BR-011 | AGA4: BR-009 | AGB4: BR-015 | AGC4: BR-006 | AGD4: BR-011 | AGE4: BR-008 | AGF4: BR-002 | AGG4: BR-012 | AGH4: BR-013 | AGI4: BR-009 | AGJ4: BR-005 | AGK4: BR-007 | AGL4: BR-010 | AGM4: BR-013 | AGN4: BR-001 | AGO4: BR-010 | AGP4: BR-005 | AGQ4: BR-012 | AGR4: BR-014 | AGS4: BR-010 | AGT4: BR-014 | AGU4: BR-002 | AGV4: BR-012 | AGW4: BR-006 | AGX4: BR-011 | AGY4: BR-001 | AGZ4: BR-003 | AHA4: BR-005 | AHB4: BR-004 | AHC4: BR-003 | AHD4: BR-010 | AHE4: BR-013 | AHF4: BR-005 | AHG4: BR-011 | AHH4: BR-008 | AHI4: BR-011 | AHJ4: BR-004 | AHK4: BR-001 | AHL4: BR-011 | AHM4: BR-007 | AHN4: BR-008 | AHO4: BR-003 | AHP4: BR-006 | AHQ4: BR-002 | AHR4: BR-007 | AHS4: BR-015 | AHT4: BR-008 | AHU4: BR-006 | AHV4: BR-006 | AHW4: BR-005 | AHX4: BR-008 | AHY4: BR-001 | AHZ4: BR-010 | AIA4: BR-004 | AIB4: BR-015 | AIC4: BR-004 | AID4: BR-003 | AIE4: BR-003 | AIF4: BR-004 | AIG4: BR-011 | AIH4: BR-001 | AII4: BR-014 | AIJ4: BR-011 | AIK4: BR-013 | AIL4: BR-011 | AIM4: BR-002 | AIN4: BR-009 | AIO4: BR-010 | AIP4: BR-002 | AIQ4: BR-005 | AIR4: BR-009 | AIS4: BR-009 | AIT4: BR-008 | AIU4: BR-001 | AIV4: BR-001 | AIW4: BR-009 | AIX4: BR-013 | AIY4: BR-011 | AIZ4: BR-008 | AJA4: BR-010 | AJB4: BR-009 | AJC4: BR-007 | AJD4: BR-003 | AJE4: BR-003 | AJF4: BR-002 | AJG4: BR-005 | AJH4: BR-012 | AJI4: BR-012 | AJJ4: BR-003 | AJK4: BR-014 | AJL4: BR-006 | AJM4: BR-002 | AJN4: BR-012 | AJO4: BR-003 | AJP4: BR-005 | AJQ4: BR-012 | AJR4: BR-011 | AJS4: BR-011 | AJT4: BR-001 | AJU4: BR-013 | AJV4: BR-001 | AJW4: BR-010 | AJX4: BR-009 | AJY4: BR-007 | AJZ4: BR-001 | AKA4: BR-015 | AKB4: BR-012 | AKC4: BR-014 | AKD4: BR-008 | AKE4: BR-003 | AKF4: BR-008 | AKG4: BR-015 | AKH4: BR-005 | AKI4: BR-001 | AKJ4: BR-007 | AKK4: BR-005 | AKL4: BR-006 | AKM4: BR-006 | AKN4: BR-008 | AKO4: BR-009 | AKP4: BR-002 | AKQ4: BR-009 | AKR4: BR-012 | AKS4: BR-015 | AKT4: BR-011 | AKU4: BR-010 | AKV4: BR-009 | AKW4: BR-013 | AKX4: BR-010 | AKY4: BR-015 | AKZ4: BR-010 | ALA4: BR-007 | ALB4: BR-001 | ALC4: BR-007 | ALD4: BR-010 | ALE4: BR-005 | ALF4: BR-006 | ALG4: BR-010 | ALH4: BR-007 | ALI4: BR-014 | ALJ4: BR-015 | ALK4: BR-005 | ALL4: BR-007 | ALM4: BR-009
A5: Region | B5: East | C5: South | D5: East | E5: Central | F5: South | G5: West | H5: East | I5: South | J5: East | K5: South | L5: North | M5: East | N5: West | O5: West | P5: Central | Q5: South | R5: East | S5: Central | T5: East | U5: South | V5: West | W5: North | X5: West | Y5: Central | Z5: North | AA5: Central | AB5: South | AC5: North | AD5: Central | AE5: South | AF5: West | AG5: South | AH5: East | AI5: South | AJ5: South | AK5: East | AL5: Central | AM5: Central | AN5: South | AO5: East | AP5: East | AQ5: West | AR5: Central | AS5: North | AT5: Central | AU5: Central | AV5: West | AW5: North | AX5: West | AY5: North | AZ5: South | BA5: North | BB5: West | BC5: Central | BD5: North | BE5: North | BF5: East | BG5: Central | BH5: South | BI5: West | BJ5: South | BK5: Central | BL5: North | BM5: North | BN5: Central | BO5: North | BP5: North | BQ5: North | BR5: West | BS5: West | BT5: East | BU5: South | BV5: Central | BW5: Central | BX5: Central | BY5: East | BZ5: West | CA5: East | CB5: Central | CC5: South | CD5: North | CE5: West | CF5: West | CG5: East | CH5: West | CI5: Central | CJ5: Central | CK5: East | CL5: Central | CM5: South | CN5: East | CO5: South | CP5: North | CQ5: South | CR5: North | CS5: North | CT5: South | CU5: East | CV5: Central | CW5: Central | CX5: North | CY5: North | CZ5: East | DA5: West | DB5: South | DC5: North | DD5: Central | DE5: East | DF5: South | DG5: East | DH5: South | DI5: South | DJ5: North | DK5: East | DL5: East | DM5: Central | DN5: Central | DO5: North | DP5: North | DQ5: West | DR5: Central | DS5: South | DT5: East | DU5: North | DV5: East | DW5: East | DX5: West | DY5: Central | DZ5: North | EA5: East | EB5: North | EC5: South | ED5: West | EE5: South | EF5: North | EG5: North | EH5: Central | EI5: East | EJ5: East | EK5: South | EL5: West | EM5: East | EN5: Central | EO5: South | EP5: South | EQ5: Central | ER5: West | ES5: Central | ET5: West | EU5: Central | EV5: Central | EW5: North | EX5: South | EY5: Central | EZ5: Central | FA5: East | FB5: South | FC5: East | FD5: South | FE5: East | FF5: Central | FG5: Central | FH5: North | FI5: East | FJ5: West | FK5: North | FL5: East | FM5: East | FN5: North | FO5: Central | FP5: East | FQ5: Central | FR5: North | FS5: Central | FT5: South | FU5: West | FV5: East | FW5: West | FX5: Central | FY5: East | FZ5: Central | GA5: South | GB5: North | GC5: East | GD5: South | GE5: South | GF5: East | GG5: Central | GH5: South | GI5: West | GJ5: South | GK5: Central | GL5: Central | GM5: West | GN5: South | GO5: Central | GP5: East | GQ5: North | GR5: North | GS5: North | GT5: South | GU5: West | GV5: Central | GW5: East | GX5: East | GY5: South | GZ5: North | HA5: South | HB5: West | HC5: West | HD5: Central | HE5: Central | HF5: West | HG5: West | HH5: West | HI5: South | HJ5: West | HK5: East | HL5: North | HM5: West | HN5: North | HO5: South | HP5: North | HQ5: South | HR5: East | HS5: South | HT5: South | HU5: Central | HV5: West | HW5: West | HX5: East | HY5: East | HZ5: West | IA5: Central | IB5: West | IC5: Central | ID5: East | IE5: North | IF5: East | IG5: East | IH5: South | II5: South | IJ5: South | IK5: South | IL5: Central | IM5: West | IN5: North | IO5: East | IP5: Central | IQ5: North | IR5: Central | IS5: Central | IT5: East | IU5: West | IV5: South | IW5: West | IX5: East | IY5: East | IZ5: East | JA5: North | JB5: West | JC5: West | JD5: Central | JE5: Central | JF5: Central | JG5: East | JH5: West | JI5: East | JJ5: North | JK5: Central | JL5: East | JM5: East | JN5: North | JO5: South | JP5: West | JQ5: South | JR5: Central | JS5: East | JT5: North | JU5: North | JV5: West | JW5: South | JX5: West | JY5: East | JZ5: West | KA5: North | KB5: North | KC5: Central | KD5: Central | KE5: East | KF5: South | KG5: West | KH5: East | KI5: Central | KJ5: West | KK5: Central | KL5: West | KM5: South | KN5: East | KO5: West | KP5: North | KQ5: North | KR5: West | KS5: West | KT5: West | KU5: North | KV5: North | KW5: West | KX5: Central | KY5: Central | KZ5: South | LA5: East | LB5: Central | LC5: North | LD5: Central | LE5: South | LF5: South | LG5: East | LH5: Central | LI5: North | LJ5: North | LK5: West | LL5: North | LM5: East | LN5: East | LO5: North | LP5: North | LQ5: West | LR5: North | LS5: West | LT5: West | LU5: North | LV5: South | LW5: South | LX5: West | LY5: North | LZ5: South | MA5: North | MB5: North | MC5: North | MD5: Central | ME5: North | MF5: Central | MG5: West | MH5: South | MI5: South | MJ5: South | MK5: South | ML5: South | MM5: South | MN5: South | MO5: West | MP5: North | MQ5: East | MR5: Central | MS5: East | MT5: East | MU5: North | MV5: North | MW5: North | MX5: South | MY5: West | MZ5: South | NA5: West | NB5: West | NC5: East | ND5: East | NE5: West | NF5: West | NG5: South | NH5: South | NI5: East | NJ5: North | NK5: West | NL5: South | NM5: East | NN5: South | NO5: West | NP5: West | NQ5: Central | NR5: North | NS5: Central | NT5: East | NU5: South | NV5: East | NW5: West | NX5: Central | NY5: Central | NZ5: Central | OA5: East | OB5: West | OC5: South | OD5: South | OE5: East | OF5: Central | OG5: North | OH5: East | OI5: East | OJ5: West | OK5: South | OL5: East | OM5: East | ON5: Central | OO5: Central | OP5: North | OQ5: West | OR5: North | OS5: Central | OT5: South | OU5: Central | OV5: West | OW5: Central | OX5: West | OY5: West | OZ5: West | PA5: West | PB5: West | PC5: South | PD5: North | PE5: East | PF5: North | PG5: West | PH5: South | PI5: Central | PJ5: South | PK5: West | PL5: South | PM5: South | PN5: West | PO5: South | PP5: East | PQ5: East | PR5: South | PS5: Central | PT5: West | PU5: East | PV5: Central | PW5: South | PX5: Central | PY5: North | PZ5: East | QA5: South | QB5: West | QC5: South | QD5: West | QE5: South | QF5: Central | QG5: Central | QH5: Central | QI5: North | QJ5: West | QK5: Central | QL5: North | QM5: West | QN5: South | QO5: North | QP5: East | QQ5: North | QR5: North | QS5: West | QT5: South | QU5: East | QV5: Central | QW5: Central | QX5: North | QY5: West | QZ5: West | RA5: Central | RB5: East | RC5: South | RD5: East | RE5: South | RF5: Central | RG5: South | RH5: West | RI5: North | RJ5: North | RK5: Central | RL5: West | RM5: East | RN5: West | RO5: North | RP5: North | RQ5: West | RR5: West | RS5: North | RT5: East | RU5: Central | RV5: Central | RW5: West | RX5: Central | RY5: North | RZ5: North | SA5: West | SB5: West | SC5: West | SD5: East | SE5: Central | SF5: West | SG5: South | SH5: South | SI5: North | SJ5: Central | SK5: West | SL5: South | SM5: Central | SN5: North | SO5: East | SP5: Central | SQ5: Central | SR5: East | SS5: Central | ST5: North | SU5: North | SV5: East | SW5: West | SX5: South | SY5: West | SZ5: Central | TA5: South | TB5: East | TC5: East | TD5: South | TE5: North | TF5: South | TG5: Central | TH5: North | TI5: East | TJ5: South | TK5: West | TL5: West | TM5: Central | TN5: West | TO5: South | TP5: South | TQ5: West | TR5: South | TS5: Central | TT5: North | TU5: Central | TV5: Central | TW5: South | TX5: North | TY5: South | TZ5: East | UA5: South | UB5: South | UC5: South | UD5: North | UE5: South | UF5: North | UG5: West | UH5: East | UI5: North | UJ5: West | UK5: North | UL5: North | UM5: East | UN5: Central | UO5: Central | UP5: North | UQ5: South | UR5: West | US5: South | UT5: South | UU5: North | UV5: North | UW5: North | UX5: North | UY5: Central | UZ5: North | VA5: Central | VB5: Central | VC5: North | VD5: East | VE5: West | VF5: South | VG5: Central | VH5: West | VI5: East | VJ5: South | VK5: South | VL5: Central | VM5: North | VN5: East | VO5: Central | VP5: East | VQ5: North | VR5: North | VS5: Central | VT5: North | VU5: West | VV5: South | VW5: Central | VX5: East | VY5: West | VZ5: Central | WA5: North | WB5: North | WC5: North | WD5: North | WE5: East | WF5: West | WG5: South | WH5: East | WI5: East | WJ5: South | WK5: South | WL5: North | WM5: East | WN5: Central | WO5: South | WP5: South | WQ5: West | WR5: Central | WS5: Central | WT5: South | WU5: North | WV5: West | WW5: Central | WX5: South | WY5: Central | WZ5: West | XA5: West | XB5: East | XC5: South | XD5: West | XE5: East | XF5: East | XG5: Central | XH5: Central | XI5: East | XJ5: Central | XK5: West | XL5: North | XM5: West | XN5: East | XO5: East | XP5: West | XQ5: Central | XR5: Central | XS5: East | XT5: South | XU5: Central | XV5: West | XW5: Central | XX5: West | XY5: East | XZ5: Central | YA5: West | YB5: East | YC5: South | YD5: West | YE5: South | YF5: South | YG5: North | YH5: Central | YI5: West | YJ5: South | YK5: North | YL5: East | YM5: West | YN5: South | YO5: Central | YP5: North | YQ5: South | YR5: Central | YS5: South | YT5: West | YU5: West | YV5: West | YW5: North | YX5: West | YY5: Central | YZ5: South | ZA5: East | ZB5: Central | ZC5: Central | ZD5: West | ZE5: North | ZF5: South | ZG5: North | ZH5: South | ZI5: South | ZJ5: North | ZK5: Central | ZL5: South | ZM5: North | ZN5: South | ZO5: East | ZP5: Central | ZQ5: West | ZR5: South | ZS5: East | ZT5: West | ZU5: West | ZV5: South | ZW5: North | ZX5: South | ZY5: East | ZZ5: West | AAA5: South | AAB5: North | AAC5: South | AAD5: Central | AAE5: North | AAF5: East | AAG5: West | AAH5: South | AAI5: North | AAJ5: Central | AAK5: North | AAL5: Central | AAM5: East | AAN5: West | AAO5: East | AAP5: South | AAQ5: North | AAR5: Central | AAS5: Central | AAT5: North | AAU5: North | AAV5: South | AAW5: East | AAX5: Central | AAY5: South | AAZ5: East | ABA5: South | ABB5: Central | ABC5: North | ABD5: North | ABE5: East | ABF5: West | ABG5: East | ABH5: West | ABI5: South | ABJ5: South | ABK5: Central | ABL5: West | ABM5: Central | ABN5: North | ABO5: West | ABP5: East | ABQ5: North | ABR5: North | ABS5: East | ABT5: North | ABU5: West | ABV5: Central | ABW5: North | ABX5: West | ABY5: South | ABZ5: West | ACA5: Central | ACB5: West | ACC5: East | ACD5: Central | ACE5: South | ACF5: East | ACG5: West | ACH5: Central | ACI5: South | ACJ5: East | ACK5: South | ACL5: West | ACM5: South | ACN5: North | ACO5: East | ACP5: South | ACQ5: West | ACR5: West | ACS5: South | ACT5: West | ACU5: Central | ACV5: Central | ACW5: Central | ACX5: North | ACY5: South | ACZ5: North | ADA5: West | ADB5: North | ADC5: West | ADD5: West | ADE5: East | ADF5: Central | ADG5: West | ADH5: East | ADI5: Central | ADJ5: West | ADK5: West | ADL5: North | ADM5: North | ADN5: Central | ADO5: West | ADP5: South | ADQ5: North | ADR5: Central | ADS5: West | ADT5: West | ADU5: South | ADV5: Central | ADW5: West | ADX5: North | ADY5: South | ADZ5: Central | AEA5: South | AEB5: North | AEC5: Central | AED5: South | AEE5: East | AEF5: North | AEG5: North | AEH5: North | AEI5: East | AEJ5: East | AEK5: West | AEL5: South | AEM5: West | AEN5: South | AEO5: East | AEP5: East | AEQ5: West | AER5: Central | AES5: West | AET5: South | AEU5: West | AEV5: North | AEW5: South | AEX5: South | AEY5: Central | AEZ5: East | AFA5: South | AFB5: East | AFC5: West | AFD5: North | AFE5: Central | AFF5: East | AFG5: South | AFH5: East | AFI5: South | AFJ5: East | AFK5: South | AFL5: West | AFM5: South | AFN5: South | AFO5: North | AFP5: South | AFQ5: North | AFR5: Central | AFS5: North | AFT5: West | AFU5: North | AFV5: Central | AFW5: West | AFX5: East | AFY5: East | AFZ5: North | AGA5: North | AGB5: Central | AGC5: Central | AGD5: South | AGE5: Central | AGF5: South | AGG5: West | AGH5: North | AGI5: West | AGJ5: Central | AGK5: West | AGL5: West | AGM5: West | AGN5: Central | AGO5: West | AGP5: South | AGQ5: Central | AGR5: West | AGS5: Central | AGT5: East | AGU5: South | AGV5: West | AGW5: East | AGX5: East | AGY5: Central | AGZ5: East | AHA5: South | AHB5: South | AHC5: North | AHD5: South | AHE5: East | AHF5: South | AHG5: Central | AHH5: North | AHI5: East | AHJ5: North | AHK5: East | AHL5: Central | AHM5: North | AHN5: West | AHO5: East | AHP5: West | AHQ5: North | AHR5: West | AHS5: West | AHT5: North | AHU5: Central | AHV5: West | AHW5: West | AHX5: Central | AHY5: West | AHZ5: West | AIA5: West | AIB5: South | AIC5: Central | AID5: West | AIE5: Central | AIF5: East | AIG5: East | AIH5: West | AII5: Central | AIJ5: Central | AIK5: Central | AIL5: South | AIM5: East | AIN5: Central | AIO5: Central | AIP5: South | AIQ5: South | AIR5: Central | AIS5: North | AIT5: Central | AIU5: Central | AIV5: South | AIW5: South | AIX5: Central | AIY5: Central | AIZ5: Central | AJA5: South | AJB5: Central | AJC5: Central | AJD5: West | AJE5: North | AJF5: East | AJG5: North | AJH5: West | AJI5: East | AJJ5: Central | AJK5: West | AJL5: Central | AJM5: South | AJN5: West | AJO5: South | AJP5: West | AJQ5: West | AJR5: South | AJS5: East | AJT5: North | AJU5: Central | AJV5: West | AJW5: Central | AJX5: South | AJY5: Central | AJZ5: South | AKA5: Central | AKB5: North | AKC5: North | AKD5: North | AKE5: North | AKF5: North | AKG5: North | AKH5: South | AKI5: West | AKJ5: Central | AKK5: North | AKL5: South | AKM5: South | AKN5: South | AKO5: West | AKP5: Central | AKQ5: West | AKR5: East | AKS5: South | AKT5: East | AKU5: North | AKV5: North | AKW5: West | AKX5: Central | AKY5: East | AKZ5: Central | ALA5: West | ALB5: North | ALC5: Central | ALD5: Central | ALE5: North | ALF5: East | ALG5: North | ALH5: Central | ALI5: East | ALJ5: East | ALK5: North | ALL5: Central | ALM5: West
A6: Product | B6: Wealth Management | C6: Personal Loan | D6: Auto Loan | E6: Mortgage | F6: Auto Loan | G6: Mortgage | H6: Mortgage | I6: Auto Loan | J6: Mortgage | K6: Mortgage | L6: Personal Loan | M6: Wealth Management | N6: Wealth Management | O6: Personal Loan | P6: Auto Loan | Q6: Credit Card | R6: Credit Card | S6: Credit Card | T6: Personal Loan | U6: Personal Loan | V6: Mortgage | W6: Credit Card | X6: Auto Loan | Y6: Auto Loan | Z6: Credit Card | AA6: Credit Card | AB6: Credit Card | AC6: Personal Loan | AD6: Personal Loan | AE6: Personal Loan | AF6: Wealth Management | AG6: Auto Loan | AH6: Auto Loan | AI6: Mortgage | AJ6: Personal Loan | AK6: Wealth Management | AL6: Wealth Management | AM6: Auto Loan | AN6: Personal Loan | AO6: Mortgage | AP6: Personal Loan | AQ6: Credit Card | AR6: Personal Loan | AS6: Credit Card | AT6: Credit Card | AU6: Mortgage | AV6: Auto Loan | AW6: Personal Loan | AX6: Credit Card | AY6: Personal Loan | AZ6: Auto Loan | BA6: Auto Loan | BB6: Wealth Management | BC6: Auto Loan | BD6: Mortgage | BE6: Credit Card | BF6: Wealth Management | BG6: Mortgage | BH6: Personal Loan | BI6: Credit Card | BJ6: Auto Loan | BK6: Credit Card | BL6: Personal Loan | BM6: Wealth Management | BN6: Wealth Management | BO6: Wealth Management | BP6: Auto Loan | BQ6: Mortgage | BR6: Mortgage | BS6: Credit Card | BT6: Auto Loan | BU6: Wealth Management | BV6: Wealth Management | BW6: Personal Loan | BX6: Personal Loan | BY6: Wealth Management | BZ6: Wealth Management | CA6: Auto Loan | CB6: Mortgage | CC6: Personal Loan | CD6: Mortgage | CE6: Auto Loan | CF6: Wealth Management | CG6: Mortgage | CH6: Wealth Management | CI6: Wealth Management | CJ6: Credit Card | CK6: Mortgage | CL6: Mortgage | CM6: Wealth Management | CN6: Auto Loan | CO6: Credit Card | CP6: Wealth Management | CQ6: Personal Loan | CR6: Personal Loan | CS6: Credit Card | CT6: Auto Loan | CU6: Wealth Management | CV6: Mortgage | CW6: Credit Card | CX6: Auto Loan | CY6: Mortgage | CZ6: Personal Loan | DA6: Personal Loan | DB6: Mortgage | DC6: Credit Card | DD6: Personal Loan | DE6: Wealth Management | DF6: Mortgage | DG6: Mortgage | DH6: Personal Loan | DI6: Credit Card | DJ6: Wealth Management | DK6: Credit Card | DL6: Auto Loan | DM6: Auto Loan | DN6: Personal Loan | DO6: Personal Loan | DP6: Personal Loan | DQ6: Auto Loan | DR6: Credit Card | DS6: Credit Card | DT6: Personal Loan | DU6: Wealth Management | DV6: Credit Card | DW6: Auto Loan | DX6: Mortgage | DY6: Mortgage | DZ6: Mortgage | EA6: Wealth Management | EB6: Personal Loan | EC6: Auto Loan | ED6: Wealth Management | EE6: Auto Loan | EF6: Auto Loan | EG6: Personal Loan | EH6: Mortgage | EI6: Personal Loan | EJ6: Wealth Management | EK6: Wealth Management | EL6: Wealth Management | EM6: Personal Loan | EN6: Auto Loan | EO6: Auto Loan | EP6: Credit Card | EQ6: Wealth Management | ER6: Auto Loan | ES6: Credit Card | ET6: Auto Loan | EU6: Wealth Management | EV6: Mortgage | EW6: Wealth Management | EX6: Personal Loan | EY6: Auto Loan | EZ6: Auto Loan | FA6: Personal Loan | FB6: Personal Loan | FC6: Mortgage | FD6: Auto Loan | FE6: Auto Loan | FF6: Mortgage | FG6: Credit Card | FH6: Mortgage | FI6: Wealth Management | FJ6: Auto Loan | FK6: Personal Loan | FL6: Wealth Management | FM6: Auto Loan | FN6: Mortgage | FO6: Wealth Management | FP6: Auto Loan | FQ6: Credit Card | FR6: Credit Card | FS6: Personal Loan | FT6: Auto Loan | FU6: Credit Card | FV6: Mortgage | FW6: Auto Loan | FX6: Mortgage | FY6: Mortgage | FZ6: Credit Card | GA6: Auto Loan | GB6: Wealth Management | GC6: Credit Card | GD6: Credit Card | GE6: Auto Loan | GF6: Auto Loan | GG6: Mortgage | GH6: Auto Loan | GI6: Mortgage | GJ6: Credit Card | GK6: Personal Loan | GL6: Wealth Management | GM6: Credit Card | GN6: Auto Loan | GO6: Wealth Management | GP6: Personal Loan | GQ6: Personal Loan | GR6: Mortgage | GS6: Wealth Management | GT6: Mortgage | GU6: Credit Card | GV6: Wealth Management | GW6: Credit Card | GX6: Mortgage | GY6: Wealth Management | GZ6: Mortgage | HA6: Wealth Management | HB6: Mortgage | HC6: Personal Loan | HD6: Mortgage | HE6: Personal Loan | HF6: Mortgage | HG6: Wealth Management | HH6: Wealth Management | HI6: Wealth Management | HJ6: Auto Loan | HK6: Credit Card | HL6: Wealth Management | HM6: Personal Loan | HN6: Wealth Management | HO6: Auto Loan | HP6: Personal Loan | HQ6: Auto Loan | HR6: Personal Loan | HS6: Mortgage | HT6: Credit Card | HU6: Credit Card | HV6: Auto Loan | HW6: Credit Card | HX6: Auto Loan | HY6: Auto Loan | HZ6: Auto Loan | IA6: Credit Card | IB6: Auto Loan | IC6: Credit Card | ID6: Auto Loan | IE6: Wealth Management | IF6: Auto Loan | IG6: Personal Loan | IH6: Auto Loan | II6: Mortgage | IJ6: Auto Loan | IK6: Personal Loan | IL6: Personal Loan | IM6: Credit Card | IN6: Wealth Management | IO6: Auto Loan | IP6: Credit Card | IQ6: Wealth Management | IR6: Auto Loan | IS6: Mortgage | IT6: Auto Loan | IU6: Personal Loan | IV6: Personal Loan | IW6: Mortgage | IX6: Credit Card | IY6: Wealth Management | IZ6: Auto Loan | JA6: Personal Loan | JB6: Credit Card | JC6: Mortgage | JD6: Personal Loan | JE6: Mortgage | JF6: Auto Loan | JG6: Wealth Management | JH6: Personal Loan | JI6: Personal Loan | JJ6: Auto Loan | JK6: Credit Card | JL6: Wealth Management | JM6: Personal Loan | JN6: Wealth Management | JO6: Personal Loan | JP6: Wealth Management | JQ6: Mortgage | JR6: Personal Loan | JS6: Wealth Management | JT6: Credit Card | JU6: Mortgage | JV6: Mortgage | JW6: Credit Card | JX6: Wealth Management | JY6: Auto Loan | JZ6: Credit Card | KA6: Wealth Management | KB6: Credit Card | KC6: Credit Card | KD6: Personal Loan | KE6: Wealth Management | KF6: Auto Loan | KG6: Personal Loan | KH6: Credit Card | KI6: Credit Card | KJ6: Credit Card | KK6: Wealth Management | KL6: Wealth Management | KM6: Personal Loan | KN6: Auto Loan | KO6: Personal Loan | KP6: Mortgage | KQ6: Credit Card | KR6: Credit Card | KS6: Credit Card | KT6: Personal Loan | KU6: Personal Loan | KV6: Credit Card | KW6: Personal Loan | KX6: Wealth Management | KY6: Wealth Management | KZ6: Personal Loan | LA6: Credit Card | LB6: Personal Loan | LC6: Personal Loan | LD6: Personal Loan | LE6: Mortgage | LF6: Wealth Management | LG6: Auto Loan | LH6: Auto Loan | LI6: Mortgage | LJ6: Personal Loan | LK6: Mortgage | LL6: Mortgage | LM6: Credit Card | LN6: Wealth Management | LO6: Auto Loan | LP6: Personal Loan | LQ6: Auto Loan | LR6: Auto Loan | LS6: Wealth Management | LT6: Auto Loan | LU6: Auto Loan | LV6: Mortgage | LW6: Wealth Management | LX6: Credit Card | LY6: Personal Loan | LZ6: Auto Loan | MA6: Personal Loan | MB6: Credit Card | MC6: Personal Loan | MD6: Credit Card | ME6: Mortgage | MF6: Auto Loan | MG6: Credit Card | MH6: Personal Loan | MI6: Auto Loan | MJ6: Mortgage | MK6: Auto Loan | ML6: Credit Card | MM6: Mortgage | MN6: Personal Loan | MO6: Mortgage | MP6: Mortgage | MQ6: Wealth Management | MR6: Mortgage | MS6: Mortgage | MT6: Auto Loan | MU6: Personal Loan | MV6: Auto Loan | MW6: Auto Loan | MX6: Credit Card | MY6: Auto Loan | MZ6: Wealth Management | NA6: Wealth Management | NB6: Credit Card | NC6: Personal Loan | ND6: Personal Loan | NE6: Auto Loan | NF6: Auto Loan | NG6: Auto Loan | NH6: Personal Loan | NI6: Mortgage | NJ6: Wealth Management | NK6: Mortgage | NL6: Mortgage | NM6: Personal Loan | NN6: Mortgage | NO6: Credit Card | NP6: Auto Loan | NQ6: Credit Card | NR6: Wealth Management | NS6: Auto Loan | NT6: Mortgage | NU6: Wealth Management | NV6: Auto Loan | NW6: Mortgage | NX6: Credit Card | NY6: Auto Loan | NZ6: Mortgage | OA6: Credit Card | OB6: Wealth Management | OC6: Wealth Management | OD6: Wealth Management | OE6: Wealth Management | OF6: Personal Loan | OG6: Auto Loan | OH6: Auto Loan | OI6: Personal Loan | OJ6: Mortgage | OK6: Mortgage | OL6: Wealth Management | OM6: Credit Card | ON6: Mortgage | OO6: Credit Card | OP6: Auto Loan | OQ6: Credit Card | OR6: Auto Loan | OS6: Personal Loan | OT6: Personal Loan | OU6: Wealth Management | OV6: Mortgage | OW6: Wealth Management | OX6: Auto Loan | OY6: Wealth Management | OZ6: Credit Card | PA6: Auto Loan | PB6: Personal Loan | PC6: Mortgage | PD6: Auto Loan | PE6: Auto Loan | PF6: Credit Card | PG6: Mortgage | PH6: Personal Loan | PI6: Auto Loan | PJ6: Auto Loan | PK6: Credit Card | PL6: Wealth Management | PM6: Personal Loan | PN6: Mortgage | PO6: Auto Loan | PP6: Auto Loan | PQ6: Personal Loan | PR6: Wealth Management | PS6: Auto Loan | PT6: Personal Loan | PU6: Credit Card | PV6: Wealth Management | PW6: Mortgage | PX6: Auto Loan | PY6: Personal Loan | PZ6: Credit Card | QA6: Mortgage | QB6: Personal Loan | QC6: Personal Loan | QD6: Mortgage | QE6: Credit Card | QF6: Credit Card | QG6: Wealth Management | QH6: Auto Loan | QI6: Mortgage | QJ6: Mortgage | QK6: Mortgage | QL6: Credit Card | QM6: Auto Loan | QN6: Wealth Management | QO6: Personal Loan | QP6: Personal Loan | QQ6: Mortgage | QR6: Auto Loan | QS6: Credit Card | QT6: Auto Loan | QU6: Auto Loan | QV6: Credit Card | QW6: Mortgage | QX6: Auto Loan | QY6: Personal Loan | QZ6: Credit Card | RA6: Wealth Management | RB6: Mortgage | RC6: Credit Card | RD6: Wealth Management | RE6: Wealth Management | RF6: Auto Loan | RG6: Auto Loan | RH6: Auto Loan | RI6: Credit Card | RJ6: Credit Card | RK6: Mortgage | RL6: Auto Loan | RM6: Wealth Management | RN6: Personal Loan | RO6: Mortgage | RP6: Credit Card | RQ6: Mortgage | RR6: Mortgage | RS6: Mortgage | RT6: Mortgage | RU6: Personal Loan | RV6: Auto Loan | RW6: Wealth Management | RX6: Mortgage | RY6: Mortgage | RZ6: Mortgage | SA6: Auto Loan | SB6: Credit Card | SC6: Credit Card | SD6: Personal Loan | SE6: Credit Card | SF6: Mortgage | SG6: Mortgage | SH6: Mortgage | SI6: Personal Loan | SJ6: Mortgage | SK6: Credit Card | SL6: Auto Loan | SM6: Auto Loan | SN6: Wealth Management | SO6: Credit Card | SP6: Mortgage | SQ6: Auto Loan | SR6: Credit Card | SS6: Auto Loan | ST6: Mortgage | SU6: Auto Loan | SV6: Wealth Management | SW6: Wealth Management | SX6: Auto Loan | SY6: Credit Card | SZ6: Credit Card | TA6: Credit Card | TB6: Auto Loan | TC6: Credit Card | TD6: Mortgage | TE6: Wealth Management | TF6: Mortgage | TG6: Credit Card | TH6: Mortgage | TI6: Credit Card | TJ6: Auto Loan | TK6: Mortgage | TL6: Auto Loan | TM6: Auto Loan | TN6: Personal Loan | TO6: Credit Card | TP6: Wealth Management | TQ6: Credit Card | TR6: Wealth Management | TS6: Credit Card | TT6: Auto Loan | TU6: Mortgage | TV6: Mortgage | TW6: Personal Loan | TX6: Wealth Management | TY6: Wealth Management | TZ6: Wealth Management | UA6: Auto Loan | UB6: Wealth Management | UC6: Mortgage | UD6: Auto Loan | UE6: Credit Card | UF6: Wealth Management | UG6: Wealth Management | UH6: Credit Card | UI6: Wealth Management | UJ6: Credit Card | UK6: Auto Loan | UL6: Mortgage | UM6: Credit Card | UN6: Personal Loan | UO6: Credit Card | UP6: Wealth Management | UQ6: Auto Loan | UR6: Auto Loan | US6: Credit Card | UT6: Mortgage | UU6: Personal Loan | UV6: Auto Loan | UW6: Wealth Management | UX6: Wealth Management | UY6: Mortgage | UZ6: Auto Loan | VA6: Credit Card | VB6: Wealth Management | VC6: Mortgage | VD6: Auto Loan | VE6: Auto Loan | VF6: Auto Loan | VG6: Auto Loan | VH6: Auto Loan | VI6: Wealth Management | VJ6: Mortgage | VK6: Auto Loan | VL6: Personal Loan | VM6: Personal Loan | VN6: Mortgage | VO6: Credit Card | VP6: Credit Card | VQ6: Credit Card | VR6: Personal Loan | VS6: Credit Card | VT6: Wealth Management | VU6: Auto Loan | VV6: Personal Loan | VW6: Mortgage | VX6: Mortgage | VY6: Auto Loan | VZ6: Personal Loan | WA6: Credit Card | WB6: Credit Card | WC6: Wealth Management | WD6: Wealth Management | WE6: Credit Card | WF6: Mortgage | WG6: Mortgage | WH6: Wealth Management | WI6: Auto Loan | WJ6: Credit Card | WK6: Wealth Management | WL6: Wealth Management | WM6: Credit Card | WN6: Credit Card | WO6: Mortgage | WP6: Auto Loan | WQ6: Auto Loan | WR6: Credit Card | WS6: Personal Loan | WT6: Wealth Management | WU6: Wealth Management | WV6: Credit Card | WW6: Personal Loan | WX6: Mortgage | WY6: Credit Card | WZ6: Credit Card | XA6: Wealth Management | XB6: Credit Card | XC6: Credit Card | XD6: Credit Card | XE6: Wealth Management | XF6: Mortgage | XG6: Mortgage | XH6: Credit Card | XI6: Wealth Management | XJ6: Mortgage | XK6: Mortgage | XL6: Mortgage | XM6: Wealth Management | XN6: Wealth Management | XO6: Credit Card | XP6: Auto Loan | XQ6: Mortgage | XR6: Auto Loan | XS6: Wealth Management | XT6: Wealth Management | XU6: Wealth Management | XV6: Auto Loan | XW6: Wealth Management | XX6: Credit Card | XY6: Wealth Management | XZ6: Personal Loan | YA6: Auto Loan | YB6: Personal Loan | YC6: Wealth Management | YD6: Credit Card | YE6: Mortgage | YF6: Wealth Management | YG6: Credit Card | YH6: Auto Loan | YI6: Personal Loan | YJ6: Personal Loan | YK6: Personal Loan | YL6: Auto Loan | YM6: Credit Card | YN6: Auto Loan | YO6: Personal Loan | YP6: Wealth Management | YQ6: Mortgage | YR6: Auto Loan | YS6: Auto Loan | YT6: Credit Card | YU6: Credit Card | YV6: Auto Loan | YW6: Personal Loan | YX6: Mortgage | YY6: Credit Card | YZ6: Personal Loan | ZA6: Wealth Management | ZB6: Credit Card | ZC6: Personal Loan | ZD6: Personal Loan | ZE6: Mortgage | ZF6: Mortgage | ZG6: Wealth Management | ZH6: Personal Loan | ZI6: Personal Loan | ZJ6: Mortgage | ZK6: Credit Card | ZL6: Credit Card | ZM6: Auto Loan | ZN6: Mortgage | ZO6: Auto Loan | ZP6: Mortgage | ZQ6: Wealth Management | ZR6: Personal Loan | ZS6: Wealth Management | ZT6: Mortgage | ZU6: Personal Loan | ZV6: Credit Card | ZW6: Credit Card | ZX6: Auto Loan | ZY6: Mortgage | ZZ6: Mortgage | AAA6: Credit Card | AAB6: Wealth Management | AAC6: Personal Loan | AAD6: Wealth Management | AAE6: Wealth Management | AAF6: Credit Card | AAG6: Credit Card | AAH6: Credit Card | AAI6: Auto Loan | AAJ6: Wealth Management | AAK6: Mortgage | AAL6: Personal Loan | AAM6: Auto Loan | AAN6: Mortgage | AAO6: Wealth Management | AAP6: Credit Card | AAQ6: Wealth Management | AAR6: Personal Loan | AAS6: Auto Loan | AAT6: Auto Loan | AAU6: Personal Loan | AAV6: Mortgage | AAW6: Mortgage | AAX6: Auto Loan | AAY6: Auto Loan | AAZ6: Credit Card | ABA6: Mortgage | ABB6: Personal Loan | ABC6: Mortgage | ABD6: Credit Card | ABE6: Auto Loan | ABF6: Auto Loan | ABG6: Credit Card | ABH6: Personal Loan | ABI6: Auto Loan | ABJ6: Wealth Management | ABK6: Auto Loan | ABL6: Wealth Management | ABM6: Credit Card | ABN6: Credit Card | ABO6: Auto Loan | ABP6: Mortgage | ABQ6: Wealth Management | ABR6: Personal Loan | ABS6: Auto Loan | ABT6: Personal Loan | ABU6: Auto Loan | ABV6: Mortgage | ABW6: Mortgage | ABX6: Mortgage | ABY6: Mortgage | ABZ6: Credit Card | ACA6: Credit Card | ACB6: Wealth Management | ACC6: Personal Loan | ACD6: Auto Loan | ACE6: Auto Loan | ACF6: Credit Card | ACG6: Auto Loan | ACH6: Credit Card | ACI6: Wealth Management | ACJ6: Personal Loan | ACK6: Wealth Management | ACL6: Mortgage | ACM6: Mortgage | ACN6: Mortgage | ACO6: Wealth Management | ACP6: Auto Loan | ACQ6: Personal Loan | ACR6: Mortgage | ACS6: Mortgage | ACT6: Mortgage | ACU6: Personal Loan | ACV6: Mortgage | ACW6: Personal Loan | ACX6: Mortgage | ACY6: Wealth Management | ACZ6: Wealth Management | ADA6: Personal Loan | ADB6: Wealth Management | ADC6: Personal Loan | ADD6: Wealth Management | ADE6: Wealth Management | ADF6: Personal Loan | ADG6: Auto Loan | ADH6: Wealth Management | ADI6: Mortgage | ADJ6: Auto Loan | ADK6: Personal Loan | ADL6: Auto Loan | ADM6: Credit Card | ADN6: Credit Card | ADO6: Wealth Management | ADP6: Wealth Management | ADQ6: Mortgage | ADR6: Auto Loan | ADS6: Credit Card | ADT6: Wealth Management | ADU6: Auto Loan | ADV6: Wealth Management | ADW6: Wealth Management | ADX6: Credit Card | ADY6: Credit Card | ADZ6: Wealth Management | AEA6: Personal Loan | AEB6: Wealth Management | AEC6: Wealth Management | AED6: Mortgage | AEE6: Mortgage | AEF6: Mortgage | AEG6: Personal Loan | AEH6: Personal Loan | AEI6: Wealth Management | AEJ6: Mortgage | AEK6: Personal Loan | AEL6: Credit Card | AEM6: Wealth Management | AEN6: Auto Loan | AEO6: Wealth Management | AEP6: Auto Loan | AEQ6: Mortgage | AER6: Auto Loan | AES6: Mortgage | AET6: Credit Card | AEU6: Auto Loan | AEV6: Wealth Management | AEW6: Mortgage | AEX6: Wealth Management | AEY6: Personal Loan | AEZ6: Mortgage | AFA6: Auto Loan | AFB6: Mortgage | AFC6: Wealth Management | AFD6: Credit Card | AFE6: Mortgage | AFF6: Auto Loan | AFG6: Personal Loan | AFH6: Credit Card | AFI6: Personal Loan | AFJ6: Mortgage | AFK6: Wealth Management | AFL6: Wealth Management | AFM6: Auto Loan | AFN6: Wealth Management | AFO6: Credit Card | AFP6: Wealth Management | AFQ6: Auto Loan | AFR6: Mortgage | AFS6: Mortgage | AFT6: Wealth Management | AFU6: Personal Loan | AFV6: Mortgage | AFW6: Wealth Management | AFX6: Auto Loan | AFY6: Wealth Management | AFZ6: Mortgage | AGA6: Auto Loan | AGB6: Wealth Management | AGC6: Credit Card | AGD6: Auto Loan | AGE6: Credit Card | AGF6: Personal Loan | AGG6: Auto Loan | AGH6: Credit Card | AGI6: Mortgage | AGJ6: Mortgage | AGK6: Personal Loan | AGL6: Auto Loan | AGM6: Auto Loan | AGN6: Auto Loan | AGO6: Personal Loan | AGP6: Auto Loan | AGQ6: Mortgage | AGR6: Credit Card | AGS6: Mortgage | AGT6: Mortgage | AGU6: Credit Card | AGV6: Mortgage | AGW6: Personal Loan | AGX6: Credit Card | AGY6: Mortgage | AGZ6: Wealth Management | AHA6: Mortgage | AHB6: Personal Loan | AHC6: Auto Loan | AHD6: Mortgage | AHE6: Auto Loan | AHF6: Wealth Management | AHG6: Mortgage | AHH6: Credit Card | AHI6: Auto Loan | AHJ6: Wealth Management | AHK6: Credit Card | AHL6: Credit Card | AHM6: Credit Card | AHN6: Credit Card | AHO6: Mortgage | AHP6: Mortgage | AHQ6: Mortgage | AHR6: Wealth Management | AHS6: Wealth Management | AHT6: Wealth Management | AHU6: Personal Loan | AHV6: Wealth Management | AHW6: Mortgage | AHX6: Mortgage | AHY6: Personal Loan | AHZ6: Personal Loan | AIA6: Wealth Management | AIB6: Auto Loan | AIC6: Personal Loan | AID6: Credit Card | AIE6: Mortgage | AIF6: Credit Card | AIG6: Mortgage | AIH6: Mortgage | AII6: Personal Loan | AIJ6: Personal Loan | AIK6: Credit Card | AIL6: Mortgage | AIM6: Credit Card | AIN6: Auto Loan | AIO6: Credit Card | AIP6: Wealth Management | AIQ6: Credit Card | AIR6: Wealth Management | AIS6: Wealth Management | AIT6: Wealth Management | AIU6: Auto Loan | AIV6: Credit Card | AIW6: Credit Card | AIX6: Auto Loan | AIY6: Mortgage | AIZ6: Personal Loan | AJA6: Credit Card | AJB6: Personal Loan | AJC6: Auto Loan | AJD6: Mortgage | AJE6: Mortgage | AJF6: Mortgage | AJG6: Auto Loan | AJH6: Wealth Management | AJI6: Wealth Management | AJJ6: Personal Loan | AJK6: Wealth Management | AJL6: Wealth Management | AJM6: Mortgage | AJN6: Mortgage | AJO6: Personal Loan | AJP6: Credit Card | AJQ6: Personal Loan | AJR6: Personal Loan | AJS6: Auto Loan | AJT6: Auto Loan | AJU6: Personal Loan | AJV6: Personal Loan | AJW6: Personal Loan | AJX6: Wealth Management | AJY6: Auto Loan | AJZ6: Personal Loan | AKA6: Mortgage | AKB6: Mortgage | AKC6: Wealth Management | AKD6: Wealth Management | AKE6: Credit Card | AKF6: Credit Card | AKG6: Credit Card | AKH6: Wealth Management | AKI6: Wealth Management | AKJ6: Wealth Management | AKK6: Mortgage | AKL6: Wealth Management | AKM6: Mortgage | AKN6: Credit Card | AKO6: Credit Card | AKP6: Credit Card | AKQ6: Personal Loan | AKR6: Personal Loan | AKS6: Auto Loan | AKT6: Auto Loan | AKU6: Auto Loan | AKV6: Personal Loan | AKW6: Personal Loan | AKX6: Auto Loan | AKY6: Auto Loan | AKZ6: Wealth Management | ALA6: Auto Loan | ALB6: Wealth Management | ALC6: Mortgage | ALD6: Personal Loan | ALE6: Auto Loan | ALF6: Personal Loan | ALG6: Personal Loan | ALH6: Personal Loan | ALI6: Mortgage | ALJ6: Credit Card | ALK6: Auto Loan | ALL6: Credit Card | ALM6: Credit Card
A7: Lead Source | B7: Walk-in | C7: Website | D7: Social Media | E7: Website | F7: Website | G7: Walk-in | H7: Website | I7: Walk-in | J7: Social Media | K7: Email Campaign | L7: Walk-in | M7: Social Media | N7: Email Campaign | O7: Referral | P7: Walk-in | Q7: Walk-in | R7: Referral | S7: Referral | T7: Walk-in | U7: Referral | V7: Website | W7: Email Campaign | X7: Email Campaign | Y7: Email Campaign | Z7: Website | AA7: Referral | AB7: Social Media | AC7: Referral | AD7: Walk-in | AE7: Email Campaign | AF7: Referral | AG7: Social Media | AH7: Walk-in | AI7: Website | AJ7: Website | AK7: Social Media | AL7: Walk-in | AM7: Email Campaign | AN7: Referral | AO7: Walk-in | AP7: Website | AQ7: Social Media | AR7: Social Media | AS7: Referral | AT7: Social Media | AU7: Social Media | AV7: Walk-in | AW7: Email Campaign | AX7: Referral | AY7: Walk-in | AZ7: Email Campaign | BA7: Walk-in | BB7: Walk-in | BC7: Social Media | BD7: Email Campaign | BE7: Referral | BF7: Referral | BG7: Email Campaign | BH7: Social Media | BI7: Website | BJ7: Walk-in | BK7: Social Media | BL7: Email Campaign | BM7: Walk-in | BN7: Referral | BO7: Website | BP7: Referral | BQ7: Email Campaign | BR7: Walk-in | BS7: Email Campaign | BT7: Walk-in | BU7: Social Media | BV7: Website | BW7: Social Media | BX7: Social Media | BY7: Email Campaign | BZ7: Website | CA7: Walk-in | CB7: Walk-in | CC7: Referral | CD7: Walk-in | CE7: Email Campaign | CF7: Social Media | CG7: Social Media | CH7: Social Media | CI7: Website | CJ7: Walk-in | CK7: Email Campaign | CL7: Website | CM7: Referral | CN7: Email Campaign | CO7: Email Campaign | CP7: Email Campaign | CQ7: Social Media | CR7: Email Campaign | CS7: Walk-in | CT7: Email Campaign | CU7: Social Media | CV7: Email Campaign | CW7: Referral | CX7: Referral | CY7: Social Media | CZ7: Walk-in | DA7: Walk-in | DB7: Website | DC7: Social Media | DD7: Email Campaign | DE7: Social Media | DF7: Website | DG7: Social Media | DH7: Social Media | DI7: Website | DJ7: Walk-in | DK7: Email Campaign | DL7: Website | DM7: Referral | DN7: Walk-in | DO7: Referral | DP7: Walk-in | DQ7: Email Campaign | DR7: Email Campaign | DS7: Social Media | DT7: Referral | DU7: Walk-in | DV7: Email Campaign | DW7: Website | DX7: Email Campaign | DY7: Website | DZ7: Walk-in | EA7: Email Campaign | EB7: Email Campaign | EC7: Walk-in | ED7: Email Campaign | EE7: Website | EF7: Email Campaign | EG7: Referral | EH7: Social Media | EI7: Website | EJ7: Referral | EK7: Walk-in | EL7: Website | EM7: Social Media | EN7: Social Media | EO7: Walk-in | EP7: Walk-in | EQ7: Website | ER7: Email Campaign | ES7: Walk-in | ET7: Email Campaign | EU7: Referral | EV7: Social Media | EW7: Email Campaign | EX7: Social Media | EY7: Email Campaign | EZ7: Referral | FA7: Walk-in | FB7: Referral | FC7: Walk-in | FD7: Walk-in | FE7: Social Media | FF7: Referral | FG7: Email Campaign | FH7: Referral | FI7: Social Media | FJ7: Walk-in | FK7: Social Media | FL7: Website | FM7: Website | FN7: Email Campaign | FO7: Social Media | FP7: Email Campaign | FQ7: Email Campaign | FR7: Website | FS7: Email Campaign | FT7: Website | FU7: Walk-in | FV7: Social Media | FW7: Email Campaign | FX7: Website | FY7: Referral | FZ7: Email Campaign | GA7: Walk-in | GB7: Walk-in | GC7: Referral | GD7: Website | GE7: Email Campaign | GF7: Website | GG7: Walk-in | GH7: Website | GI7: Walk-in | GJ7: Website | GK7: Referral | GL7: Social Media | GM7: Referral | GN7: Referral | GO7: Social Media | GP7: Social Media | GQ7: Email Campaign | GR7: Email Campaign | GS7: Referral | GT7: Referral | GU7: Walk-in | GV7: Walk-in | GW7: Email Campaign | GX7: Email Campaign | GY7: Walk-in | GZ7: Walk-in | HA7: Website | HB7: Website | HC7: Walk-in | HD7: Website | HE7: Social Media | HF7: Email Campaign | HG7: Email Campaign | HH7: Walk-in | HI7: Referral | HJ7: Walk-in | HK7: Website | HL7: Referral | HM7: Website | HN7: Social Media | HO7: Website | HP7: Social Media | HQ7: Social Media | HR7: Website | HS7: Website | HT7: Social Media | HU7: Referral | HV7: Social Media | HW7: Email Campaign | HX7: Social Media | HY7: Referral | HZ7: Email Campaign | IA7: Walk-in | IB7: Walk-in | IC7: Referral | ID7: Social Media | IE7: Website | IF7: Referral | IG7: Email Campaign | IH7: Email Campaign | II7: Walk-in | IJ7: Email Campaign | IK7: Referral | IL7: Email Campaign | IM7: Referral | IN7: Website | IO7: Walk-in | IP7: Email Campaign | IQ7: Referral | IR7: Social Media | IS7: Walk-in | IT7: Website | IU7: Referral | IV7: Website | IW7: Website | IX7: Email Campaign | IY7: Email Campaign | IZ7: Referral | JA7: Social Media | JB7: Referral | JC7: Social Media | JD7: Website | JE7: Walk-in | JF7: Referral | JG7: Referral | JH7: Social Media | JI7: Website | JJ7: Website | JK7: Social Media | JL7: Website | JM7: Email Campaign | JN7: Walk-in | JO7: Referral | JP7: Walk-in | JQ7: Referral | JR7: Email Campaign | JS7: Website | JT7: Social Media | JU7: Email Campaign | JV7: Walk-in | JW7: Social Media | JX7: Website | JY7: Email Campaign | JZ7: Social Media | KA7: Email Campaign | KB7: Email Campaign | KC7: Website | KD7: Referral | KE7: Social Media | KF7: Website | KG7: Email Campaign | KH7: Website | KI7: Referral | KJ7: Social Media | KK7: Referral | KL7: Walk-in | KM7: Social Media | KN7: Referral | KO7: Email Campaign | KP7: Social Media | KQ7: Social Media | KR7: Website | KS7: Email Campaign | KT7: Walk-in | KU7: Referral | KV7: Website | KW7: Referral | KX7: Walk-in | KY7: Walk-in | KZ7: Social Media | LA7: Walk-in | LB7: Referral | LC7: Email Campaign | LD7: Email Campaign | LE7: Social Media | LF7: Referral | LG7: Referral | LH7: Walk-in | LI7: Referral | LJ7: Website | LK7: Walk-in | LL7: Website | LM7: Social Media | LN7: Email Campaign | LO7: Social Media | LP7: Email Campaign | LQ7: Social Media | LR7: Referral | LS7: Website | LT7: Email Campaign | LU7: Walk-in | LV7: Website | LW7: Walk-in | LX7: Website | LY7: Website | LZ7: Social Media | MA7: Email Campaign | MB7: Email Campaign | MC7: Website | MD7: Referral | ME7: Referral | MF7: Walk-in | MG7: Walk-in | MH7: Social Media | MI7: Website | MJ7: Walk-in | MK7: Walk-in | ML7: Website | MM7: Social Media | MN7: Walk-in | MO7: Social Media | MP7: Email Campaign | MQ7: Social Media | MR7: Referral | MS7: Referral | MT7: Social Media | MU7: Referral | MV7: Email Campaign | MW7: Website | MX7: Referral | MY7: Referral | MZ7: Social Media | NA7: Email Campaign | NB7: Website | NC7: Social Media | ND7: Social Media | NE7: Email Campaign | NF7: Website | NG7: Email Campaign | NH7: Website | NI7: Email Campaign | NJ7: Social Media | NK7: Social Media | NL7: Walk-in | NM7: Referral | NN7: Email Campaign | NO7: Walk-in | NP7: Referral | NQ7: Email Campaign | NR7: Website | NS7: Referral | NT7: Social Media | NU7: Walk-in | NV7: Referral | NW7: Referral | NX7: Social Media | NY7: Email Campaign | NZ7: Website | OA7: Social Media | OB7: Website | OC7: Email Campaign | OD7: Referral | OE7: Website | OF7: Walk-in | OG7: Walk-in | OH7: Social Media | OI7: Email Campaign | OJ7: Social Media | OK7: Social Media | OL7: Social Media | OM7: Walk-in | ON7: Walk-in | OO7: Social Media | OP7: Walk-in | OQ7: Email Campaign | OR7: Social Media | OS7: Walk-in | OT7: Website | OU7: Social Media | OV7: Social Media | OW7: Email Campaign | OX7: Referral | OY7: Referral | OZ7: Email Campaign | PA7: Email Campaign | PB7: Email Campaign | PC7: Referral | PD7: Email Campaign | PE7: Walk-in | PF7: Social Media | PG7: Social Media | PH7: Website | PI7: Website | PJ7: Social Media | PK7: Walk-in | PL7: Referral | PM7: Referral | PN7: Walk-in | PO7: Referral | PP7: Email Campaign | PQ7: Social Media | PR7: Social Media | PS7: Walk-in | PT7: Referral | PU7: Website | PV7: Website | PW7: Referral | PX7: Website | PY7: Walk-in | PZ7: Walk-in | QA7: Referral | QB7: Website | QC7: Walk-in | QD7: Walk-in | QE7: Email Campaign | QF7: Email Campaign | QG7: Walk-in | QH7: Referral | QI7: Social Media | QJ7: Social Media | QK7: Walk-in | QL7: Walk-in | QM7: Walk-in | QN7: Referral | QO7: Email Campaign | QP7: Walk-in | QQ7: Walk-in | QR7: Website | QS7: Referral | QT7: Walk-in | QU7: Website | QV7: Social Media | QW7: Walk-in | QX7: Walk-in | QY7: Website | QZ7: Referral | RA7: Walk-in | RB7: Social Media | RC7: Walk-in | RD7: Social Media | RE7: Email Campaign | RF7: Email Campaign | RG7: Social Media | RH7: Referral | RI7: Walk-in | RJ7: Walk-in | RK7: Email Campaign | RL7: Social Media | RM7: Walk-in | RN7: Walk-in | RO7: Referral | RP7: Website | RQ7: Email Campaign | RR7: Email Campaign | RS7: Website | RT7: Walk-in | RU7: Referral | RV7: Referral | RW7: Email Campaign | RX7: Referral | RY7: Website | RZ7: Walk-in | SA7: Website | SB7: Social Media | SC7: Email Campaign | SD7: Referral | SE7: Social Media | SF7: Referral | SG7: Walk-in | SH7: Walk-in | SI7: Walk-in | SJ7: Referral | SK7: Social Media | SL7: Walk-in | SM7: Social Media | SN7: Referral | SO7: Social Media | SP7: Referral | SQ7: Referral | SR7: Email Campaign | SS7: Referral | ST7: Referral | SU7: Website | SV7: Walk-in | SW7: Email Campaign | SX7: Email Campaign | SY7: Email Campaign | SZ7: Website | TA7: Referral | TB7: Walk-in | TC7: Social Media | TD7: Referral | TE7: Website | TF7: Referral | TG7: Referral | TH7: Website | TI7: Email Campaign | TJ7: Email Campaign | TK7: Walk-in | TL7: Walk-in | TM7: Email Campaign | TN7: Social Media | TO7: Referral | TP7: Social Media | TQ7: Referral | TR7: Email Campaign | TS7: Walk-in | TT7: Walk-in | TU7: Social Media | TV7: Walk-in | TW7: Email Campaign | TX7: Social Media | TY7: Referral | TZ7: Walk-in | UA7: Website | UB7: Walk-in | UC7: Referral | UD7: Social Media | UE7: Referral | UF7: Website | UG7: Email Campaign | UH7: Walk-in | UI7: Social Media | UJ7: Email Campaign | UK7: Referral | UL7: Social Media | UM7: Email Campaign | UN7: Social Media | UO7: Website | UP7: Website | UQ7: Walk-in | UR7: Walk-in | US7: Website | UT7: Social Media | UU7: Website | UV7: Walk-in | UW7: Website | UX7: Website | UY7: Social Media | UZ7: Email Campaign | VA7: Walk-in | VB7: Social Media | VC7: Website | VD7: Website | VE7: Email Campaign | VF7: Walk-in | VG7: Walk-in | VH7: Referral | VI7: Walk-in | VJ7: Email Campaign | VK7: Referral | VL7: Referral | VM7: Website | VN7: Website | VO7: Walk-in | VP7: Referral | VQ7: Website | VR7: Email Campaign | VS7: Website | VT7: Website | VU7: Referral | VV7: Referral | VW7: Social Media | VX7: Email Campaign | VY7: Referral | VZ7: Walk-in | WA7: Email Campaign | WB7: Email Campaign | WC7: Referral | WD7: Email Campaign | WE7: Referral | WF7: Website | WG7: Social Media | WH7: Website | WI7: Referral | WJ7: Referral | WK7: Website | WL7: Walk-in | WM7: Walk-in | WN7: Walk-in | WO7: Referral | WP7: Email Campaign | WQ7: Referral | WR7: Email Campaign | WS7: Website | WT7: Social Media | WU7: Email Campaign | WV7: Walk-in | WW7: Referral | WX7: Website | WY7: Walk-in | WZ7: Website | XA7: Social Media | XB7: Referral | XC7: Referral | XD7: Social Media | XE7: Referral | XF7: Email Campaign | XG7: Website | XH7: Walk-in | XI7: Social Media | XJ7: Email Campaign | XK7: Walk-in | XL7: Walk-in | XM7: Social Media | XN7: Email Campaign | XO7: Walk-in | XP7: Walk-in | XQ7: Email Campaign | XR7: Referral | XS7: Walk-in | XT7: Website | XU7: Email Campaign | XV7: Walk-in | XW7: Social Media | XX7: Website | XY7: Walk-in | XZ7: Website | YA7: Website | YB7: Referral | YC7: Website | YD7: Referral | YE7: Email Campaign | YF7: Referral | YG7: Social Media | YH7: Walk-in | YI7: Email Campaign | YJ7: Email Campaign | YK7: Social Media | YL7: Referral | YM7: Walk-in | YN7: Referral | YO7: Website | YP7: Referral | YQ7: Email Campaign | YR7: Walk-in | YS7: Referral | YT7: Walk-in | YU7: Walk-in | YV7: Website | YW7: Website | YX7: Email Campaign | YY7: Social Media | YZ7: Walk-in | ZA7: Social Media | ZB7: Email Campaign | ZC7: Walk-in | ZD7: Walk-in | ZE7: Social Media | ZF7: Referral | ZG7: Website | ZH7: Referral | ZI7: Social Media | ZJ7: Website | ZK7: Referral | ZL7: Website | ZM7: Walk-in | ZN7: Referral | ZO7: Website | ZP7: Website | ZQ7: Website | ZR7: Referral | ZS7: Email Campaign | ZT7: Referral | ZU7: Social Media | ZV7: Referral | ZW7: Website | ZX7: Walk-in | ZY7: Referral | ZZ7: Referral | AAA7: Website | AAB7: Walk-in | AAC7: Walk-in | AAD7: Social Media | AAE7: Referral | AAF7: Walk-in | AAG7: Walk-in | AAH7: Email Campaign | AAI7: Email Campaign | AAJ7: Walk-in | AAK7: Social Media | AAL7: Walk-in | AAM7: Website | AAN7: Referral | AAO7: Social Media | AAP7: Website | AAQ7: Social Media | AAR7: Website | AAS7: Referral | AAT7: Referral | AAU7: Email Campaign | AAV7: Website | AAW7: Email Campaign | AAX7: Website | AAY7: Email Campaign | AAZ7: Referral | ABA7: Social Media | ABB7: Email Campaign | ABC7: Website | ABD7: Website | ABE7: Referral | ABF7: Website | ABG7: Walk-in | ABH7: Social Media | ABI7: Email Campaign | ABJ7: Social Media | ABK7: Referral | ABL7: Email Campaign | ABM7: Email Campaign | ABN7: Walk-in | ABO7: Referral | ABP7: Website | ABQ7: Walk-in | ABR7: Walk-in | ABS7: Social Media | ABT7: Social Media | ABU7: Social Media | ABV7: Walk-in | ABW7: Website | ABX7: Email Campaign | ABY7: Social Media | ABZ7: Website | ACA7: Referral | ACB7: Social Media | ACC7: Email Campaign | ACD7: Referral | ACE7: Referral | ACF7: Email Campaign | ACG7: Social Media | ACH7: Walk-in | ACI7: Email Campaign | ACJ7: Email Campaign | ACK7: Email Campaign | ACL7: Referral | ACM7: Website | ACN7: Walk-in | ACO7: Social Media | ACP7: Social Media | ACQ7: Website | ACR7: Email Campaign | ACS7: Walk-in | ACT7: Social Media | ACU7: Social Media | ACV7: Email Campaign | ACW7: Website | ACX7: Walk-in | ACY7: Website | ACZ7: Website | ADA7: Walk-in | ADB7: Walk-in | ADC7: Social Media | ADD7: Social Media | ADE7: Walk-in | ADF7: Referral | ADG7: Social Media | ADH7: Referral | ADI7: Walk-in | ADJ7: Social Media | ADK7: Website | ADL7: Walk-in | ADM7: Email Campaign | ADN7: Referral | ADO7: Walk-in | ADP7: Walk-in | ADQ7: Social Media | ADR7: Social Media | ADS7: Social Media | ADT7: Email Campaign | ADU7: Social Media | ADV7: Walk-in | ADW7: Social Media | ADX7: Website | ADY7: Social Media | ADZ7: Email Campaign | AEA7: Website | AEB7: Walk-in | AEC7: Walk-in | AED7: Referral | AEE7: Website | AEF7: Referral | AEG7: Website | AEH7: Website | AEI7: Email Campaign | AEJ7: Referral | AEK7: Email Campaign | AEL7: Website | AEM7: Walk-in | AEN7: Website | AEO7: Email Campaign | AEP7: Referral | AEQ7: Referral | AER7: Email Campaign | AES7: Referral | AET7: Social Media | AEU7: Walk-in | AEV7: Walk-in | AEW7: Walk-in | AEX7: Referral | AEY7: Referral | AEZ7: Website | AFA7: Website | AFB7: Walk-in | AFC7: Social Media | AFD7: Website | AFE7: Website | AFF7: Referral | AFG7: Social Media | AFH7: Walk-in | AFI7: Website | AFJ7: Social Media | AFK7: Social Media | AFL7: Walk-in | AFM7: Social Media | AFN7: Social Media | AFO7: Social Media | AFP7: Website | AFQ7: Walk-in | AFR7: Social Media | AFS7: Social Media | AFT7: Website | AFU7: Walk-in | AFV7: Referral | AFW7: Website | AFX7: Walk-in | AFY7: Social Media | AFZ7: Walk-in | AGA7: Walk-in | AGB7: Walk-in | AGC7: Referral | AGD7: Walk-in | AGE7: Referral | AGF7: Social Media | AGG7: Referral | AGH7: Social Media | AGI7: Social Media | AGJ7: Referral | AGK7: Website | AGL7: Email Campaign | AGM7: Walk-in | AGN7: Email Campaign | AGO7: Walk-in | AGP7: Walk-in | AGQ7: Social Media | AGR7: Walk-in | AGS7: Walk-in | AGT7: Referral | AGU7: Email Campaign | AGV7: Referral | AGW7: Walk-in | AGX7: Social Media | AGY7: Referral | AGZ7: Referral | AHA7: Website | AHB7: Walk-in | AHC7: Social Media | AHD7: Referral | AHE7: Referral | AHF7: Social Media | AHG7: Walk-in | AHH7: Website | AHI7: Referral | AHJ7: Website | AHK7: Email Campaign | AHL7: Walk-in | AHM7: Email Campaign | AHN7: Email Campaign | AHO7: Email Campaign | AHP7: Walk-in | AHQ7: Walk-in | AHR7: Social Media | AHS7: Website | AHT7: Website | AHU7: Social Media | AHV7: Social Media | AHW7: Email Campaign | AHX7: Social Media | AHY7: Referral | AHZ7: Website | AIA7: Social Media | AIB7: Referral | AIC7: Referral | AID7: Referral | AIE7: Referral | AIF7: Email Campaign | AIG7: Referral | AIH7: Email Campaign | AII7: Email Campaign | AIJ7: Referral | AIK7: Website | AIL7: Referral | AIM7: Referral | AIN7: Referral | AIO7: Website | AIP7: Walk-in | AIQ7: Walk-in | AIR7: Email Campaign | AIS7: Email Campaign | AIT7: Website | AIU7: Social Media | AIV7: Walk-in | AIW7: Email Campaign | AIX7: Walk-in | AIY7: Website | AIZ7: Website | AJA7: Social Media | AJB7: Social Media | AJC7: Website | AJD7: Email Campaign | AJE7: Walk-in | AJF7: Referral | AJG7: Social Media | AJH7: Referral | AJI7: Email Campaign | AJJ7: Social Media | AJK7: Referral | AJL7: Email Campaign | AJM7: Walk-in | AJN7: Email Campaign | AJO7: Social Media | AJP7: Website | AJQ7: Walk-in | AJR7: Referral | AJS7: Social Media | AJT7: Website | AJU7: Email Campaign | AJV7: Website | AJW7: Social Media | AJX7: Social Media | AJY7: Website | AJZ7: Email Campaign | AKA7: Website | AKB7: Social Media | AKC7: Social Media | AKD7: Referral | AKE7: Referral | AKF7: Walk-in | AKG7: Social Media | AKH7: Referral | AKI7: Website | AKJ7: Email Campaign | AKK7: Website | AKL7: Email Campaign | AKM7: Referral | AKN7: Walk-in | AKO7: Website | AKP7: Website | AKQ7: Website | AKR7: Email Campaign | AKS7: Referral | AKT7: Website | AKU7: Website | AKV7: Walk-in | AKW7: Walk-in | AKX7: Referral | AKY7: Referral | AKZ7: Social Media | ALA7: Walk-in | ALB7: Social Media | ALC7: Email Campaign | ALD7: Social Media | ALE7: Website | ALF7: Social Media | ALG7: Referral | ALH7: Email Campaign | ALI7: Website | ALJ7: Social Media | ALK7: Email Campaign | ALL7: Email Campaign | ALM7: Website
A8: Customer Segment | B8: Retail | C8: High Net Worth | D8: High Net Worth | E8: Retail | F8: High Net Worth | G8: High Net Worth | H8: Retail | I8: Retail | J8: Corporate | K8: SME | L8: SME | M8: Retail | N8: Retail | O8: High Net Worth | P8: Corporate | Q8: Corporate | R8: Retail | S8: High Net Worth | T8: High Net Worth | U8: SME | V8: SME | W8: High Net Worth | X8: SME | Y8: Retail | Z8: High Net Worth | AA8: SME | AB8: Corporate | AC8: High Net Worth | AD8: High Net Worth | AE8: Corporate | AF8: Retail | AG8: Corporate | AH8: High Net Worth | AI8: Retail | AJ8: SME | AK8: SME | AL8: SME | AM8: High Net Worth | AN8: Corporate | AO8: Retail | AP8: SME | AQ8: Retail | AR8: High Net Worth | AS8: SME | AT8: High Net Worth | AU8: Corporate | AV8: High Net Worth | AW8: High Net Worth | AX8: Corporate | AY8: Retail | AZ8: Corporate | BA8: Corporate | BB8: High Net Worth | BC8: Retail | BD8: SME | BE8: Corporate | BF8: Retail | BG8: Corporate | BH8: Corporate | BI8: Corporate | BJ8: Corporate | BK8: High Net Worth | BL8: Retail | BM8: Retail | BN8: Retail | BO8: Corporate | BP8: High Net Worth | BQ8: Corporate | BR8: Corporate | BS8: Retail | BT8: Corporate | BU8: SME | BV8: Corporate | BW8: SME | BX8: Corporate | BY8: High Net Worth | BZ8: High Net Worth | CA8: Retail | CB8: Corporate | CC8: SME | CD8: SME | CE8: Corporate | CF8: SME | CG8: High Net Worth | CH8: SME | CI8: Retail | CJ8: High Net Worth | CK8: High Net Worth | CL8: High Net Worth | CM8: Corporate | CN8: Corporate | CO8: High Net Worth | CP8: Corporate | CQ8: SME | CR8: Corporate | CS8: Corporate | CT8: High Net Worth | CU8: Retail | CV8: Retail | CW8: Retail | CX8: SME | CY8: Corporate | CZ8: Retail | DA8: High Net Worth | DB8: Retail | DC8: Retail | DD8: Corporate | DE8: Corporate | DF8: Corporate | DG8: SME | DH8: SME | DI8: Retail | DJ8: Corporate | DK8: Retail | DL8: High Net Worth | DM8: High Net Worth | DN8: Corporate | DO8: Corporate | DP8: High Net Worth | DQ8: Corporate | DR8: SME | DS8: SME | DT8: Corporate | DU8: High Net Worth | DV8: Retail | DW8: Corporate | DX8: Corporate | DY8: Retail | DZ8: Corporate | EA8: Retail | EB8: High Net Worth | EC8: SME | ED8: High Net Worth | EE8: SME | EF8: Retail | EG8: SME | EH8: High Net Worth | EI8: SME | EJ8: Retail | EK8: SME | EL8: Corporate | EM8: High Net Worth | EN8: Corporate | EO8: Retail | EP8: SME | EQ8: Corporate | ER8: Corporate | ES8: SME | ET8: SME | EU8: High Net Worth | EV8: Corporate | EW8: Corporate | EX8: Retail | EY8: High Net Worth | EZ8: Retail | FA8: Corporate | FB8: Retail | FC8: Corporate | FD8: Corporate | FE8: Retail | FF8: Retail | FG8: SME | FH8: SME | FI8: SME | FJ8: Corporate | FK8: Retail | FL8: High Net Worth | FM8: Corporate | FN8: High Net Worth | FO8: Retail | FP8: Corporate | FQ8: High Net Worth | FR8: High Net Worth | FS8: SME | FT8: SME | FU8: SME | FV8: Corporate | FW8: Retail | FX8: Retail | FY8: SME | FZ8: SME | GA8: SME | GB8: High Net Worth | GC8: SME | GD8: High Net Worth | GE8: Retail | GF8: Corporate | GG8: Corporate | GH8: Corporate | GI8: Corporate | GJ8: High Net Worth | GK8: High Net Worth | GL8: SME | GM8: High Net Worth | GN8: SME | GO8: SME | GP8: Corporate | GQ8: High Net Worth | GR8: High Net Worth | GS8: SME | GT8: SME | GU8: Retail | GV8: Retail | GW8: SME | GX8: Retail | GY8: Retail | GZ8: SME | HA8: SME | HB8: High Net Worth | HC8: SME | HD8: SME | HE8: Corporate | HF8: High Net Worth | HG8: High Net Worth | HH8: High Net Worth | HI8: Corporate | HJ8: SME | HK8: High Net Worth | HL8: High Net Worth | HM8: Retail | HN8: High Net Worth | HO8: SME | HP8: SME | HQ8: Retail | HR8: High Net Worth | HS8: High Net Worth | HT8: High Net Worth | HU8: Corporate | HV8: High Net Worth | HW8: SME | HX8: SME | HY8: Corporate | HZ8: Corporate | IA8: High Net Worth | IB8: Retail | IC8: Corporate | ID8: Corporate | IE8: High Net Worth | IF8: High Net Worth | IG8: Corporate | IH8: Retail | II8: Corporate | IJ8: High Net Worth | IK8: High Net Worth | IL8: Corporate | IM8: Retail | IN8: Corporate | IO8: Corporate | IP8: High Net Worth | IQ8: Retail | IR8: SME | IS8: Retail | IT8: Corporate | IU8: Corporate | IV8: Corporate | IW8: Retail | IX8: High Net Worth | IY8: Corporate | IZ8: Corporate | JA8: Retail | JB8: SME | JC8: SME | JD8: High Net Worth | JE8: High Net Worth | JF8: Corporate | JG8: Retail | JH8: Corporate | JI8: High Net Worth | JJ8: Retail | JK8: Retail | JL8: High Net Worth | JM8: SME | JN8: SME | JO8: Retail | JP8: Corporate | JQ8: SME | JR8: Corporate | JS8: SME | JT8: SME | JU8: Corporate | JV8: High Net Worth | JW8: SME | JX8: SME | JY8: Corporate | JZ8: High Net Worth | KA8: SME | KB8: SME | KC8: High Net Worth | KD8: SME | KE8: High Net Worth | KF8: High Net Worth | KG8: Corporate | KH8: Retail | KI8: High Net Worth | KJ8: Corporate | KK8: Retail | KL8: SME | KM8: Retail | KN8: High Net Worth | KO8: High Net Worth | KP8: High Net Worth | KQ8: High Net Worth | KR8: High Net Worth | KS8: Corporate | KT8: High Net Worth | KU8: Corporate | KV8: SME | KW8: High Net Worth | KX8: High Net Worth | KY8: Retail | KZ8: SME | LA8: High Net Worth | LB8: High Net Worth | LC8: SME | LD8: Corporate | LE8: High Net Worth | LF8: Retail | LG8: High Net Worth | LH8: Retail | LI8: Retail | LJ8: High Net Worth | LK8: High Net Worth | LL8: Retail | LM8: SME | LN8: SME | LO8: High Net Worth | LP8: Corporate | LQ8: SME | LR8: High Net Worth | LS8: SME | LT8: Corporate | LU8: High Net Worth | LV8: Corporate | LW8: High Net Worth | LX8: Corporate | LY8: SME | LZ8: SME | MA8: Corporate | MB8: Corporate | MC8: Corporate | MD8: High Net Worth | ME8: SME | MF8: High Net Worth | MG8: SME | MH8: Retail | MI8: High Net Worth | MJ8: SME | MK8: SME | ML8: High Net Worth | MM8: High Net Worth | MN8: SME | MO8: High Net Worth | MP8: Corporate | MQ8: High Net Worth | MR8: High Net Worth | MS8: High Net Worth | MT8: SME | MU8: Corporate | MV8: Retail | MW8: Retail | MX8: Corporate | MY8: Corporate | MZ8: Corporate | NA8: SME | NB8: Retail | NC8: Corporate | ND8: SME | NE8: Retail | NF8: High Net Worth | NG8: SME | NH8: Retail | NI8: SME | NJ8: Retail | NK8: Retail | NL8: High Net Worth | NM8: SME | NN8: Corporate | NO8: High Net Worth | NP8: High Net Worth | NQ8: Retail | NR8: Corporate | NS8: SME | NT8: Corporate | NU8: Corporate | NV8: Corporate | NW8: Corporate | NX8: Corporate | NY8: Retail | NZ8: Retail | OA8: High Net Worth | OB8: Retail | OC8: High Net Worth | OD8: High Net Worth | OE8: SME | OF8: Corporate | OG8: Retail | OH8: SME | OI8: Retail | OJ8: High Net Worth | OK8: Retail | OL8: Corporate | OM8: High Net Worth | ON8: High Net Worth | OO8: SME | OP8: Corporate | OQ8: High Net Worth | OR8: Corporate | OS8: Retail | OT8: Corporate | OU8: High Net Worth | OV8: SME | OW8: High Net Worth | OX8: Corporate | OY8: Corporate | OZ8: High Net Worth | PA8: Corporate | PB8: Retail | PC8: High Net Worth | PD8: SME | PE8: High Net Worth | PF8: Retail | PG8: Retail | PH8: Retail | PI8: Retail | PJ8: Retail | PK8: SME | PL8: Corporate | PM8: Retail | PN8: Retail | PO8: High Net Worth | PP8: SME | PQ8: SME | PR8: Corporate | PS8: SME | PT8: High Net Worth | PU8: High Net Worth | PV8: Corporate | PW8: High Net Worth | PX8: Retail | PY8: Retail | PZ8: High Net Worth | QA8: Corporate | QB8: SME | QC8: Corporate | QD8: SME | QE8: High Net Worth | QF8: High Net Worth | QG8: Retail | QH8: SME | QI8: Corporate | QJ8: High Net Worth | QK8: Corporate | QL8: Retail | QM8: SME | QN8: SME | QO8: High Net Worth | QP8: SME | QQ8: High Net Worth | QR8: Retail | QS8: SME | QT8: High Net Worth | QU8: Corporate | QV8: High Net Worth | QW8: SME | QX8: Retail | QY8: SME | QZ8: SME | RA8: High Net Worth | RB8: Corporate | RC8: SME | RD8: Corporate | RE8: High Net Worth | RF8: Corporate | RG8: High Net Worth | RH8: Retail | RI8: Corporate | RJ8: Corporate | RK8: Retail | RL8: Corporate | RM8: Retail | RN8: SME | RO8: High Net Worth | RP8: Retail | RQ8: Corporate | RR8: Retail | RS8: Corporate | RT8: SME | RU8: Retail | RV8: SME | RW8: High Net Worth | RX8: Corporate | RY8: Corporate | RZ8: SME | SA8: High Net Worth | SB8: Retail | SC8: Retail | SD8: Corporate | SE8: SME | SF8: SME | SG8: Retail | SH8: High Net Worth | SI8: High Net Worth | SJ8: Retail | SK8: Retail | SL8: SME | SM8: High Net Worth | SN8: Retail | SO8: Retail | SP8: Corporate | SQ8: Retail | SR8: Retail | SS8: High Net Worth | ST8: SME | SU8: High Net Worth | SV8: SME | SW8: Corporate | SX8: Retail | SY8: Corporate | SZ8: SME | TA8: High Net Worth | TB8: High Net Worth | TC8: Corporate | TD8: SME | TE8: Corporate | TF8: Corporate | TG8: Retail | TH8: Corporate | TI8: Retail | TJ8: Retail | TK8: High Net Worth | TL8: Retail | TM8: Retail | TN8: High Net Worth | TO8: Corporate | TP8: SME | TQ8: SME | TR8: SME | TS8: Corporate | TT8: Retail | TU8: SME | TV8: Corporate | TW8: Retail | TX8: High Net Worth | TY8: SME | TZ8: Retail | UA8: SME | UB8: SME | UC8: SME | UD8: Retail | UE8: Corporate | UF8: Retail | UG8: SME | UH8: Retail | UI8: High Net Worth | UJ8: Corporate | UK8: Retail | UL8: High Net Worth | UM8: Corporate | UN8: High Net Worth | UO8: Corporate | UP8: Retail | UQ8: High Net Worth | UR8: SME | US8: High Net Worth | UT8: Corporate | UU8: Retail | UV8: Corporate | UW8: High Net Worth | UX8: High Net Worth | UY8: SME | UZ8: Retail | VA8: Retail | VB8: High Net Worth | VC8: Retail | VD8: SME | VE8: Corporate | VF8: Retail | VG8: High Net Worth | VH8: Corporate | VI8: Corporate | VJ8: SME | VK8: High Net Worth | VL8: Retail | VM8: High Net Worth | VN8: Corporate | VO8: High Net Worth | VP8: Retail | VQ8: Retail | VR8: SME | VS8: Retail | VT8: Retail | VU8: High Net Worth | VV8: High Net Worth | VW8: Corporate | VX8: SME | VY8: High Net Worth | VZ8: Retail | WA8: Corporate | WB8: High Net Worth | WC8: SME | WD8: SME | WE8: Corporate | WF8: Corporate | WG8: Corporate | WH8: Corporate | WI8: Corporate | WJ8: Retail | WK8: Retail | WL8: High Net Worth | WM8: SME | WN8: Retail | WO8: Retail | WP8: Retail | WQ8: High Net Worth | WR8: Corporate | WS8: High Net Worth | WT8: SME | WU8: SME | WV8: SME | WW8: SME | WX8: Retail | WY8: Retail | WZ8: High Net Worth | XA8: Corporate | XB8: SME | XC8: High Net Worth | XD8: Retail | XE8: Retail | XF8: Corporate | XG8: Corporate | XH8: Corporate | XI8: High Net Worth | XJ8: Retail | XK8: Retail | XL8: Corporate | XM8: SME | XN8: Corporate | XO8: High Net Worth | XP8: Corporate | XQ8: Corporate | XR8: High Net Worth | XS8: Corporate | XT8: Retail | XU8: SME | XV8: Corporate | XW8: High Net Worth | XX8: SME | XY8: High Net Worth | XZ8: SME | YA8: SME | YB8: Corporate | YC8: Retail | YD8: Corporate | YE8: High Net Worth | YF8: High Net Worth | YG8: SME | YH8: SME | YI8: Retail | YJ8: Corporate | YK8: High Net Worth | YL8: SME | YM8: Retail | YN8: High Net Worth | YO8: SME | YP8: High Net Worth | YQ8: Retail | YR8: Retail | YS8: High Net Worth | YT8: Corporate | YU8: High Net Worth | YV8: SME | YW8: Corporate | YX8: SME | YY8: High Net Worth | YZ8: Corporate | ZA8: SME | ZB8: High Net Worth | ZC8: High Net Worth | ZD8: Corporate | ZE8: High Net Worth | ZF8: Retail | ZG8: SME | ZH8: SME | ZI8: High Net Worth | ZJ8: High Net Worth | ZK8: Retail | ZL8: Corporate | ZM8: High Net Worth | ZN8: High Net Worth | ZO8: High Net Worth | ZP8: High Net Worth | ZQ8: SME | ZR8: High Net Worth | ZS8: SME | ZT8: High Net Worth | ZU8: Corporate | ZV8: Retail | ZW8: Corporate | ZX8: High Net Worth | ZY8: High Net Worth | ZZ8: High Net Worth | AAA8: Corporate | AAB8: High Net Worth | AAC8: Corporate | AAD8: SME | AAE8: Retail | AAF8: Retail | AAG8: Corporate | AAH8: SME | AAI8: Corporate | AAJ8: SME | AAK8: High Net Worth | AAL8: SME | AAM8: SME | AAN8: SME | AAO8: Retail | AAP8: SME | AAQ8: High Net Worth | AAR8: High Net Worth | AAS8: High Net Worth | AAT8: SME | AAU8: Corporate | AAV8: Corporate | AAW8: High Net Worth | AAX8: Retail | AAY8: Corporate | AAZ8: SME | ABA8: Corporate | ABB8: High Net Worth | ABC8: Retail | ABD8: Corporate | ABE8: Corporate | ABF8: High Net Worth | ABG8: Retail | ABH8: Retail | ABI8: High Net Worth | ABJ8: SME | ABK8: Corporate | ABL8: SME | ABM8: Corporate | ABN8: Corporate | ABO8: SME | ABP8: High Net Worth | ABQ8: High Net Worth | ABR8: Corporate | ABS8: High Net Worth | ABT8: Corporate | ABU8: High Net Worth | ABV8: Corporate | ABW8: High Net Worth | ABX8: Retail | ABY8: SME | ABZ8: Retail | ACA8: SME | ACB8: SME | ACC8: Corporate | ACD8: SME | ACE8: Retail | ACF8: Retail | ACG8: High Net Worth | ACH8: Retail | ACI8: High Net Worth | ACJ8: SME | ACK8: Retail | ACL8: SME | ACM8: Retail | ACN8: Retail | ACO8: High Net Worth | ACP8: SME | ACQ8: Retail | ACR8: Corporate | ACS8: SME | ACT8: SME | ACU8: SME | ACV8: High Net Worth | ACW8: Corporate | ACX8: SME | ACY8: Retail | ACZ8: Retail | ADA8: High Net Worth | ADB8: Retail | ADC8: SME | ADD8: Retail | ADE8: SME | ADF8: Retail | ADG8: Corporate | ADH8: High Net Worth | ADI8: High Net Worth | ADJ8: Corporate | ADK8: Corporate | ADL8: High Net Worth | ADM8: Corporate | ADN8: SME | ADO8: Retail | ADP8: High Net Worth | ADQ8: Corporate | ADR8: SME | ADS8: High Net Worth | ADT8: Corporate | ADU8: High Net Worth | ADV8: Corporate | ADW8: High Net Worth | ADX8: SME | ADY8: SME | ADZ8: Retail | AEA8: High Net Worth | AEB8: Retail | AEC8: High Net Worth | AED8: Corporate | AEE8: Corporate | AEF8: Retail | AEG8: High Net Worth | AEH8: Retail | AEI8: SME | AEJ8: Retail | AEK8: Retail | AEL8: Corporate | AEM8: Retail | AEN8: High Net Worth | AEO8: Corporate | AEP8: Retail | AEQ8: SME | AER8: Retail | AES8: Retail | AET8: Retail | AEU8: Corporate | AEV8: High Net Worth | AEW8: SME | AEX8: Retail | AEY8: High Net Worth | AEZ8: High Net Worth | AFA8: Corporate | AFB8: SME | AFC8: Corporate | AFD8: High Net Worth | AFE8: High Net Worth | AFF8: High Net Worth | AFG8: Corporate | AFH8: SME | AFI8: Retail | AFJ8: Corporate | AFK8: High Net Worth | AFL8: Corporate | AFM8: High Net Worth | AFN8: Retail | AFO8: Retail | AFP8: SME | AFQ8: High Net Worth | AFR8: SME | AFS8: SME | AFT8: Retail | AFU8: Corporate | AFV8: Corporate | AFW8: SME | AFX8: Retail | AFY8: High Net Worth | AFZ8: Corporate | AGA8: SME | AGB8: Corporate | AGC8: Corporate | AGD8: High Net Worth | AGE8: Retail | AGF8: High Net Worth | AGG8: Retail | AGH8: Corporate | AGI8: SME | AGJ8: High Net Worth | AGK8: Retail | AGL8: Corporate | AGM8: Retail | AGN8: Retail | AGO8: Retail | AGP8: Corporate | AGQ8: SME | AGR8: SME | AGS8: SME | AGT8: Retail | AGU8: Corporate | AGV8: Retail | AGW8: SME | AGX8: SME | AGY8: Corporate | AGZ8: Retail | AHA8: High Net Worth | AHB8: High Net Worth | AHC8: SME | AHD8: Corporate | AHE8: Retail | AHF8: Retail | AHG8: SME | AHH8: SME | AHI8: Retail | AHJ8: Retail | AHK8: SME | AHL8: Retail | AHM8: High Net Worth | AHN8: SME | AHO8: Retail | AHP8: SME | AHQ8: Corporate | AHR8: SME | AHS8: SME | AHT8: Corporate | AHU8: High Net Worth | AHV8: Retail | AHW8: Corporate | AHX8: SME | AHY8: Retail | AHZ8: Corporate | AIA8: Retail | AIB8: Retail | AIC8: Corporate | AID8: Retail | AIE8: High Net Worth | AIF8: Corporate | AIG8: High Net Worth | AIH8: SME | AII8: Retail | AIJ8: SME | AIK8: SME | AIL8: Retail | AIM8: Corporate | AIN8: Retail | AIO8: SME | AIP8: SME | AIQ8: Corporate | AIR8: Retail | AIS8: SME | AIT8: High Net Worth | AIU8: SME | AIV8: SME | AIW8: Corporate | AIX8: High Net Worth | AIY8: SME | AIZ8: SME | AJA8: High Net Worth | AJB8: Retail | AJC8: Retail | AJD8: SME | AJE8: SME | AJF8: Retail | AJG8: Corporate | AJH8: High Net Worth | AJI8: High Net Worth | AJJ8: Corporate | AJK8: Corporate | AJL8: Corporate | AJM8: Corporate | AJN8: Corporate | AJO8: Corporate | AJP8: High Net Worth | AJQ8: Corporate | AJR8: Retail | AJS8: Corporate | AJT8: Corporate | AJU8: High Net Worth | AJV8: High Net Worth | AJW8: Corporate | AJX8: High Net Worth | AJY8: SME | AJZ8: High Net Worth | AKA8: High Net Worth | AKB8: High Net Worth | AKC8: High Net Worth | AKD8: Retail | AKE8: Retail | AKF8: Retail | AKG8: Corporate | AKH8: Corporate | AKI8: SME | AKJ8: Retail | AKK8: Corporate | AKL8: High Net Worth | AKM8: High Net Worth | AKN8: Retail | AKO8: SME | AKP8: SME | AKQ8: High Net Worth | AKR8: SME | AKS8: Retail | AKT8: High Net Worth | AKU8: Corporate | AKV8: Corporate | AKW8: SME | AKX8: High Net Worth | AKY8: High Net Worth | AKZ8: Corporate | ALA8: High Net Worth | ALB8: High Net Worth | ALC8: High Net Worth | ALD8: SME | ALE8: High Net Worth | ALF8: Retail | ALG8: SME | ALH8: High Net Worth | ALI8: High Net Worth | ALJ8: Retail | ALK8: SME | ALL8: Corporate | ALM8: Corporate
A9: Customer Age | B9: 74 | C9: 28 | D9: 44 | E9: 35 | F9: 63 | G9: 51 | H9: 29 | I9: 59 | J9: 65 | K9: 22 | L9: 28 | M9: 27 | N9: 64 | O9: 71 | P9: 59 | Q9: 62 | R9: 36 | S9: 55 | T9: 50 | U9: 30 | V9: 58 | W9: 38 | X9: 70 | Y9: 25 | Z9: 73 | AA9: 49 | AB9: 59 | AC9: 54 | AD9: 63 | AE9: 65 | AF9: 43 | AG9: 25 | AH9: 50 | AI9: 26 | AJ9: 66 | AK9: 64 | AL9: 24 | AM9: 49 | AN9: 43 | AO9: 26 | AP9: 52 | AQ9: 62 | AR9: 38 | AS9: 35 | AT9: 60 | AU9: 52 | AV9: 29 | AW9: 57 | AX9: 30 | AY9: 40 | AZ9: 26 | BA9: 68 | BB9: 23 | BC9: 62 | BD9: 31 | BE9: 63 | BF9: 37 | BG9: 52 | BH9: 24 | BI9: 24 | BJ9: 37 | BK9: 61 | BL9: 39 | BM9: 25 | BN9: 52 | BO9: 42 | BP9: 26 | BQ9: 55 | BR9: 42 | BS9: 21 | BT9: 40 | BU9: 42 | BV9: 68 | BW9: 31 | BX9: 33 | BY9: 62 | BZ9: 23 | CA9: 29 | CB9: 32 | CC9: 43 | CD9: 34 | CE9: 53 | CF9: 38 | CG9: 69 | CH9: 61 | CI9: 29 | CJ9: 43 | CK9: 30 | CL9: 39 | CM9: 67 | CN9: 25 | CO9: 67 | CP9: 72 | CQ9: 43 | CR9: 50 | CS9: 45 | CT9: 48 | CU9: 54 | CV9: 65 | CW9: 68 | CX9: 67 | CY9: 45 | CZ9: 30 | DA9: 34 | DB9: 62 | DC9: 66 | DD9: 50 | DE9: 61 | DF9: 45 | DG9: 34 | DH9: 55 | DI9: 72 | DJ9: 68 | DK9: 54 | DL9: 30 | DM9: 55 | DN9: 31 | DO9: 31 | DP9: 41 | DQ9: 41 | DR9: 42 | DS9: 65 | DT9: 27 | DU9: 37 | DV9: 22 | DW9: 32 | DX9: 62 | DY9: 38 | DZ9: 74 | EA9: 31 | EB9: 36 | EC9: 69 | ED9: 71 | EE9: 38 | EF9: 55 | EG9: 73 | EH9: 46 | EI9: 36 | EJ9: 26 | EK9: 64 | EL9: 63 | EM9: 67 | EN9: 67 | EO9: 68 | EP9: 62 | EQ9: 32 | ER9: 33 | ES9: 24 | ET9: 59 | EU9: 74 | EV9: 22 | EW9: 46 | EX9: 47 | EY9: 47 | EZ9: 35 | FA9: 28 | FB9: 27 | FC9: 67 | FD9: 66 | FE9: 60 | FF9: 32 | FG9: 33 | FH9: 63 | FI9: 37 | FJ9: 37 | FK9: 56 | FL9: 41 | FM9: 28 | FN9: 25 | FO9: 46 | FP9: 36 | FQ9: 56 | FR9: 48 | FS9: 74 | FT9: 49 | FU9: 67 | FV9: 32 | FW9: 57 | FX9: 50 | FY9: 43 | FZ9: 36 | GA9: 34 | GB9: 30 | GC9: 27 | GD9: 65 | GE9: 72 | GF9: 57 | GG9: 49 | GH9: 23 | GI9: 35 | GJ9: 56 | GK9: 67 | GL9: 66 | GM9: 72 | GN9: 39 | GO9: 33 | GP9: 62 | GQ9: 41 | GR9: 57 | GS9: 47 | GT9: 72 | GU9: 49 | GV9: 40 | GW9: 45 | GX9: 26 | GY9: 56 | GZ9: 22 | HA9: 42 | HB9: 52 | HC9: 36 | HD9: 38 | HE9: 25 | HF9: 74 | HG9: 56 | HH9: 50 | HI9: 65 | HJ9: 39 | HK9: 43 | HL9: 54 | HM9: 33 | HN9: 63 | HO9: 74 | HP9: 49 | HQ9: 56 | HR9: 42 | HS9: 72 | HT9: 72 | HU9: 67 | HV9: 56 | HW9: 29 | HX9: 59 | HY9: 71 | HZ9: 39 | IA9: 58 | IB9: 26 | IC9: 72 | ID9: 67 | IE9: 35 | IF9: 40 | IG9: 29 | IH9: 52 | II9: 24 | IJ9: 70 | IK9: 38 | IL9: 25 | IM9: 40 | IN9: 43 | IO9: 31 | IP9: 57 | IQ9: 42 | IR9: 24 | IS9: 49 | IT9: 64 | IU9: 54 | IV9: 33 | IW9: 62 | IX9: 29 | IY9: 62 | IZ9: 51 | JA9: 27 | JB9: 24 | JC9: 39 | JD9: 62 | JE9: 50 | JF9: 51 | JG9: 55 | JH9: 41 | JI9: 51 | JJ9: 39 | JK9: 51 | JL9: 73 | JM9: 52 | JN9: 22 | JO9: 72 | JP9: 30 | JQ9: 22 | JR9: 22 | JS9: 44 | JT9: 37 | JU9: 52 | JV9: 36 | JW9: 36 | JX9: 66 | JY9: 59 | JZ9: 73 | KA9: 51 | KB9: 63 | KC9: 44 | KD9: 21 | KE9: 31 | KF9: 41 | KG9: 24 | KH9: 27 | KI9: 46 | KJ9: 67 | KK9: 70 | KL9: 32 | KM9: 51 | KN9: 37 | KO9: 53 | KP9: 31 | KQ9: 48 | KR9: 52 | KS9: 21 | KT9: 67 | KU9: 48 | KV9: 73 | KW9: 62 | KX9: 27 | KY9: 22 | KZ9: 62 | LA9: 44 | LB9: 24 | LC9: 64 | LD9: 39 | LE9: 46 | LF9: 31 | LG9: 60 | LH9: 70 | LI9: 63 | LJ9: 31 | LK9: 65 | LL9: 23 | LM9: 32 | LN9: 23 | LO9: 62 | LP9: 47 | LQ9: 69 | LR9: 74 | LS9: 22 | LT9: 69 | LU9: 36 | LV9: 22 | LW9: 74 | LX9: 50 | LY9: 40 | LZ9: 58 | MA9: 48 | MB9: 45 | MC9: 52 | MD9: 30 | ME9: 62 | MF9: 60 | MG9: 53 | MH9: 33 | MI9: 61 | MJ9: 74 | MK9: 62 | ML9: 67 | MM9: 57 | MN9: 74 | MO9: 36 | MP9: 65 | MQ9: 42 | MR9: 40 | MS9: 70 | MT9: 63 | MU9: 47 | MV9: 61 | MW9: 36 | MX9: 54 | MY9: 52 | MZ9: 46 | NA9: 45 | NB9: 22 | NC9: 32 | ND9: 60 | NE9: 29 | NF9: 32 | NG9: 46 | NH9: 29 | NI9: 30 | NJ9: 52 | NK9: 54 | NL9: 68 | NM9: 40 | NN9: 59 | NO9: 22 | NP9: 21 | NQ9: 71 | NR9: 56 | NS9: 44 | NT9: 74 | NU9: 47 | NV9: 22 | NW9: 51 | NX9: 34 | NY9: 22 | NZ9: 49 | OA9: 35 | OB9: 32 | OC9: 57 | OD9: 48 | OE9: 40 | OF9: 59 | OG9: 44 | OH9: 41 | OI9: 30 | OJ9: 66 | OK9: 34 | OL9: 57 | OM9: 38 | ON9: 44 | OO9: 34 | OP9: 54 | OQ9: 32 | OR9: 42 | OS9: 26 | OT9: 56 | OU9: 65 | OV9: 56 | OW9: 42 | OX9: 34 | OY9: 36 | OZ9: 56 | PA9: 45 | PB9: 52 | PC9: 53 | PD9: 65 | PE9: 56 | PF9: 40 | PG9: 38 | PH9: 58 | PI9: 23 | PJ9: 43 | PK9: 52 | PL9: 65 | PM9: 36 | PN9: 25 | PO9: 24 | PP9: 41 | PQ9: 60 | PR9: 71 | PS9: 34 | PT9: 59 | PU9: 51 | PV9: 34 | PW9: 26 | PX9: 32 | PY9: 36 | PZ9: 37 | QA9: 65 | QB9: 43 | QC9: 34 | QD9: 27 | QE9: 66 | QF9: 52 | QG9: 35 | QH9: 64 | QI9: 37 | QJ9: 61 | QK9: 74 | QL9: 67 | QM9: 64 | QN9: 54 | QO9: 25 | QP9: 65 | QQ9: 47 | QR9: 72 | QS9: 43 | QT9: 60 | QU9: 34 | QV9: 35 | QW9: 63 | QX9: 53 | QY9: 73 | QZ9: 51 | RA9: 55 | RB9: 37 | RC9: 48 | RD9: 39 | RE9: 66 | RF9: 74 | RG9: 43 | RH9: 52 | RI9: 60 | RJ9: 33 | RK9: 40 | RL9: 55 | RM9: 25 | RN9: 29 | RO9: 49 | RP9: 26 | RQ9: 45 | RR9: 51 | RS9: 42 | RT9: 22 | RU9: 65 | RV9: 25 | RW9: 47 | RX9: 45 | RY9: 28 | RZ9: 21 | SA9: 40 | SB9: 64 | SC9: 43 | SD9: 52 | SE9: 31 | SF9: 59 | SG9: 67 | SH9: 74 | SI9: 44 | SJ9: 31 | SK9: 49 | SL9: 74 | SM9: 46 | SN9: 36 | SO9: 55 | SP9: 40 | SQ9: 66 | SR9: 23 | SS9: 21 | ST9: 73 | SU9: 67 | SV9: 21 | SW9: 37 | SX9: 22 | SY9: 49 | SZ9: 40 | TA9: 26 | TB9: 28 | TC9: 49 | TD9: 68 | TE9: 71 | TF9: 53 | TG9: 23 | TH9: 55 | TI9: 25 | TJ9: 47 | TK9: 64 | TL9: 32 | TM9: 40 | TN9: 65 | TO9: 40 | TP9: 29 | TQ9: 59 | TR9: 24 | TS9: 71 | TT9: 74 | TU9: 39 | TV9: 58 | TW9: 47 | TX9: 65 | TY9: 63 | TZ9: 33 | UA9: 33 | UB9: 42 | UC9: 48 | UD9: 72 | UE9: 67 | UF9: 73 | UG9: 65 | UH9: 42 | UI9: 63 | UJ9: 39 | UK9: 28 | UL9: 72 | UM9: 28 | UN9: 62 | UO9: 46 | UP9: 68 | UQ9: 71 | UR9: 46 | US9: 43 | UT9: 63 | UU9: 33 | UV9: 48 | UW9: 29 | UX9: 40 | UY9: 39 | UZ9: 68 | VA9: 59 | VB9: 71 | VC9: 32 | VD9: 35 | VE9: 51 | VF9: 34 | VG9: 31 | VH9: 46 | VI9: 62 | VJ9: 47 | VK9: 31 | VL9: 58 | VM9: 54 | VN9: 63 | VO9: 39 | VP9: 26 | VQ9: 66 | VR9: 72 | VS9: 58 | VT9: 69 | VU9: 62 | VV9: 48 | VW9: 21 | VX9: 55 | VY9: 60 | VZ9: 28 | WA9: 72 | WB9: 74 | WC9: 67 | WD9: 27 | WE9: 31 | WF9: 59 | WG9: 24 | WH9: 45 | WI9: 32 | WJ9: 46 | WK9: 58 | WL9: 66 | WM9: 32 | WN9: 63 | WO9: 71 | WP9: 73 | WQ9: 57 | WR9: 66 | WS9: 73 | WT9: 44 | WU9: 36 | WV9: 33 | WW9: 45 | WX9: 74 | WY9: 74 | WZ9: 72 | XA9: 74 | XB9: 24 | XC9: 31 | XD9: 52 | XE9: 69 | XF9: 27 | XG9: 66 | XH9: 31 | XI9: 48 | XJ9: 74 | XK9: 61 | XL9: 43 | XM9: 65 | XN9: 43 | XO9: 70 | XP9: 48 | XQ9: 63 | XR9: 67 | XS9: 46 | XT9: 45 | XU9: 74 | XV9: 49 | XW9: 39 | XX9: 53 | XY9: 56 | XZ9: 34 | YA9: 34 | YB9: 55 | YC9: 50 | YD9: 48 | YE9: 37 | YF9: 23 | YG9: 36 | YH9: 66 | YI9: 50 | YJ9: 72 | YK9: 49 | YL9: 65 | YM9: 35 | YN9: 66 | YO9: 45 | YP9: 71 | YQ9: 58 | YR9: 62 | YS9: 67 | YT9: 73 | YU9: 74 | YV9: 72 | YW9: 58 | YX9: 43 | YY9: 45 | YZ9: 62 | ZA9: 27 | ZB9: 42 | ZC9: 37 | ZD9: 38 | ZE9: 69 | ZF9: 61 | ZG9: 30 | ZH9: 30 | ZI9: 27 | ZJ9: 68 | ZK9: 70 | ZL9: 58 | ZM9: 47 | ZN9: 72 | ZO9: 53 | ZP9: 21 | ZQ9: 64 | ZR9: 73 | ZS9: 54 | ZT9: 24 | ZU9: 37 | ZV9: 24 | ZW9: 63 | ZX9: 74 | ZY9: 46 | ZZ9: 24 | AAA9: 21 | AAB9: 27 | AAC9: 50 | AAD9: 70 | AAE9: 29 | AAF9: 55 | AAG9: 28 | AAH9: 44 | AAI9: 39 | AAJ9: 56 | AAK9: 70 | AAL9: 72 | AAM9: 63 | AAN9: 47 | AAO9: 52 | AAP9: 34 | AAQ9: 38 | AAR9: 48 | AAS9: 49 | AAT9: 36 | AAU9: 55 | AAV9: 67 | AAW9: 51 | AAX9: 24 | AAY9: 57 | AAZ9: 37 | ABA9: 59 | ABB9: 68 | ABC9: 66 | ABD9: 46 | ABE9: 68 | ABF9: 59 | ABG9: 61 | ABH9: 24 | ABI9: 50 | ABJ9: 50 | ABK9: 42 | ABL9: 31 | ABM9: 22 | ABN9: 64 | ABO9: 32 | ABP9: 50 | ABQ9: 56 | ABR9: 38 | ABS9: 46 | ABT9: 73 | ABU9: 27 | ABV9: 21 | ABW9: 46 | ABX9: 43 | ABY9: 46 | ABZ9: 65 | ACA9: 26 | ACB9: 26 | ACC9: 64 | ACD9: 28 | ACE9: 44 | ACF9: 42 | ACG9: 39 | ACH9: 57 | ACI9: 38 | ACJ9: 51 | ACK9: 57 | ACL9: 50 | ACM9: 62 | ACN9: 53 | ACO9: 30 | ACP9: 57 | ACQ9: 32 | ACR9: 74 | ACS9: 50 | ACT9: 47 | ACU9: 59 | ACV9: 29 | ACW9: 74 | ACX9: 41 | ACY9: 32 | ACZ9: 49 | ADA9: 53 | ADB9: 63 | ADC9: 73 | ADD9: 35 | ADE9: 22 | ADF9: 72 | ADG9: 59 | ADH9: 73 | ADI9: 64 | ADJ9: 74 | ADK9: 38 | ADL9: 23 | ADM9: 27 | ADN9: 63 | ADO9: 38 | ADP9: 64 | ADQ9: 58 | ADR9: 57 | ADS9: 53 | ADT9: 64 | ADU9: 51 | ADV9: 31 | ADW9: 24 | ADX9: 38 | ADY9: 24 | ADZ9: 69 | AEA9: 54 | AEB9: 49 | AEC9: 44 | AED9: 42 | AEE9: 22 | AEF9: 64 | AEG9: 26 | AEH9: 62 | AEI9: 45 | AEJ9: 41 | AEK9: 36 | AEL9: 51 | AEM9: 34 | AEN9: 59 | AEO9: 48 | AEP9: 52 | AEQ9: 48 | AER9: 71 | AES9: 69 | AET9: 29 | AEU9: 65 | AEV9: 42 | AEW9: 52 | AEX9: 25 | AEY9: 43 | AEZ9: 25 | AFA9: 62 | AFB9: 73 | AFC9: 52 | AFD9: 30 | AFE9: 59 | AFF9: 35 | AFG9: 27 | AFH9: 49 | AFI9: 67 | AFJ9: 23 | AFK9: 39 | AFL9: 30 | AFM9: 48 | AFN9: 49 | AFO9: 35 | AFP9: 55 | AFQ9: 26 | AFR9: 32 | AFS9: 67 | AFT9: 58 | AFU9: 33 | AFV9: 49 | AFW9: 39 | AFX9: 23 | AFY9: 28 | AFZ9: 28 | AGA9: 40 | AGB9: 67 | AGC9: 24 | AGD9: 71 | AGE9: 41 | AGF9: 23 | AGG9: 65 | AGH9: 28 | AGI9: 43 | AGJ9: 36 | AGK9: 33 | AGL9: 23 | AGM9: 68 | AGN9: 29 | AGO9: 34 | AGP9: 33 | AGQ9: 73 | AGR9: 27 | AGS9: 35 | AGT9: 27 | AGU9: 58 | AGV9: 54 | AGW9: 61 | AGX9: 42 | AGY9: 44 | AGZ9: 69 | AHA9: 57 | AHB9: 64 | AHC9: 21 | AHD9: 30 | AHE9: 63 | AHF9: 36 | AHG9: 66 | AHH9: 28 | AHI9: 69 | AHJ9: 45 | AHK9: 70 | AHL9: 32 | AHM9: 45 | AHN9: 37 | AHO9: 46 | AHP9: 66 | AHQ9: 68 | AHR9: 34 | AHS9: 61 | AHT9: 56 | AHU9: 43 | AHV9: 63 | AHW9: 26 | AHX9: 67 | AHY9: 25 | AHZ9: 63 | AIA9: 45 | AIB9: 38 | AIC9: 33 | AID9: 63 | AIE9: 34 | AIF9: 48 | AIG9: 38 | AIH9: 48 | AII9: 71 | AIJ9: 47 | AIK9: 52 | AIL9: 67 | AIM9: 29 | AIN9: 60 | AIO9: 52 | AIP9: 40 | AIQ9: 48 | AIR9: 53 | AIS9: 24 | AIT9: 66 | AIU9: 54 | AIV9: 68 | AIW9: 23 | AIX9: 46 | AIY9: 28 | AIZ9: 26 | AJA9: 36 | AJB9: 44 | AJC9: 68 | AJD9: 59 | AJE9: 50 | AJF9: 65 | AJG9: 33 | AJH9: 25 | AJI9: 45 | AJJ9: 40 | AJK9: 74 | AJL9: 38 | AJM9: 67 | AJN9: 38 | AJO9: 22 | AJP9: 30 | AJQ9: 65 | AJR9: 70 | AJS9: 67 | AJT9: 32 | AJU9: 67 | AJV9: 33 | AJW9: 70 | AJX9: 67 | AJY9: 31 | AJZ9: 39 | AKA9: 55 | AKB9: 59 | AKC9: 73 | AKD9: 46 | AKE9: 66 | AKF9: 34 | AKG9: 74 | AKH9: 65 | AKI9: 64 | AKJ9: 44 | AKK9: 61 | AKL9: 21 | AKM9: 71 | AKN9: 63 | AKO9: 42 | AKP9: 43 | AKQ9: 74 | AKR9: 39 | AKS9: 38 | AKT9: 32 | AKU9: 48 | AKV9: 48 | AKW9: 53 | AKX9: 39 | AKY9: 48 | AKZ9: 72 | ALA9: 69 | ALB9: 57 | ALC9: 46 | ALD9: 55 | ALE9: 54 | ALF9: 55 | ALG9: 60 | ALH9: 36 | ALI9: 58 | ALJ9: 33 | ALK9: 43 | ALL9: 74 | ALM9: 42
A10: Account Tenure Months | B10: 16 | C10: 28 | D10: 112 | E10: 35 | F10: 60 | G10: 45 | H10: 46 | I10: 72 | J10: 108 | K10: 55 | L10: 119 | M10: 86 | N10: 85 | O10: 26 | P10: 104 | Q10: 85 | R10: 25 | S10: 105 | T10: 65 | U10: 6 | V10: 23 | W10: 115 | X10: 64 | Y10: 87 | Z10: 43 | AA10: 107 | AB10: 23 | AC10: 96 | AD10: 30 | AE10: 77 | AF10: 107 | AG10: 18 | AH10: 87 | AI10: 79 | AJ10: 97 | AK10: 21 | AL10: 57 | AM10: 103 | AN10: 23 | AO10: 91 | AP10: 45 | AQ10: 44 | AR10: 82 | AS10: 88 | AT10: 115 | AU10: 47 | AV10: 40 | AW10: 51 | AX10: 42 | AY10: 7 | AZ10: 50 | BA10: 48 | BB10: 84 | BC10: 91 | BD10: 6 | BE10: 91 | BF10: 9 | BG10: 117 | BH10: 109 | BI10: 57 | BJ10: 31 | BK10: 21 | BL10: 90 | BM10: 40 | BN10: 112 | BO10: 45 | BP10: 77 | BQ10: 49 | BR10: 87 | BS10: 20 | BT10: 101 | BU10: 118 | BV10: 117 | BW10: 92 | BX10: 17 | BY10: 28 | BZ10: 41 | CA10: 66 | CB10: 25 | CC10: 58 | CD10: 114 | CE10: 41 | CF10: 6 | CG10: 75 | CH10: 38 | CI10: 6 | CJ10: 45 | CK10: 75 | CL10: 14 | CM10: 66 | CN10: 40 | CO10: 3 | CP10: 119 | CQ10: 117 | CR10: 99 | CS10: 97 | CT10: 24 | CU10: 19 | CV10: 18 | CW10: 64 | CX10: 113 | CY10: 116 | CZ10: 88 | DA10: 109 | DB10: 35 | DC10: 62 | DD10: 1 | DE10: 100 | DF10: 25 | DG10: 45 | DH10: 49 | DI10: 107 | DJ10: 98 | DK10: 89 | DL10: 16 | DM10: 98 | DN10: 93 | DO10: 19 | DP10: 23 | DQ10: 83 | DR10: 25 | DS10: 16 | DT10: 54 | DU10: 115 | DV10: 73 | DW10: 1 | DX10: 42 | DY10: 19 | DZ10: 97 | EA10: 34 | EB10: 80 | EC10: 108 | ED10: 104 | EE10: 55 | EF10: 18 | EG10: 34 | EH10: 89 | EI10: 45 | EJ10: 6 | EK10: 21 | EL10: 70 | EM10: 96 | EN10: 105 | EO10: 48 | EP10: 107 | EQ10: 39 | ER10: 31 | ES10: 106 | ET10: 10 | EU10: 30 | EV10: 116 | EW10: 18 | EX10: 60 | EY10: 88 | EZ10: 116 | FA10: 73 | FB10: 95 | FC10: 15 | FD10: 4 | FE10: 63 | FF10: 40 | FG10: 9 | FH10: 109 | FI10: 9 | FJ10: 26 | FK10: 4 | FL10: 81 | FM10: 16 | FN10: 15 | FO10: 99 | FP10: 52 | FQ10: 69 | FR10: 119 | FS10: 5 | FT10: 20 | FU10: 79 | FV10: 18 | FW10: 111 | FX10: 2 | FY10: 93 | FZ10: 13 | GA10: 4 | GB10: 42 | GC10: 109 | GD10: 74 | GE10: 61 | GF10: 95 | GG10: 105 | GH10: 8 | GI10: 67 | GJ10: 112 | GK10: 63 | GL10: 110 | GM10: 9 | GN10: 94 | GO10: 117 | GP10: 11 | GQ10: 99 | GR10: 101 | GS10: 42 | GT10: 13 | GU10: 36 | GV10: 13 | GW10: 12 | GX10: 37 | GY10: 74 | GZ10: 73 | HA10: 52 | HB10: 71 | HC10: 2 | HD10: 118 | HE10: 56 | HF10: 60 | HG10: 23 | HH10: 103 | HI10: 40 | HJ10: 64 | HK10: 103 | HL10: 85 | HM10: 23 | HN10: 29 | HO10: 78 | HP10: 90 | HQ10: 51 | HR10: 69 | HS10: 119 | HT10: 95 | HU10: 89 | HV10: 31 | HW10: 50 | HX10: 20 | HY10: 108 | HZ10: 55 | IA10: 81 | IB10: 109 | IC10: 2 | ID10: 25 | IE10: 13 | IF10: 103 | IG10: 92 | IH10: 106 | II10: 119 | IJ10: 70 | IK10: 67 | IL10: 58 | IM10: 99 | IN10: 82 | IO10: 75 | IP10: 118 | IQ10: 84 | IR10: 64 | IS10: 69 | IT10: 83 | IU10: 86 | IV10: 59 | IW10: 60 | IX10: 83 | IY10: 111 | IZ10: 62 | JA10: 16 | JB10: 88 | JC10: 105 | JD10: 68 | JE10: 15 | JF10: 89 | JG10: 108 | JH10: 55 | JI10: 35 | JJ10: 55 | JK10: 14 | JL10: 49 | JM10: 83 | JN10: 102 | JO10: 100 | JP10: 7 | JQ10: 30 | JR10: 83 | JS10: 49 | JT10: 89 | JU10: 16 | JV10: 111 | JW10: 118 | JX10: 104 | JY10: 51 | JZ10: 72 | KA10: 82 | KB10: 92 | KC10: 80 | KD10: 116 | KE10: 83 | KF10: 42 | KG10: 17 | KH10: 63 | KI10: 45 | KJ10: 77 | KK10: 7 | KL10: 27 | KM10: 10 | KN10: 34 | KO10: 36 | KP10: 25 | KQ10: 6 | KR10: 24 | KS10: 18 | KT10: 87 | KU10: 6 | KV10: 29 | KW10: 25 | KX10: 55 | KY10: 81 | KZ10: 46 | LA10: 24 | LB10: 75 | LC10: 26 | LD10: 115 | LE10: 98 | LF10: 28 | LG10: 3 | LH10: 75 | LI10: 38 | LJ10: 61 | LK10: 78 | LL10: 51 | LM10: 90 | LN10: 48 | LO10: 21 | LP10: 54 | LQ10: 56 | LR10: 103 | LS10: 94 | LT10: 59 | LU10: 72 | LV10: 51 | LW10: 20 | LX10: 112 | LY10: 96 | LZ10: 86 | MA10: 59 | MB10: 71 | MC10: 9 | MD10: 109 | ME10: 1 | MF10: 29 | MG10: 63 | MH10: 72 | MI10: 56 | MJ10: 118 | MK10: 68 | ML10: 35 | MM10: 3 | MN10: 118 | MO10: 109 | MP10: 104 | MQ10: 7 | MR10: 27 | MS10: 1 | MT10: 91 | MU10: 80 | MV10: 102 | MW10: 71 | MX10: 44 | MY10: 87 | MZ10: 41 | NA10: 75 | NB10: 42 | NC10: 117 | ND10: 33 | NE10: 50 | NF10: 63 | NG10: 100 | NH10: 37 | NI10: 105 | NJ10: 59 | NK10: 81 | NL10: 99 | NM10: 48 | NN10: 5 | NO10: 48 | NP10: 96 | NQ10: 3 | NR10: 116 | NS10: 47 | NT10: 62 | NU10: 99 | NV10: 116 | NW10: 14 | NX10: 63 | NY10: 112 | NZ10: 61 | OA10: 31 | OB10: 95 | OC10: 17 | OD10: 24 | OE10: 116 | OF10: 23 | OG10: 82 | OH10: 50 | OI10: 118 | OJ10: 78 | OK10: 114 | OL10: 79 | OM10: 79 | ON10: 70 | OO10: 27 | OP10: 15 | OQ10: 50 | OR10: 36 | OS10: 119 | OT10: 8 | OU10: 79 | OV10: 3 | OW10: 62 | OX10: 47 | OY10: 77 | OZ10: 105 | PA10: 98 | PB10: 88 | PC10: 104 | PD10: 96 | PE10: 61 | PF10: 32 | PG10: 94 | PH10: 116 | PI10: 113 | PJ10: 13 | PK10: 1 | PL10: 34 | PM10: 62 | PN10: 79 | PO10: 108 | PP10: 78 | PQ10: 93 | PR10: 98 | PS10: 82 | PT10: 118 | PU10: 71 | PV10: 93 | PW10: 119 | PX10: 31 | PY10: 64 | PZ10: 25 | QA10: 38 | QB10: 14 | QC10: 8 | QD10: 91 | QE10: 54 | QF10: 2 | QG10: 81 | QH10: 101 | QI10: 78 | QJ10: 89 | QK10: 56 | QL10: 94 | QM10: 93 | QN10: 84 | QO10: 85 | QP10: 61 | QQ10: 117 | QR10: 22 | QS10: 35 | QT10: 101 | QU10: 16 | QV10: 50 | QW10: 113 | QX10: 43 | QY10: 17 | QZ10: 80 | RA10: 58 | RB10: 119 | RC10: 2 | RD10: 4 | RE10: 85 | RF10: 39 | RG10: 98 | RH10: 94 | RI10: 6 | RJ10: 81 | RK10: 103 | RL10: 89 | RM10: 69 | RN10: 69 | RO10: 20 | RP10: 64 | RQ10: 16 | RR10: 51 | RS10: 105 | RT10: 37 | RU10: 104 | RV10: 73 | RW10: 69 | RX10: 42 | RY10: 57 | RZ10: 66 | SA10: 9 | SB10: 107 | SC10: 100 | SD10: 86 | SE10: 64 | SF10: 86 | SG10: 22 | SH10: 34 | SI10: 55 | SJ10: 29 | SK10: 38 | SL10: 110 | SM10: 97 | SN10: 18 | SO10: 71 | SP10: 65 | SQ10: 97 | SR10: 1 | SS10: 88 | ST10: 4 | SU10: 4 | SV10: 82 | SW10: 27 | SX10: 43 | SY10: 59 | SZ10: 32 | TA10: 33 | TB10: 28 | TC10: 106 | TD10: 105 | TE10: 55 | TF10: 100 | TG10: 60 | TH10: 70 | TI10: 62 | TJ10: 80 | TK10: 34 | TL10: 87 | TM10: 114 | TN10: 106 | TO10: 88 | TP10: 56 | TQ10: 113 | TR10: 13 | TS10: 56 | TT10: 18 | TU10: 54 | TV10: 77 | TW10: 113 | TX10: 101 | TY10: 43 | TZ10: 39 | UA10: 61 | UB10: 42 | UC10: 81 | UD10: 79 | UE10: 18 | UF10: 23 | UG10: 54 | UH10: 115 | UI10: 30 | UJ10: 98 | UK10: 58 | UL10: 68 | UM10: 67 | UN10: 71 | UO10: 18 | UP10: 106 | UQ10: 7 | UR10: 40 | US10: 70 | UT10: 86 | UU10: 65 | UV10: 68 | UW10: 110 | UX10: 49 | UY10: 52 | UZ10: 114 | VA10: 107 | VB10: 29 | VC10: 21 | VD10: 90 | VE10: 78 | VF10: 9 | VG10: 47 | VH10: 76 | VI10: 42 | VJ10: 51 | VK10: 56 | VL10: 51 | VM10: 70 | VN10: 20 | VO10: 88 | VP10: 27 | VQ10: 38 | VR10: 72 | VS10: 65 | VT10: 54 | VU10: 113 | VV10: 113 | VW10: 24 | VX10: 47 | VY10: 71 | VZ10: 83 | WA10: 86 | WB10: 63 | WC10: 57 | WD10: 55 | WE10: 60 | WF10: 99 | WG10: 62 | WH10: 30 | WI10: 93 | WJ10: 22 | WK10: 75 | WL10: 84 | WM10: 29 | WN10: 115 | WO10: 41 | WP10: 42 | WQ10: 98 | WR10: 65 | WS10: 31 | WT10: 30 | WU10: 112 | WV10: 18 | WW10: 119 | WX10: 17 | WY10: 38 | WZ10: 14 | XA10: 87 | XB10: 89 | XC10: 79 | XD10: 110 | XE10: 56 | XF10: 22 | XG10: 67 | XH10: 56 | XI10: 119 | XJ10: 19 | XK10: 57 | XL10: 44 | XM10: 98 | XN10: 35 | XO10: 114 | XP10: 1 | XQ10: 52 | XR10: 85 | XS10: 93 | XT10: 70 | XU10: 37 | XV10: 65 | XW10: 51 | XX10: 1 | XY10: 91 | XZ10: 21 | YA10: 53 | YB10: 16 | YC10: 108 | YD10: 61 | YE10: 54 | YF10: 40 | YG10: 26 | YH10: 80 | YI10: 92 | YJ10: 65 | YK10: 100 | YL10: 74 | YM10: 64 | YN10: 43 | YO10: 17 | YP10: 59 | YQ10: 23 | YR10: 7 | YS10: 44 | YT10: 53 | YU10: 71 | YV10: 108 | YW10: 79 | YX10: 34 | YY10: 46 | YZ10: 109 | ZA10: 68 | ZB10: 78 | ZC10: 78 | ZD10: 16 | ZE10: 71 | ZF10: 96 | ZG10: 19 | ZH10: 2 | ZI10: 10 | ZJ10: 50 | ZK10: 81 | ZL10: 101 | ZM10: 12 | ZN10: 70 | ZO10: 22 | ZP10: 32 | ZQ10: 105 | ZR10: 84 | ZS10: 1 | ZT10: 54 | ZU10: 111 | ZV10: 117 | ZW10: 58 | ZX10: 70 | ZY10: 83 | ZZ10: 18 | AAA10: 6 | AAB10: 45 | AAC10: 97 | AAD10: 23 | AAE10: 23 | AAF10: 26 | AAG10: 77 | AAH10: 7 | AAI10: 79 | AAJ10: 44 | AAK10: 27 | AAL10: 26 | AAM10: 97 | AAN10: 79 | AAO10: 36 | AAP10: 109 | AAQ10: 55 | AAR10: 64 | AAS10: 91 | AAT10: 57 | AAU10: 69 | AAV10: 61 | AAW10: 2 | AAX10: 55 | AAY10: 97 | AAZ10: 80 | ABA10: 87 | ABB10: 38 | ABC10: 119 | ABD10: 80 | ABE10: 78 | ABF10: 29 | ABG10: 26 | ABH10: 35 | ABI10: 79 | ABJ10: 67 | ABK10: 87 | ABL10: 29 | ABM10: 34 | ABN10: 97 | ABO10: 41 | ABP10: 41 | ABQ10: 23 | ABR10: 71 | ABS10: 3 | ABT10: 58 | ABU10: 32 | ABV10: 31 | ABW10: 82 | ABX10: 43 | ABY10: 7 | ABZ10: 105 | ACA10: 1 | ACB10: 61 | ACC10: 14 | ACD10: 52 | ACE10: 96 | ACF10: 6 | ACG10: 103 | ACH10: 10 | ACI10: 71 | ACJ10: 90 | ACK10: 98 | ACL10: 30 | ACM10: 100 | ACN10: 21 | ACO10: 60 | ACP10: 81 | ACQ10: 97 | ACR10: 74 | ACS10: 115 | ACT10: 63 | ACU10: 111 | ACV10: 42 | ACW10: 51 | ACX10: 64 | ACY10: 76 | ACZ10: 56 | ADA10: 80 | ADB10: 41 | ADC10: 32 | ADD10: 15 | ADE10: 62 | ADF10: 27 | ADG10: 28 | ADH10: 81 | ADI10: 64 | ADJ10: 110 | ADK10: 59 | ADL10: 114 | ADM10: 58 | ADN10: 2 | ADO10: 36 | ADP10: 114 | ADQ10: 71 | ADR10: 13 | ADS10: 15 | ADT10: 89 | ADU10: 87 | ADV10: 60 | ADW10: 22 | ADX10: 63 | ADY10: 90 | ADZ10: 97 | AEA10: 75 | AEB10: 74 | AEC10: 25 | AED10: 101 | AEE10: 48 | AEF10: 43 | AEG10: 117 | AEH10: 38 | AEI10: 41 | AEJ10: 45 | AEK10: 88 | AEL10: 40 | AEM10: 110 | AEN10: 97 | AEO10: 17 | AEP10: 88 | AEQ10: 101 | AER10: 57 | AES10: 2 | AET10: 96 | AEU10: 62 | AEV10: 88 | AEW10: 9 | AEX10: 68 | AEY10: 81 | AEZ10: 17 | AFA10: 117 | AFB10: 50 | AFC10: 112 | AFD10: 94 | AFE10: 40 | AFF10: 58 | AFG10: 75 | AFH10: 85 | AFI10: 21 | AFJ10: 18 | AFK10: 55 | AFL10: 29 | AFM10: 24 | AFN10: 74 | AFO10: 109 | AFP10: 17 | AFQ10: 18 | AFR10: 42 | AFS10: 112 | AFT10: 84 | AFU10: 101 | AFV10: 45 | AFW10: 82 | AFX10: 17 | AFY10: 73 | AFZ10: 14 | AGA10: 49 | AGB10: 29 | AGC10: 95 | AGD10: 4 | AGE10: 82 | AGF10: 20 | AGG10: 47 | AGH10: 107 | AGI10: 108 | AGJ10: 9 | AGK10: 77 | AGL10: 79 | AGM10: 27 | AGN10: 15 | AGO10: 92 | AGP10: 101 | AGQ10: 119 | AGR10: 19 | AGS10: 90 | AGT10: 52 | AGU10: 26 | AGV10: 89 | AGW10: 26 | AGX10: 26 | AGY10: 46 | AGZ10: 92 | AHA10: 49 | AHB10: 82 | AHC10: 96 | AHD10: 53 | AHE10: 3 | AHF10: 66 | AHG10: 97 | AHH10: 42 | AHI10: 19 | AHJ10: 17 | AHK10: 108 | AHL10: 33 | AHM10: 76 | AHN10: 49 | AHO10: 56 | AHP10: 63 | AHQ10: 3 | AHR10: 107 | AHS10: 49 | AHT10: 55 | AHU10: 26 | AHV10: 99 | AHW10: 72 | AHX10: 52 | AHY10: 100 | AHZ10: 117 | AIA10: 118 | AIB10: 7 | AIC10: 46 | AID10: 46 | AIE10: 100 | AIF10: 16 | AIG10: 24 | AIH10: 61 | AII10: 54 | AIJ10: 62 | AIK10: 1 | AIL10: 49 | AIM10: 25 | AIN10: 10 | AIO10: 118 | AIP10: 80 | AIQ10: 16 | AIR10: 58 | AIS10: 72 | AIT10: 29 | AIU10: 103 | AIV10: 92 | AIW10: 6 | AIX10: 16 | AIY10: 20 | AIZ10: 80 | AJA10: 71 | AJB10: 105 | AJC10: 78 | AJD10: 43 | AJE10: 26 | AJF10: 90 | AJG10: 78 | AJH10: 71 | AJI10: 33 | AJJ10: 26 | AJK10: 45 | AJL10: 84 | AJM10: 63 | AJN10: 67 | AJO10: 52 | AJP10: 68 | AJQ10: 26 | AJR10: 75 | AJS10: 2 | AJT10: 14 | AJU10: 108 | AJV10: 30 | AJW10: 49 | AJX10: 12 | AJY10: 90 | AJZ10: 44 | AKA10: 33 | AKB10: 13 | AKC10: 78 | AKD10: 88 | AKE10: 98 | AKF10: 108 | AKG10: 26 | AKH10: 21 | AKI10: 28 | AKJ10: 48 | AKK10: 100 | AKL10: 40 | AKM10: 66 | AKN10: 106 | AKO10: 73 | AKP10: 87 | AKQ10: 79 | AKR10: 77 | AKS10: 23 | AKT10: 81 | AKU10: 48 | AKV10: 2 | AKW10: 84 | AKX10: 20 | AKY10: 59 | AKZ10: 46 | ALA10: 3 | ALB10: 55 | ALC10: 12 | ALD10: 40 | ALE10: 66 | ALF10: 100 | ALG10: 78 | ALH10: 16 | ALI10: 83 | ALJ10: 34 | ALK10: 44 | ALL10: 110 | ALM10: 6
A11: Revenue | B11: 25114.07 | C11: 9331.6 | D11: 5853.67 | E11: 42184.29 | F11: 30899.59 | G11: 16628.32 | H11: 9990.94 | I11: 27997.12 | J11: 29404 | K11: 10746.18 | L11: 42644.58 | M11: 4671.09 | N11: 18126.61 | O11: 34179.03 | P11: 14068.96 | Q11: 41469.92 | R11: 37123.46 | S11: 39556.63 | T11: 6395.77 | U11: 7457.08 | V11: 14680.45 | W11: 26144.82 | X11: 37526.8 | Y11: 41908.28 | Z11: 35364.6 | AA11: 46465.55 | AB11: 37067.8 | AC11: 15660.26 | AD11: 13621.52 | AE11: 34961.53 | AF11: 10047.09 | AG11: 5089.38 | AH11: 26845.03 | AI11: 41171.26 | AJ11: 5518.3 | AK11: 39698.62 | AL11: 40672.81 | AM11: 24372.56 | AN11: 3336.86 | AO11: 9142.2 | AP11: 35517.6 | AQ11: 35733.01 | AR11: 44968.59 | AS11: 29342.96 | AT11: 6643.31 | AU11: 6510.04 | AV11: 36196.05 | AW11: 9597.34 | AX11: 16755.08 | AY11: 24616.99 | AZ11: 1725.86 | BA11: 12816.54 | BB11: 20690.54 | BC11: 14342 | BD11: 7250.33 | BE11: 36536.61 | BF11: 40750.81 | BG11: 13245.21 | BH11: 38833.76 | BI11: 19584.9 | BJ11: 25580.95 | BK11: 42872.05 | BL11: 37622.71 | BM11: 40353.28 | BN11: 7273.84 | BO11: 3951.11 | BP11: 44723.53 | BQ11: 19697.8 | BR11: 14750.04 | BS11: 36372.46 | BT11: 41902.57 | BU11: 43193.24 | BV11: 16141.86 | BW11: 42684.51 | BX11: 2526.23 | BY11: 2958.24 | BZ11: 31364.2 | CA11: 3623.77 | CB11: 16568.15 | CC11: 33801.42 | CD11: 17194.71 | CE11: 9390.19 | CF11: 14426.86 | CG11: 23149.98 | CH11: 24031.6 | CI11: 39258.51 | CJ11: 37632.58 | CK11: 23112.48 | CL11: 42360.53 | CM11: 6154.74 | CN11: 13139.99 | CO11: 41484.83 | CP11: 19210.7 | CQ11: 49068.49 | CR11: 23579.54 | CS11: 39700.81 | CT11: 20414.2 | CU11: 21535.2 | CV11: 19452.72 | CW11: 36094.24 | CX11: 27602.14 | CY11: 47217.02 | CZ11: 12919.07 | DA11: 5477.86 | DB11: 19966.44 | DC11: 31027.28 | DD11: 43109.55 | DE11: 17636.75 | DF11: 32862.44 | DG11: 17834.83 | DH11: 31052.37 | DI11: 44297.99 | DJ11: 11952.2 | DK11: 20509.96 | DL11: 49666.63 | DM11: 43493.57 | DN11: 28449.67 | DO11: 26073.07 | DP11: 14587.72 | DQ11: 26101.87 | DR11: 42484.98 | DS11: 34416.14 | DT11: 14857.18 | DU11: 10472.46 | DV11: 13627.82 | DW11: 8903.08 | DX11: 5234.21 | DY11: 21247.24 | DZ11: 6108.33 | EA11: 9009.67 | EB11: 27592.57 | EC11: 8647.66 | ED11: 3662.05 | EE11: 16210.75 | EF11: 11405.8 | EG11: 26007.61 | EH11: 5567.17 | EI11: 37712.65 | EJ11: 45358.56 | EK11: 37300.04 | EL11: 26874.94 | EM11: 43103.06 | EN11: 34898.46 | EO11: 1022.28 | EP11: 20007.46 | EQ11: 42622.12 | ER11: 17620.01 | ES11: 2243.15 | ET11: 37435.89 | EU11: 40200.89 | EV11: 8449.39 | EW11: 27098.35 | EX11: 10001.79 | EY11: 36102.1 | EZ11: 13941.75 | FA11: 16152.65 | FB11: 42326.06 | FC11: 24077.96 | FD11: 33652.85 | FE11: 20417.47 | FF11: 15251.34 | FG11: 31461.16 | FH11: 8165.45 | FI11: 18963.49 | FJ11: 10847.33 | FK11: 34941.85 | FL11: 47238.34 | FM11: 49777.79 | FN11: 22788.7 | FO11: 13000.25 | FP11: 22420.05 | FQ11: 42439.84 | FR11: 10697.28 | FS11: 47628.73 | FT11: 17422.36 | FU11: 49297.28 | FV11: 42011.14 | FW11: 40524.24 | FX11: 16236.28 | FY11: 934.47 | FZ11: 19415.58 | GA11: 15439.56 | GB11: 2351.15 | GC11: 25515.58 | GD11: 20450.05 | GE11: 31910.55 | GF11: 31248.72 | GG11: 6476.96 | GH11: 48859.79 | GI11: 9753.11 | GJ11: 22541.06 | GK11: 24661.82 | GL11: 40746.61 | GM11: 5411.87 | GN11: 21717.89 | GO11: 31610.86 | GP11: 11150.2 | GQ11: 31559.66 | GR11: 46221.41 | GS11: 49877.15 | GT11: 2106.33 | GU11: 12161.62 | GV11: 15860.2 | GW11: 20256.74 | GX11: 12491.73 | GY11: 10572.66 | GZ11: 47750.42 | HA11: 45966.82 | HB11: 2826.13 | HC11: 17271.24 | HD11: 20554.85 | HE11: 12331.22 | HF11: 31629.21 | HG11: 32198.85 | HH11: 42599.96 | HI11: 37173.03 | HJ11: 27357.38 | HK11: 32852.55 | HL11: 14062.44 | HM11: 29856.28 | HN11: 24716.75 | HO11: 7100.55 | HP11: 12505.94 | HQ11: 14938.83 | HR11: 46253.32 | HS11: 11904.14 | HT11: 14817.57 | HU11: 18783.03 | HV11: 33355.27 | HW11: 6352.8 | HX11: 47720.29 | HY11: 43345.78 | HZ11: 29072.2 | IA11: 33864.87 | IB11: 1324.69 | IC11: 17277.77 | ID11: 39885.18 | IE11: 4335.41 | IF11: 14474.53 | IG11: 29472.19 | IH11: 13192.44 | II11: 46731.91 | IJ11: 6987.4 | IK11: 39971.02 | IL11: 25643.46 | IM11: 37641.37 | IN11: 15880.41 | IO11: 25967.24 | IP11: 42913.35 | IQ11: 23610.47 | IR11: 18306.13 | IS11: 27039.69 | IT11: 36009.46 | IU11: 22456.39 | IV11: 46974.41 | IW11: 15099.82 | IX11: 24035.45 | IY11: 37967.92 | IZ11: 34611.49 | JA11: 43250.23 | JB11: 49842.05 | JC11: 21629.49 | JD11: 6001.97 | JE11: 2005.59 | JF11: 36480.41 | JG11: 43763.68 | JH11: 11425.27 | JI11: 8343.18 | JJ11: 3579.15 | JK11: 41223.79 | JL11: 15913.41 | JM11: 20384 | JN11: 25386.13 | JO11: 42052.94 | JP11: 32716.24 | JQ11: 30945.7 | JR11: 9195.77 | JS11: 25902.9 | JT11: 35911.36 | JU11: 48676.41 | JV11: 10469.61 | JW11: 972.4 | JX11: 4227.42 | JY11: 19104.7 | JZ11: 41116.96 | KA11: 853.53 | KB11: 23108.16 | KC11: 16796.92 | KD11: 3097.84 | KE11: 22786.7 | KF11: 13110.06 | KG11: 17918.3 | KH11: 35427.96 | KI11: 26316.77 | KJ11: 6670.05 | KK11: 48090.02 | KL11: 31977.58 | KM11: 38410.49 | KN11: 4421.05 | KO11: 2829.39 | KP11: 1462.68 | KQ11: 9845.3 | KR11: 21013.22 | KS11: 46823.39 | KT11: 23124.45 | KU11: 14867.63 | KV11: 28315.8 | KW11: 6040.76 | KX11: 30670.54 | KY11: 28637.38 | KZ11: 39703.66 | LA11: 49341.04 | LB11: 12918.24 | LC11: 25727.99 | LD11: 45488.84 | LE11: 39366.9 | LF11: 24626.61 | LG11: 47295.9 | LH11: 3333.22 | LI11: 46584.43 | LJ11: 3000.12 | LK11: 27591.58 | LL11: 44576.83 | LM11: 13504.69 | LN11: 23876.3 | LO11: 16554.28 | LP11: 47631.12 | LQ11: 41270.46 | LR11: 35595.57 | LS11: 29587.54 | LT11: 41119.29 | LU11: 19917.22 | LV11: 22653.82 | LW11: 36635.09 | LX11: 18208.86 | LY11: 3663.1 | LZ11: 4179.56 | MA11: 6210.46 | MB11: 43549.23 | MC11: 23875.21 | MD11: 35787.68 | ME11: 19949.01 | MF11: 13306.19 | MG11: 17686.01 | MH11: 39812.03 | MI11: 31448.2 | MJ11: 46913.17 | MK11: 34145.39 | ML11: 28723.99 | MM11: 30704.7 | MN11: 47147.39 | MO11: 39515.95 | MP11: 1690.04 | MQ11: 26939.91 | MR11: 34572.75 | MS11: 37560.57 | MT11: 11050.53 | MU11: 43425.28 | MV11: 47814.24 | MW11: 12217.41 | MX11: 44189.47 | MY11: 5300.45 | MZ11: 3257.49 | NA11: 6896.58 | NB11: 3358.18 | NC11: 42328.11 | ND11: 3422.98 | NE11: 13947.38 | NF11: 5635.94 | NG11: 15123.39 | NH11: 4982.69 | NI11: 33566.16 | NJ11: 7099.68 | NK11: 42666.37 | NL11: 40950.96 | NM11: 1176.25 | NN11: 44838.45 | NO11: 1932.74 | NP11: 12362.47 | NQ11: 2103.26 | NR11: 17124.25 | NS11: 25936.39 | NT11: 39933.92 | NU11: 17230.09 | NV11: 35421.76 | NW11: 9781.47 | NX11: 37654.62 | NY11: 12181.83 | NZ11: 7605.47 | OA11: 9677.74 | OB11: 9512.12 | OC11: 25886.71 | OD11: 42317.48 | OE11: 4440.45 | OF11: 35494.34 | OG11: 32890.15 | OH11: 43689.74 | OI11: 12585.3 | OJ11: 22780.44 | OK11: 46328.46 | OL11: 33169.68 | OM11: 19744.04 | ON11: 7004.91 | OO11: 13493.01 | OP11: 29270.17 | OQ11: 36049.31 | OR11: 6658.88 | OS11: 30180.06 | OT11: 27742.39 | OU11: 25940.79 | OV11: 34661.09 | OW11: 41953.75 | OX11: 16487.99 | OY11: 44506.1 | OZ11: 8451.36 | PA11: 9064.68 | PB11: 13705.22 | PC11: 6416.78 | PD11: 11900.8 | PE11: 5767.38 | PF11: 41176.74 | PG11: 7378.97 | PH11: 37491.23 | PI11: 2871.74 | PJ11: 47451.76 | PK11: 35702.42 | PL11: 836.43 | PM11: 38310.9 | PN11: 25947.06 | PO11: 39078.58 | PP11: 26363.59 | PQ11: 32230.73 | PR11: 39423.42 | PS11: 20552.85 | PT11: 634.05 | PU11: 42572.35 | PV11: 19354.07 | PW11: 25054.11 | PX11: 884.45 | PY11: 24858.55 | PZ11: 49331.13 | QA11: 14274.25 | QB11: 20073.2 | QC11: 34515.9 | QD11: 40832.29 | QE11: 21160.89 | QF11: 15828.61 | QG11: 46922.38 | QH11: 34018.68 | QI11: 6391.55 | QJ11: 3911.93 | QK11: 24435.72 | QL11: 11394.46 | QM11: 13072.25 | QN11: 43945.76 | QO11: 4933.52 | QP11: 35910.52 | QQ11: 13921.54 | QR11: 38136.25 | QS11: 36259.36 | QT11: 865.9 | QU11: 25702.2 | QV11: 7396.31 | QW11: 43378.24 | QX11: 43643.5 | QY11: 21208.12 | QZ11: 22497.58 | RA11: 15512.51 | RB11: 35972.01 | RC11: 18253.74 | RD11: 13755.73 | RE11: 21895.44 | RF11: 5028.63 | RG11: 37456.86 | RH11: 1123.52 | RI11: 32402.01 | RJ11: 9551.79 | RK11: 12004 | RL11: 31963.78 | RM11: 49650.7 | RN11: 38997.02 | RO11: 11679.06 | RP11: 9213.23 | RQ11: 43378.53 | RR11: 22487.11 | RS11: 7284.11 | RT11: 43179.47 | RU11: 40896.57 | RV11: 49203.37 | RW11: 45532.31 | RX11: 42663.62 | RY11: 3102.43 | RZ11: 5668.56 | SA11: 28664.67 | SB11: 26808.22 | SC11: 23169.18 | SD11: 20141.07 | SE11: 21844.92 | SF11: 28680.25 | SG11: 602.79 | SH11: 13405.08 | SI11: 26154.85 | SJ11: 36249.7 | SK11: 9120.76 | SL11: 27570.62 | SM11: 35865.75 | SN11: 22509.07 | SO11: 1840.52 | SP11: 22738.77 | SQ11: 15174.02 | SR11: 46517.66 | SS11: 6668.36 | ST11: 32797.56 | SU11: 3109.63 | SV11: 22585.44 | SW11: 27921.98 | SX11: 15248.77 | SY11: 23026.24 | SZ11: 8595.91 | TA11: 15554.13 | TB11: 31244.76 | TC11: 15439.1 | TD11: 45037.28 | TE11: 31606.14 | TF11: 22213.13 | TG11: 2418.47 | TH11: 25227.64 | TI11: 38356.42 | TJ11: 13645.1 | TK11: 40435.29 | TL11: 12964.43 | TM11: 41275.45 | TN11: 4720.78 | TO11: 43376.09 | TP11: 25209.73 | TQ11: 15178.61 | TR11: 13623.11 | TS11: 21884.52 | TT11: 49952.95 | TU11: 11406.21 | TV11: 5609.22 | TW11: 29459.24 | TX11: 24682.85 | TY11: 26447.72 | TZ11: 33513.3 | UA11: 13723.63 | UB11: 45577.92 | UC11: 22065.77 | UD11: 6889.77 | UE11: 37243.79 | UF11: 32333.67 | UG11: 16129.3 | UH11: 31265.18 | UI11: 11383.17 | UJ11: 22519.55 | UK11: 45020.92 | UL11: 7109.94 | UM11: 19641.47 | UN11: 41146.55 | UO11: 48489.8 | UP11: 22969.34 | UQ11: 25596.48 | UR11: 28822.51 | US11: 46651.23 | UT11: 42981.24 | UU11: 8944.76 | UV11: 22119.51 | UW11: 23468.02 | UX11: 39560.26 | UY11: 30343.2 | UZ11: 32883.91 | VA11: 49910.9 | VB11: 4210.52 | VC11: 11538.99 | VD11: 20690.85 | VE11: 17715.23 | VF11: 1571.46 | VG11: 5042.99 | VH11: 34207.19 | VI11: 44026.56 | VJ11: 25954.24 | VK11: 27189.96 | VL11: 13127.12 | VM11: 38509.88 | VN11: 37713.83 | VO11: 29624.1 | VP11: 11026.88 | VQ11: 5302.4 | VR11: 3679.81 | VS11: 29838.46 | VT11: 41339.25 | VU11: 42987.36 | VV11: 23449.29 | VW11: 39321.43 | VX11: 47370.57 | VY11: 14120.92 | VZ11: 20199.04 | WA11: 46608.21 | WB11: 17242.43 | WC11: 45736.88 | WD11: 49061.72 | WE11: 33259.63 | WF11: 40936.07 | WG11: 37602.51 | WH11: 35126.95 | WI11: 15693.09 | WJ11: 3326.17 | WK11: 17481.06 | WL11: 33513.33 | WM11: 5575.2 | WN11: 1089.94 | WO11: 7414.77 | WP11: 35928.93 | WQ11: 48653.29 | WR11: 49161.7 | WS11: 24951.97 | WT11: 43532.94 | WU11: 36972.91 | WV11: 25301.49 | WW11: 28851.65 | WX11: 7292.74 | WY11: 46914.24 | WZ11: 17920.52 | XA11: 22584.39 | XB11: 33747.18 | XC11: 17028.17 | XD11: 13085.83 | XE11: 31736.94 | XF11: 1736.71 | XG11: 36175.89 | XH11: 25944.16 | XI11: 30484.81 | XJ11: 31778.07 | XK11: 26588.98 | XL11: 29335.42 | XM11: 34347.52 | XN11: 37779.38 | XO11: 36508.89 | XP11: 43546.01 | XQ11: 9877.45 | XR11: 20356.82 | XS11: 47415.91 | XT11: 20131.23 | XU11: 6681.07 | XV11: 26509.53 | XW11: 5919.8 | XX11: 10541.24 | XY11: 49916.78 | XZ11: 27297.45 | YA11: 14560.89 | YB11: 49741.36 | YC11: 48344.67 | YD11: 22316.58 | YE11: 13389.95 | YF11: 42000.78 | YG11: 35923.23 | YH11: 34503.6 | YI11: 44709.13 | YJ11: 34626.15 | YK11: 14548 | YL11: 34846.23 | YM11: 15637.77 | YN11: 38082.33 | YO11: 31177.52 | YP11: 4331.87 | YQ11: 25885.35 | YR11: 17493.4 | YS11: 16764.25 | YT11: 30311.69 | YU11: 16455.08 | YV11: 38956.24 | YW11: 4004.18 | YX11: 33189.22 | YY11: 40555.14 | YZ11: 33805.17 | ZA11: 25112.85 | ZB11: 47540.2 | ZC11: 15346.96 | ZD11: 1448.81 | ZE11: 21883.47 | ZF11: 2134.09 | ZG11: 47719.87 | ZH11: 10890.94 | ZI11: 39551.89 | ZJ11: 38841.32 | ZK11: 11277.58 | ZL11: 31250.71 | ZM11: 2879.91 | ZN11: 24436.94 | ZO11: 1225.03 | ZP11: 46096.62 | ZQ11: 48816.26 | ZR11: 11503 | ZS11: 10801.25 | ZT11: 37809.15 | ZU11: 13042.28 | ZV11: 44806.29 | ZW11: 28909.49 | ZX11: 17863.49 | ZY11: 41718.34 | ZZ11: 24923.63 | AAA11: 45625.83 | AAB11: 46436.7 | AAC11: 8688.3 | AAD11: 615.01 | AAE11: 49204.58 | AAF11: 45353.81 | AAG11: 3244.54 | AAH11: 41735.2 | AAI11: 23161.34 | AAJ11: 13318.6 | AAK11: 43997.95 | AAL11: 10235.03 | AAM11: 47391.35 | AAN11: 10678.26 | AAO11: 30877.32 | AAP11: 11542.77 | AAQ11: 27510.6 | AAR11: 34356.77 | AAS11: 9916.28 | AAT11: 26283.85 | AAU11: 23718.46 | AAV11: 4016.35 | AAW11: 41006.24 | AAX11: 17116.28 | AAY11: 28941.82 | AAZ11: 25981.82 | ABA11: 25906.39 | ABB11: 5807.51 | ABC11: 21462.36 | ABD11: 22892.15 | ABE11: 36815.32 | ABF11: 42080.93 | ABG11: 27476.62 | ABH11: 4795.76 | ABI11: 12224.05 | ABJ11: 8664.23 | ABK11: 6668.45 | ABL11: 18612.02 | ABM11: 11854.98 | ABN11: 11306 | ABO11: 3207.31 | ABP11: 1374.67 | ABQ11: 5587.03 | ABR11: 9023.78 | ABS11: 21833.69 | ABT11: 25770.75 | ABU11: 7459.3 | ABV11: 21526.78 | ABW11: 17416.57 | ABX11: 9579.47 | ABY11: 838.62 | ABZ11: 23617.38 | ACA11: 34439.76 | ACB11: 11700.73 | ACC11: 7024.44 | ACD11: 44408.62 | ACE11: 14113.73 | ACF11: 11568.82 | ACG11: 42926.3 | ACH11: 40946.8 | ACI11: 22693.15 | ACJ11: 24717.32 | ACK11: 11278.56 | ACL11: 4375.93 | ACM11: 28884.88 | ACN11: 5368.07 | ACO11: 22739.09 | ACP11: 47054.61 | ACQ11: 47665.3 | ACR11: 12346.95 | ACS11: 31393.61 | ACT11: 23966.78 | ACU11: 43846.41 | ACV11: 13935.83 | ACW11: 683.27 | ACX11: 8546.78 | ACY11: 17801.38 | ACZ11: 16128.2 | ADA11: 39672.46 | ADB11: 34187.75 | ADC11: 15328.04 | ADD11: 23158.32 | ADE11: 5230.18 | ADF11: 44958.25 | ADG11: 46803.53 | ADH11: 49000.28 | ADI11: 43493.37 | ADJ11: 9111.06 | ADK11: 2786.73 | ADL11: 29190.04 | ADM11: 45673.95 | ADN11: 9278.89 | ADO11: 848.62 | ADP11: 40372.05 | ADQ11: 4301.39 | ADR11: 20978.45 | ADS11: 34104.92 | ADT11: 12221.48 | ADU11: 4656.15 | ADV11: 38616.05 | ADW11: 31693.67 | ADX11: 49430.28 | ADY11: 17543.25 | ADZ11: 3557.24 | AEA11: 36850.33 | AEB11: 26325.8 | AEC11: 11053.59 | AED11: 39195.58 | AEE11: 10585.9 | AEF11: 13402.75 | AEG11: 5080.16 | AEH11: 20271.9 | AEI11: 21237 | AEJ11: 25970.81 | AEK11: 35593.73 | AEL11: 45352 | AEM11: 7317.84 | AEN11: 3190.23 | AEO11: 1417.3 | AEP11: 7609.26 | AEQ11: 33068.5 | AER11: 36510.12 | AES11: 39432.03 | AET11: 12563.56 | AEU11: 15641.79 | AEV11: 24415.16 | AEW11: 3627.56 | AEX11: 30751.51 | AEY11: 49194.88 | AEZ11: 18359.91 | AFA11: 37765.95 | AFB11: 25251.68 | AFC11: 6826.69 | AFD11: 29320.75 | AFE11: 15343.78 | AFF11: 2202.96 | AFG11: 31929.02 | AFH11: 43017.15 | AFI11: 17566.1 | AFJ11: 19819.63 | AFK11: 44605.57 | AFL11: 40773.64 | AFM11: 35890.16 | AFN11: 12815.45 | AFO11: 45555.72 | AFP11: 8143.58 | AFQ11: 31525.14 | AFR11: 1925.66 | AFS11: 32364.13 | AFT11: 14218.65 | AFU11: 22759.01 | AFV11: 17590.6 | AFW11: 9051.46 | AFX11: 31288.05 | AFY11: 44157.79 | AFZ11: 47974.67 | AGA11: 10021.14 | AGB11: 36009.95 | AGC11: 33384.8 | AGD11: 17497.2 | AGE11: 1445.41 | AGF11: 34644.67 | AGG11: 47302 | AGH11: 31789.95 | AGI11: 22046.99 | AGJ11: 26495.12 | AGK11: 10381.63 | AGL11: 37651.94 | AGM11: 37447.78 | AGN11: 7703.11 | AGO11: 43959.93 | AGP11: 13824.89 | AGQ11: 49121.68 | AGR11: 19453.7 | AGS11: 9305.26 | AGT11: 17910.15 | AGU11: 22288.93 | AGV11: 3930.73 | AGW11: 29121.81 | AGX11: 30082.81 | AGY11: 37077.06 | AGZ11: 1943.91 | AHA11: 27291.29 | AHB11: 3118.92 | AHC11: 35206.64 | AHD11: 3258.54 | AHE11: 45630.53 | AHF11: 35253.09 | AHG11: 25615.79 | AHH11: 22354.44 | AHI11: 6968.3 | AHJ11: 14904.47 | AHK11: 43513.48 | AHL11: 45270.41 | AHM11: 537.01 | AHN11: 29909.75 | AHO11: 36105.38 | AHP11: 31127.98 | AHQ11: 4543.15 | AHR11: 11277.38 | AHS11: 12891.84 | AHT11: 41670.37 | AHU11: 23428.37 | AHV11: 24598 | AHW11: 46777.21 | AHX11: 32035.75 | AHY11: 44984.05 | AHZ11: 23097.19 | AIA11: 7897.09 | AIB11: 46531.81 | AIC11: 23205.9 | AID11: 9490.76 | AIE11: 15468.59 | AIF11: 3014.73 | AIG11: 23680.88 | AIH11: 42729.84 | AII11: 46712.23 | AIJ11: 46663.81 | AIK11: 6698.89 | AIL11: 19411.67 | AIM11: 1897.32 | AIN11: 42830.68 | AIO11: 18258.41 | AIP11: 31740.29 | AIQ11: 35887.47 | AIR11: 21777.31 | AIS11: 15668.9 | AIT11: 48129.54 | AIU11: 48242.17 | AIV11: 14827.1 | AIW11: 24241.44 | AIX11: 48655.79 | AIY11: 740.99 | AIZ11: 20927.57 | AJA11: 5472.65 | AJB11: 25703.32 | AJC11: 1721.16 | AJD11: 20641.47 | AJE11: 11424.6 | AJF11: 26898.76 | AJG11: 49801.69 | AJH11: 40126.54 | AJI11: 42359.28 | AJJ11: 31945.62 | AJK11: 2557.21 | AJL11: 10736.48 | AJM11: 46290.7 | AJN11: 18622.6 | AJO11: 5630.02 | AJP11: 35269.07 | AJQ11: 15323.16 | AJR11: 13808.42 | AJS11: 49899.88 | AJT11: 42977.88 | AJU11: 20692.92 | AJV11: 49022.93 | AJW11: 32680.6 | AJX11: 37230.11 | AJY11: 2059.9 | AJZ11: 6519.46 | AKA11: 31837.71 | AKB11: 45001.69 | AKC11: 31375.31 | AKD11: 7134.23 | AKE11: 6230.12 | AKF11: 42287.2 | AKG11: 7395.47 | AKH11: 26251.48 | AKI11: 2337.11 | AKJ11: 4493.15 | AKK11: 33781.24 | AKL11: 34614.48 | AKM11: 17402.74 | AKN11: 11172.68 | AKO11: 40778.66 | AKP11: 11246.61 | AKQ11: 27330.34 | AKR11: 48426.34 | AKS11: 7818.7 | AKT11: 47073.38 | AKU11: 9553.21 | AKV11: 28588.44 | AKW11: 19161.88 | AKX11: 48263.97 | AKY11: 14040.33 | AKZ11: 20283.07 | ALA11: 49151.58 | ALB11: 27055.28 | ALC11: 25380.19 | ALD11: 13260.04 | ALE11: 35217.5 | ALF11: 1211.46 | ALG11: 2950.88 | ALH11: 30168.25 | ALI11: 17412.89 | ALJ11: 47689.16 | ALK11: 45207.94 | ALL11: 35828.46 | ALM11: 40998.21
A12: Processing Fee | B12: 350.3 | C12: 106.51 | D12: 394.49 | E12: 144.59 | F12: 195.55 | G12: 418.66 | H12: 291.44 | I12: 436.97 | J12: 145.87 | K12: 323.5 | L12: 87.71 | M12: 339.38 | N12: 393.14 | O12: 313.22 | P12: 169.8 | Q12: 64.1 | R12: 103.75 | S12: 330.04 | T12: 470.49 | U12: 142.94 | V12: 380.76 | W12: 439.9 | X12: 284.4 | Y12: 351.17 | Z12: 416.76 | AA12: 167.3 | AB12: 183.6 | AC12: 50.28 | AD12: 483.39 | AE12: 462.9 | AF12: 394.06 | AG12: 85.58 | AH12: 251.38 | AI12: 95.85 | AJ12: 57.16 | AK12: 327.28 | AL12: 482.37 | AM12: 456.29 | AN12: 363.54 | AO12: 93.49 | AP12: 173.37 | AQ12: 194.03 | AR12: 393.42 | AS12: 411.01 | AT12: 223.3 | AU12: 238.05 | AV12: 70.03 | AW12: 180.11 | AX12: 253.08 | AY12: 102.64 | AZ12: 253.97 | BA12: 433.93 | BB12: 311.59 | BC12: 85.52 | BD12: 136.25 | BE12: 263.54 | BF12: 212.67 | BG12: 211.43 | BH12: 288.17 | BI12: 312.98 | BJ12: 408.59 | BK12: 203.43 | BL12: 412.46 | BM12: 202.38 | BN12: 74.94 | BO12: 299.38 | BP12: 314.56 | BQ12: 470.54 | BR12: 376.73 | BS12: 463 | BT12: 458.76 | BU12: 322.06 | BV12: 287.49 | BW12: 300.85 | BX12: 490.25 | BY12: 397.93 | BZ12: 97.82 | CA12: 400.29 | CB12: 126.74 | CC12: 251.31 | CD12: 144.71 | CE12: 360.31 | CF12: 444.79 | CG12: 180.66 | CH12: 86.9 | CI12: 184.32 | CJ12: 352.56 | CK12: 197.94 | CL12: 175.15 | CM12: 133 | CN12: 273.88 | CO12: 174.18 | CP12: 378.95 | CQ12: 84.48 | CR12: 348.81 | CS12: 156.9 | CT12: 270.18 | CU12: 178.74 | CV12: 375.25 | CW12: 475.39 | CX12: 462.68 | CY12: 312.54 | CZ12: 258.17 | DA12: 418.24 | DB12: 357.5 | DC12: 132.6 | DD12: 419.41 | DE12: 243 | DF12: 135.04 | DG12: 176.81 | DH12: 170.39 | DI12: 283.64 | DJ12: 155.47 | DK12: 105.6 | DL12: 105.66 | DM12: 312.47 | DN12: 380.64 | DO12: 194.69 | DP12: 65.59 | DQ12: 107.25 | DR12: 461.61 | DS12: 272.09 | DT12: 254.11 | DU12: 67.12 | DV12: 377.89 | DW12: 287.63 | DX12: 140.94 | DY12: 99.53 | DZ12: 222.52 | EA12: 426.72 | EB12: 439.38 | EC12: 321.28 | ED12: 377.39 | EE12: 101.82 | EF12: 314.66 | EG12: 350.13 | EH12: 140.32 | EI12: 446.07 | EJ12: 137.75 | EK12: 191.06 | EL12: 329.25 | EM12: 337.26 | EN12: 364.72 | EO12: 100.41 | EP12: 432.26 | EQ12: 289.78 | ER12: 262.09 | ES12: 491.49 | ET12: 383.17 | EU12: 103.1 | EV12: 390.44 | EW12: 92.86 | EX12: 62.36 | EY12: 231.63 | EZ12: 497.11 | FA12: 128.7 | FB12: 352.69 | FC12: 128.03 | FD12: 376.15 | FE12: 277.41 | FF12: 355.99 | FG12: 141.29 | FH12: 385.53 | FI12: 498.03 | FJ12: 349.54 | FK12: 272.07 | FL12: 465.43 | FM12: 57.13 | FN12: 378.47 | FO12: 449.94 | FP12: 77.75 | FQ12: 252.53 | FR12: 142.12 | FS12: 304.93 | FT12: 342.29 | FU12: 186.18 | FV12: 256.99 | FW12: 175.7 | FX12: 216.23 | FY12: 121.79 | FZ12: 448.5 | GA12: 54.5 | GB12: 447.08 | GC12: 307.26 | GD12: 199.25 | GE12: 375.38 | GF12: 278.49 | GG12: 274.6 | GH12: 99.56 | GI12: 225.28 | GJ12: 158.48 | GK12: 57.06 | GL12: 212.04 | GM12: 90.42 | GN12: 165.57 | GO12: 91.63 | GP12: 95.42 | GQ12: 139.56 | GR12: 499.93 | GS12: 50.98 | GT12: 337.4 | GU12: 113.56 | GV12: 464.28 | GW12: 92.13 | GX12: 479.78 | GY12: 324.92 | GZ12: 50.57 | HA12: 452.3 | HB12: 284.77 | HC12: 168.2 | HD12: 395.28 | HE12: 467 | HF12: 267.66 | HG12: 192 | HH12: 405.03 | HI12: 356.8 | HJ12: 449.94 | HK12: 361.63 | HL12: 159.59 | HM12: 469.25 | HN12: 97.18 | HO12: 170.57 | HP12: 284.09 | HQ12: 304.58 | HR12: 56.89 | HS12: 401.26 | HT12: 212.72 | HU12: 232.89 | HV12: 414.22 | HW12: 220.68 | HX12: 71.25 | HY12: 129.4 | HZ12: 480.16 | IA12: 81.68 | IB12: 209.72 | IC12: 276.43 | ID12: 271.98 | IE12: 51.78 | IF12: 275.52 | IG12: 222.7 | IH12: 487.44 | II12: 121.62 | IJ12: 209.37 | IK12: 238.77 | IL12: 225.81 | IM12: 349.62 | IN12: 146.98 | IO12: 149.48 | IP12: 378.14 | IQ12: 275.13 | IR12: 236.82 | IS12: 126.14 | IT12: 134.39 | IU12: 54.75 | IV12: 91.14 | IW12: 300.58 | IX12: 451.34 | IY12: 179.22 | IZ12: 197.49 | JA12: 102.02 | JB12: 224.88 | JC12: 66.75 | JD12: 462.92 | JE12: 352.9 | JF12: 495.84 | JG12: 447.27 | JH12: 262.85 | JI12: 283.86 | JJ12: 135.76 | JK12: 257.92 | JL12: 456.36 | JM12: 72.88 | JN12: 438.6 | JO12: 203.43 | JP12: 454.78 | JQ12: 473.4 | JR12: 351.89 | JS12: 348.99 | JT12: 253.74 | JU12: 425.99 | JV12: 482.73 | JW12: 398.79 | JX12: 329.87 | JY12: 323.06 | JZ12: 432.26 | KA12: 293.54 | KB12: 411.74 | KC12: 279 | KD12: 78.1 | KE12: 222.78 | KF12: 250 | KG12: 113.73 | KH12: 96.12 | KI12: 290.96 | KJ12: 88.31 | KK12: 186.33 | KL12: 385.07 | KM12: 483.99 | KN12: 373.04 | KO12: 496.68 | KP12: 364.25 | KQ12: 182.21 | KR12: 352.42 | KS12: 365.97 | KT12: 217.28 | KU12: 57.97 | KV12: 366.44 | KW12: 59.77 | KX12: 334.03 | KY12: 123.63 | KZ12: 304.52 | LA12: 276.76 | LB12: 56.08 | LC12: 213.29 | LD12: 320.49 | LE12: 431.87 | LF12: 449.89 | LG12: 267.73 | LH12: 377.79 | LI12: 192.4 | LJ12: 203.98 | LK12: 137.51 | LL12: 302.88 | LM12: 191.55 | LN12: 87.97 | LO12: 358.25 | LP12: 368.49 | LQ12: 212 | LR12: 84.53 | LS12: 241.83 | LT12: 249.05 | LU12: 350.9 | LV12: 191.94 | LW12: 357.17 | LX12: 442.17 | LY12: 156.87 | LZ12: 490.51 | MA12: 223.87 | MB12: 170.27 | MC12: 239.68 | MD12: 92.48 | ME12: 106.57 | MF12: 236.5 | MG12: 393.1 | MH12: 455.14 | MI12: 349.17 | MJ12: 97.35 | MK12: 352.41 | ML12: 335.94 | MM12: 412.59 | MN12: 421.36 | MO12: 440.69 | MP12: 236.36 | MQ12: 364.04 | MR12: 170.71 | MS12: 499.7 | MT12: 128.9 | MU12: 54.55 | MV12: 116.96 | MW12: 399.14 | MX12: 251.05 | MY12: 251.38 | MZ12: 479.76 | NA12: 463.84 | NB12: 190.04 | NC12: 144.08 | ND12: 431.82 | NE12: 457.71 | NF12: 293.72 | NG12: 333.24 | NH12: 165.61 | NI12: 410.36 | NJ12: 334.46 | NK12: 276.58 | NL12: 77.05 | NM12: 462.17 | NN12: 326.95 | NO12: 136.71 | NP12: 322.87 | NQ12: 354.86 | NR12: 286.6 | NS12: 373.15 | NT12: 311.65 | NU12: 476.5 | NV12: 74.16 | NW12: 97.81 | NX12: 128.15 | NY12: 360.58 | NZ12: 340.52 | OA12: 451.43 | OB12: 379.79 | OC12: 278.76 | OD12: 496.32 | OE12: 169.75 | OF12: 424.94 | OG12: 242.06 | OH12: 341.93 | OI12: 377.27 | OJ12: 335.19 | OK12: 113.23 | OL12: 249.33 | OM12: 302.65 | ON12: 432.07 | OO12: 249.64 | OP12: 463.44 | OQ12: 248.17 | OR12: 296.95 | OS12: 408.33 | OT12: 312.38 | OU12: 482.1 | OV12: 347.15 | OW12: 285.22 | OX12: 60.62 | OY12: 236.18 | OZ12: 184.66 | PA12: 386.65 | PB12: 143.72 | PC12: 142.35 | PD12: 135.28 | PE12: 106.53 | PF12: 189.95 | PG12: 448.66 | PH12: 398.72 | PI12: 380.86 | PJ12: 408.8 | PK12: 171.24 | PL12: 449.35 | PM12: 111.79 | PN12: 201.36 | PO12: 314.04 | PP12: 96.31 | PQ12: 378.56 | PR12: 224.26 | PS12: 402.98 | PT12: 271.8 | PU12: 131.39 | PV12: 380.64 | PW12: 163.46 | PX12: 270.86 | PY12: 83.99 | PZ12: 328.04 | QA12: 349.64 | QB12: 220.4 | QC12: 479.49 | QD12: 443.38 | QE12: 368.57 | QF12: 371.14 | QG12: 163.58 | QH12: 345.57 | QI12: 139.19 | QJ12: 114.8 | QK12: 499.76 | QL12: 330.07 | QM12: 243.94 | QN12: 179.67 | QO12: 321.76 | QP12: 72.32 | QQ12: 92.61 | QR12: 64.79 | QS12: 274.63 | QT12: 320.27 | QU12: 78.12 | QV12: 374.55 | QW12: 153.68 | QX12: 358.34 | QY12: 491.85 | QZ12: 361 | RA12: 447.44 | RB12: 476.69 | RC12: 269.04 | RD12: 366.05 | RE12: 433.39 | RF12: 210.47 | RG12: 167.63 | RH12: 475.97 | RI12: 376.84 | RJ12: 148.86 | RK12: 252.09 | RL12: 408.4 | RM12: 296.18 | RN12: 342.48 | RO12: 389.2 | RP12: 329.9 | RQ12: 293.04 | RR12: 387.33 | RS12: 377.4 | RT12: 333.44 | RU12: 211.91 | RV12: 232.62 | RW12: 486.7 | RX12: 100.57 | RY12: 170.83 | RZ12: 271.58 | SA12: 426.53 | SB12: 123.65 | SC12: 174.63 | SD12: 79.61 | SE12: 367.69 | SF12: 157.19 | SG12: 224.9 | SH12: 249.67 | SI12: 451.09 | SJ12: 235.1 | SK12: 115.35 | SL12: 285.94 | SM12: 483.33 | SN12: 323.46 | SO12: 492.52 | SP12: 428.5 | SQ12: 66.18 | SR12: 346.28 | SS12: 179.05 | ST12: 301.83 | SU12: 175.71 | SV12: 206.99 | SW12: 465.43 | SX12: 142.99 | SY12: 443.35 | SZ12: 63.71 | TA12: 90.89 | TB12: 434.6 | TC12: 333.75 | TD12: 386.26 | TE12: 144.24 | TF12: 291.69 | TG12: 381.75 | TH12: 332.29 | TI12: 262.26 | TJ12: 481.9 | TK12: 354.27 | TL12: 458.49 | TM12: 378.4 | TN12: 380.96 | TO12: 86.01 | TP12: 211.76 | TQ12: 436.27 | TR12: 154.67 | TS12: 101.98 | TT12: 196.75 | TU12: 149.2 | TV12: 466.38 | TW12: 440.58 | TX12: 274.86 | TY12: 77.6 | TZ12: 371.55 | UA12: 330.54 | UB12: 486.75 | UC12: 301.53 | UD12: 201.38 | UE12: 283.56 | UF12: 490.67 | UG12: 363.36 | UH12: 352.39 | UI12: 158.31 | UJ12: 384.62 | UK12: 387.62 | UL12: 192.78 | UM12: 267.67 | UN12: 182.57 | UO12: 166.42 | UP12: 61.65 | UQ12: 178.35 | UR12: 299.29 | US12: 50.72 | UT12: 177.45 | UU12: 446.63 | UV12: 317.14 | UW12: 323.54 | UX12: 231.51 | UY12: 354.41 | UZ12: 135.47 | VA12: 418.44 | VB12: 102.51 | VC12: 345.2 | VD12: 203.52 | VE12: 386.38 | VF12: 297.39 | VG12: 253.56 | VH12: 126.24 | VI12: 336.57 | VJ12: 488.65 | VK12: 421.52 | VL12: 77 | VM12: 219.3 | VN12: 466.51 | VO12: 276.37 | VP12: 347.95 | VQ12: 460.67 | VR12: 443.21 | VS12: 275.82 | VT12: 246.94 | VU12: 202.86 | VV12: 373.56 | VW12: 179.14 | VX12: 162.45 | VY12: 210.31 | VZ12: 129.75 | WA12: 362.8 | WB12: 327.31 | WC12: 267.3 | WD12: 225.65 | WE12: 459.08 | WF12: 63.11 | WG12: 396.1 | WH12: 455.86 | WI12: 250.86 | WJ12: 297.81 | WK12: 475.01 | WL12: 145.52 | WM12: 284.06 | WN12: 263.62 | WO12: 166.28 | WP12: 418.37 | WQ12: 454.82 | WR12: 401.87 | WS12: 137.91 | WT12: 89.04 | WU12: 322.45 | WV12: 75.69 | WW12: 352.77 | WX12: 288.69 | WY12: 348.25 | WZ12: 315.58 | XA12: 240.22 | XB12: 140.39 | XC12: 187.57 | XD12: 286.03 | XE12: 343.34 | XF12: 400.77 | XG12: 395.23 | XH12: 487.71 | XI12: 178.63 | XJ12: 82 | XK12: 205.55 | XL12: 384.48 | XM12: 247.15 | XN12: 418 | XO12: 297.2 | XP12: 468.41 | XQ12: 476.54 | XR12: 81.19 | XS12: 255.39 | XT12: 324.36 | XU12: 165.14 | XV12: 233.18 | XW12: 354.96 | XX12: 152.03 | XY12: 320.89 | XZ12: 363.85 | YA12: 90.72 | YB12: 273.89 | YC12: 168.39 | YD12: 375.97 | YE12: 135.3 | YF12: 451.51 | YG12: 243.92 | YH12: 139.1 | YI12: 247.11 | YJ12: 233.93 | YK12: 243.01 | YL12: 313.5 | YM12: 284.53 | YN12: 117.4 | YO12: 79.51 | YP12: 378.24 | YQ12: 301.87 | YR12: 211.55 | YS12: 413.76 | YT12: 224.63 | YU12: 408.18 | YV12: 187.59 | YW12: 82.78 | YX12: 469.69 | YY12: 227.55 | YZ12: 406.71 | ZA12: 175.61 | ZB12: 340.86 | ZC12: 442.99 | ZD12: 68.74 | ZE12: 423.79 | ZF12: 307.1 | ZG12: 323.36 | ZH12: 285.42 | ZI12: 443.51 | ZJ12: 69.55 | ZK12: 167.46 | ZL12: 444.09 | ZM12: 388.56 | ZN12: 57.94 | ZO12: 282.65 | ZP12: 288.31 | ZQ12: 230.4 | ZR12: 183.83 | ZS12: 356.78 | ZT12: 143.51 | ZU12: 409.53 | ZV12: 411.37 | ZW12: 236.87 | ZX12: 177.6 | ZY12: 177.75 | ZZ12: 267.03 | AAA12: 373.81 | AAB12: 211.49 | AAC12: 324.52 | AAD12: 222.12 | AAE12: 187.04 | AAF12: 61.19 | AAG12: 51.76 | AAH12: 152.24 | AAI12: 232.88 | AAJ12: 433.07 | AAK12: 409.32 | AAL12: 170.22 | AAM12: 160.04 | AAN12: 152.29 | AAO12: 202.66 | AAP12: 274.19 | AAQ12: 247.4 | AAR12: 148.22 | AAS12: 108.7 | AAT12: 55.66 | AAU12: 119.28 | AAV12: 367.41 | AAW12: 159.64 | AAX12: 260.87 | AAY12: 316.09 | AAZ12: 449.08 | ABA12: 449.98 | ABB12: 385.58 | ABC12: 65.82 | ABD12: 308.78 | ABE12: 403.96 | ABF12: 57.78 | ABG12: 297.36 | ABH12: 435.99 | ABI12: 263.35 | ABJ12: 51.85 | ABK12: 54.96 | ABL12: 237.49 | ABM12: 119.75 | ABN12: 349 | ABO12: 368.96 | ABP12: 130.05 | ABQ12: 449.84 | ABR12: 248.86 | ABS12: 114.28 | ABT12: 393.91 | ABU12: 405.49 | ABV12: 337.68 | ABW12: 434.06 | ABX12: 381.82 | ABY12: 446.99 | ABZ12: 245.25 | ACA12: 386.42 | ACB12: 499.89 | ACC12: 376.22 | ACD12: 101.38 | ACE12: 283.24 | ACF12: 314.31 | ACG12: 128.39 | ACH12: 483.3 | ACI12: 129.01 | ACJ12: 129.9 | ACK12: 461.83 | ACL12: 259.34 | ACM12: 78.43 | ACN12: 319.18 | ACO12: 320.82 | ACP12: 79.03 | ACQ12: 487.64 | ACR12: 294.81 | ACS12: 301.91 | ACT12: 284.05 | ACU12: 324.83 | ACV12: 168.93 | ACW12: 179.26 | ACX12: 280.1 | ACY12: 413.01 | ACZ12: 72.44 | ADA12: 321.53 | ADB12: 413.05 | ADC12: 120.61 | ADD12: 56.76 | ADE12: 190.72 | ADF12: 314.66 | ADG12: 112.23 | ADH12: 241.76 | ADI12: 298.54 | ADJ12: 319.5 | ADK12: 173.49 | ADL12: 230.01 | ADM12: 400.25 | ADN12: 473.55 | ADO12: 437.85 | ADP12: 303.93 | ADQ12: 234.63 | ADR12: 199.83 | ADS12: 106.23 | ADT12: 97.95 | ADU12: 359.76 | ADV12: 166.91 | ADW12: 164.6 | ADX12: 499.19 | ADY12: 134.57 | ADZ12: 116.63 | AEA12: 94.41 | AEB12: 310.91 | AEC12: 332.54 | AED12: 214.35 | AEE12: 290.94 | AEF12: 404.78 | AEG12: 418.15 | AEH12: 481.06 | AEI12: 420.92 | AEJ12: 304.18 | AEK12: 130.85 | AEL12: 94.89 | AEM12: 74.53 | AEN12: 349.94 | AEO12: 413.39 | AEP12: 278.91 | AEQ12: 74.62 | AER12: 290.96 | AES12: 471.09 | AET12: 318.93 | AEU12: 414.24 | AEV12: 410.07 | AEW12: 469.46 | AEX12: 396.6 | AEY12: 386.47 | AEZ12: 155.35 | AFA12: 76.97 | AFB12: 282.92 | AFC12: 106 | AFD12: 482.99 | AFE12: 180.47 | AFF12: 433.82 | AFG12: 224.43 | AFH12: 195.44 | AFI12: 470.82 | AFJ12: 213.5 | AFK12: 225.63 | AFL12: 97.74 | AFM12: 351.7 | AFN12: 179.98 | AFO12: 313.52 | AFP12: 316.11 | AFQ12: 373.64 | AFR12: 385.36 | AFS12: 281.5 | AFT12: 198.95 | AFU12: 426.85 | AFV12: 189.44 | AFW12: 278.38 | AFX12: 230.56 | AFY12: 434.79 | AFZ12: 244.36 | AGA12: 223.74 | AGB12: 360.42 | AGC12: 321.1 | AGD12: 98.26 | AGE12: 278.68 | AGF12: 380.97 | AGG12: 496.43 | AGH12: 333.12 | AGI12: 216.63 | AGJ12: 151.77 | AGK12: 442.77 | AGL12: 416.55 | AGM12: 155.27 | AGN12: 140.28 | AGO12: 371.81 | AGP12: 191.73 | AGQ12: 187.88 | AGR12: 118.53 | AGS12: 168.79 | AGT12: 242.38 | AGU12: 379.78 | AGV12: 201.34 | AGW12: 197.87 | AGX12: 178.21 | AGY12: 265.23 | AGZ12: 131.29 | AHA12: 268.53 | AHB12: 366.88 | AHC12: 63.41 | AHD12: 54.4 | AHE12: 83.81 | AHF12: 291.05 | AHG12: 434.5 | AHH12: 52.2 | AHI12: 471.5 | AHJ12: 97.83 | AHK12: 428.89 | AHL12: 267.28 | AHM12: 346.71 | AHN12: 279.81 | AHO12: 264.67 | AHP12: 425.7 | AHQ12: 390.15 | AHR12: 267.53 | AHS12: 100.24 | AHT12: 101.93 | AHU12: 410.69 | AHV12: 288.23 | AHW12: 266.72 | AHX12: 356.26 | AHY12: 436.48 | AHZ12: 332.99 | AIA12: 393.28 | AIB12: 394.37 | AIC12: 210.32 | AID12: 173.34 | AIE12: 410.52 | AIF12: 219.73 | AIG12: 456.5 | AIH12: 81.36 | AII12: 76.2 | AIJ12: 467.15 | AIK12: 341.8 | AIL12: 220.82 | AIM12: 389.78 | AIN12: 352.55 | AIO12: 289.04 | AIP12: 94.49 | AIQ12: 415.48 | AIR12: 439.71 | AIS12: 127.48 | AIT12: 432.73 | AIU12: 445.03 | AIV12: 297.24 | AIW12: 345.28 | AIX12: 222.01 | AIY12: 176.81 | AIZ12: 374.89 | AJA12: 437.84 | AJB12: 344.33 | AJC12: 280.22 | AJD12: 121.52 | AJE12: 74.06 | AJF12: 250.56 | AJG12: 72.21 | AJH12: 306.2 | AJI12: 222.23 | AJJ12: 390.74 | AJK12: 187.54 | AJL12: 316.84 | AJM12: 291.96 | AJN12: 52.12 | AJO12: 82.58 | AJP12: 180.67 | AJQ12: 447.01 | AJR12: 116.16 | AJS12: 369.9 | AJT12: 488.01 | AJU12: 405.76 | AJV12: 159.33 | AJW12: 458.76 | AJX12: 91.9 | AJY12: 260.66 | AJZ12: 449.39 | AKA12: 338.57 | AKB12: 236.14 | AKC12: 181.77 | AKD12: 218.79 | AKE12: 279.02 | AKF12: 193.57 | AKG12: 486.04 | AKH12: 469.88 | AKI12: 441.8 | AKJ12: 239.82 | AKK12: 361.09 | AKL12: 456.27 | AKM12: 432.69 | AKN12: 236.45 | AKO12: 100.57 | AKP12: 84.03 | AKQ12: 309.68 | AKR12: 339.18 | AKS12: 432.43 | AKT12: 181.63 | AKU12: 125.36 | AKV12: 220.55 | AKW12: 209.11 | AKX12: 109.61 | AKY12: 352.53 | AKZ12: 278.91 | ALA12: 374.51 | ALB12: 208.71 | ALC12: 196.57 | ALD12: 262.66 | ALE12: 444.83 | ALF12: 68.13 | ALG12: 412.17 | ALH12: 216.04 | ALI12: 434.58 | ALJ12: 410.99 | ALK12: 206.94 | ALL12: 362.24 | ALM12: 121.83
